Workbook

Sheet Landing_Page
B2: ="PCGH Annual QMR — "&Controls!$B$8&" — FY "&Controls!$B$5 -> PCGH Annual QMR — PC Ghana — FY 2026
B3: Quarterly management reporting command centre — select the quarter on Controls; everything below updates live.
B5: Reporting period end | D5: Quarter | F5: Entity | H5: Approval status | J5: Source refresh date | L5: Version
B6: =Controls!$B$4 -> 46203 | D6: =Controls!$B$6 -> Q2 | F6: =Controls!$B$7 -> PCGH | H6: =Controls!$B$23 -> Draft | J6: =Controls!$B$26 -> 46203 | L6: =Controls!$B$25 -> v2.5
B8: KEY INDICATORS — SELECTED QUARTER (GHS '000)
B9: Income forecast FY | D9: Secured net YTD | F9: WIP YTD | H9: Fixed costs YTD | J9: Surplus FY forecast | L9: Working capital
B10: =QMR_Report!$C$29/1000 -> 18393.381 | D10: =QMR_Report!$D$29/1000 -> 14867.848 | F10: =QMR_Report!$E$29/1000 -> 8798.0185 | H10: =QMR_Report!$F$47/1000 -> 5801.7136 | J10: =QMR_Report!$C$56/1000 -> 4619.009 | L10: =IFERROR(--INDEX(Balance_Sheet!$C$34:$F$34,1,VALUE(MID(Controls!$B$6,2,1))),0)/1000 -> 5711.2079
B12: Months cost cover | D12: Data quality
B13: =IFERROR(--INDEX(Balance_Sheet!$C$36:$F$36,1,VALUE(MID(Controls!$B$6,2,1))),0) -> 5.7737739 | D13: =Checks!$B$3 -> PASS WITH REVIEW
B15: ALERTS AND DATA STATUS
B16: Failed checks | D16: =COUNTIF(Checks!$F$8:$F$41,"FAIL") -> 0
B17: Review items | D17: =COUNTIF(Checks!$F$8:$F$41,"REVIEW") -> 5
B18: Top issue 1 | D18: =IFERROR(INDEX(Checks!$A:$A,_xlfn.AGGREGATE(15,6,ROW(Checks!$F$8:$F$41)/((Checks!$F$8:$F$41="FAIL")+(Checks!$F$8:$F$41="REVIEW")>0),1)),"—") -> Project forecast exceptions
B19: Top issue 2 | D19: =IFERROR(INDEX(Checks!$A:$A,_xlfn.AGGREGATE(15,6,ROW(Checks!$F$8:$F$41)/((Checks!$F$8:$F$41="FAIL")+(Checks!$F$8:$F$41="REVIEW")>0),2)),"—") -> Commodity/Client residual (values not in lists)
B20: Top issue 3 | D20: =IFERROR(INDEX(Checks!$A:$A,_xlfn.AGGREGATE(15,6,ROW(Checks!$F$8:$F$41)/((Checks!$F$8:$F$41="FAIL")+(Checks!$F$8:$F$41="REVIEW")>0),3)),"—") -> PA ↔ TB nominal-code reconciliation (Project Activity vs Trial Balance)
B21: Quarter data loaded | D21: =Controls!$F$5&": "&Controls!$H$5 -> Q1: DATA LOADED | F21: =Controls!$F$6&": "&Controls!$H$6 -> Q2: DATA LOADED | H21: =Controls!$F$7&": "&Controls!$H$7 -> Q3: NOT LOADED | J21: =Controls!$F$8&": "&Controls!$H$8 -> Q4: NOT LOADED
B23: MANAGEMENT ACTION POINTS (open items from Mgmt_Commentary)
B24: 1. | C24: =IFERROR(INDEX(Mgmt_Commentary!$F:$F,_xlfn.AGGREGATE(15,6,ROW(Mgmt_Commentary!$I$5:$I$34)/(Mgmt_Commentary!$I$5:$I$34="Open"),1))&" ["&INDEX(Mgmt_Commentary!$G:$G,_xlfn.AGGREGATE(15,6,ROW(Mgmt_Commentary!$I$5:$I$34)/(Mgmt_Commentary!$I$5:$I$34="Open"),1))&" — due "&INDEX(Mgmt_Commentary!$H:$H,_xlfn.AGGREGATE(15,6,ROW(Mgmt_Commentary!$I$5:$I$34)/(Mgmt_Commentary!$I$5:$I$34="Open"),1))&"]","—") -> Confirm monthly phasing with budget holders; replace even phasing if a profile is approved [Finance — due 2026-08-15]
B25: 2. | C25: =IFERROR(INDEX(Mgmt_Commentary!$F:$F,_xlfn.AGGREGATE(15,6,ROW(Mgmt_Commentary!$I$5:$I$34)/(Mgmt_Commentary!$I$5:$I$34="Open"),2))&" ["&INDEX(Mgmt_Commentary!$G:$G,_xlfn.AGGREGATE(15,6,ROW(Mgmt_Commentary!$I$5:$I$34)/(Mgmt_Commentary!$I$5:$I$34="Open"),2))&" — due "&INDEX(Mgmt_Commentary!$H:$H,_xlfn.AGGREGATE(15,6,ROW(Mgmt_Commentary!$I$5:$I$34)/(Mgmt_Commentary!$I$5:$I$34="Open"),2))&"]","—") -> PM to true-up gross forecast in MM_Income for completed projects [Project Leads — due 2026-07-31]
B26: 3. | C26: =IFERROR(INDEX(Mgmt_Commentary!$F:$F,_xlfn.AGGREGATE(15,6,ROW(Mgmt_Commentary!$I$5:$I$34)/(Mgmt_Commentary!$I$5:$I$34="Open"),3))&" ["&INDEX(Mgmt_Commentary!$G:$G,_xlfn.AGGREGATE(15,6,ROW(Mgmt_Commentary!$I$5:$I$34)/(Mgmt_Commentary!$I$5:$I$34="Open"),3))&" — due "&INDEX(Mgmt_Commentary!$H:$H,_xlfn.AGGREGATE(15,6,ROW(Mgmt_Commentary!$I$5:$I$34)/(Mgmt_Commentary!$I$5:$I$34="Open"),3))&"]","—") -> Provide portfolio split on QMR_Inputs block 1 [Finance Lead — due 2026-07-31]
B28: NAVIGATION
B29: DASHBOARDS | E29: REPORTS | H29: DATA INPUTS | K29: MAPPINGS & GOVERNANCE
B30: =HYPERLINK("#'QMR_Dashboard'!A1","QMR Dashboard") -> QMR Dashboard | E30: =HYPERLINK("#'QMR_Report'!A1","QMR Report") -> QMR Report | H30: =HYPERLINK("#'Controls'!A1","Controls") -> Controls | K30: =HYPERLINK("#'MM_Income'!A1","MM Income") -> MM Income
B31: =HYPERLINK("#'Project_Output'!A1","Project Income") -> Project Income | E31: =HYPERLINK("#'Slide_Pack'!A1","Slide Pack") -> Slide Pack | H31: =HYPERLINK("#'Project_Activity'!A1","Project Activity") -> Project Activity | K31: =HYPERLINK("#'MM_FixedCost'!A1","MM Fixed Cost") -> MM Fixed Cost
B32: =HYPERLINK("#'FixedCost_Output'!A1","Fixed Costs") -> Fixed Costs | E32: =HYPERLINK("#'FC_Budget_Vrs_Actual'!A1","FC Budget Vrs Actual") -> FC Budget Vrs Actual | H32: =HYPERLINK("#'Project_Forecast'!A1","Project Forecast") -> Project Forecast | K32: =HYPERLINK("#'Master_Mappings'!A1","Master Mappings") -> Master Mappings
B33: =HYPERLINK("#'Balance_Sheet'!A1","Balance Sheet") -> Balance Sheet | E33: =HYPERLINK("#'Annual_Summary'!A1","Annual Summary") -> Annual Summary | H33: =HYPERLINK("#'Nominal_Activity'!A1","Nominal Activity") -> Nominal Activity | K33: =HYPERLINK("#'Checks'!A1","Checks & Controls") -> Checks & Controls
B34: =HYPERLINK("#'TB_Review'!A1","Trial Balance Review") -> Trial Balance Review | E34: =HYPERLINK("#'Consolidation'!A1","Consolidation") -> Consolidation | H34: =HYPERLINK("#'Trial_Balance'!A1","Trial Balance") -> Trial Balance | K34: =HYPERLINK("#'Mgmt_Commentary'!A1","Commentary & Actions") -> Commentary & Actions
H35: =HYPERLINK("#'QMR_Inputs'!A1","QMR Inputs") -> QMR Inputs | K35: =HYPERLINK("#'Instructions'!A1","Instructions") -> Instructions

Sheet Controls
A1: PCGH Annual QMR — Controls, Reporting Calendar and Assumptions
A3: Control | B3: Value | C3: Units | D3: Source / Note | F3: Annual Reporting Calendar
A4: Reporting period end | B4: 46203 | C4: Date | D4: Q1 2026 source packs | F4: Quarter | G4: Period_End | H4: Data_Status
A5: Fiscal year | B5: =YEAR(B4) -> 2026 | C5: Year | D5: Calendar year | F5: Q1 | G5: 46112 | H5: =IF(COUNTIF(Project_Forecast!$B$2:$B$4993,$B$5&"-"&F5)+COUNTIF(Nominal_Activity!$B$2:$B$5000,$B$5&"-"&F5)+COUNTIF(Trial_Balance!$B$2:$B$4995,$B$5&"-"&F5)>0,"DATA LOADED","NOT LOADED") -> DATA LOADED
A6: Quarter | B6: ="Q"&ROUNDUP(MONTH(B4)/3,0) -> Q2 | C6: Quarter | D6: Calendar quarter | F6: Q2 | G6: 46203 | H6: =IF(COUNTIF(Project_Forecast!$B$2:$B$4993,$B$5&"-"&F6)+COUNTIF(Nominal_Activity!$B$2:$B$5000,$B$5&"-"&F6)+COUNTIF(Trial_Balance!$B$2:$B$4995,$B$5&"-"&F6)>0,"DATA LOADED","NOT LOADED") -> DATA LOADED
A7: Entity ID | B7: PCGH | C7: ID | D7: PC Ghana | F7: Q3 | G7: 46295 | H7: =IF(COUNTIF(Project_Forecast!$B$2:$B$4993,$B$5&"-"&F7)+COUNTIF(Nominal_Activity!$B$2:$B$5000,$B$5&"-"&F7)+COUNTIF(Trial_Balance!$B$2:$B$4995,$B$5&"-"&F7)>0,"DATA LOADED","NOT LOADED") -> NOT LOADED
A8: Entity name | B8: PC Ghana | C8: Text | D8: Confirmed pilot entity | F8: Q4 | G8: 46387 | H8: =IF(COUNTIF(Project_Forecast!$B$2:$B$4993,$B$5&"-"&F8)+COUNTIF(Nominal_Activity!$B$2:$B$5000,$B$5&"-"&F8)+COUNTIF(Trial_Balance!$B$2:$B$4995,$B$5&"-"&F8)>0,"DATA LOADED","NOT LOADED") -> NOT LOADED
A9: Local currency | B9: GHS | C9: Currency | D9: Entity reporting currency
A10: Group currency | B10: GHS | C10: Currency | D10: Consolidation currency
A11: Elapsed months | B11: =MONTH(B4) -> 6 | C11: Months | D11: Formula from reporting date | F11: Quarterly Management Inputs — update the blue cells as each quarter becomes available
A12: Materiality threshold | B12: 50000 | C12: GHS | D12: Default management exception threshold
A13: Materiality percentage | B13: 0.1 | C13: % | D13: Default management exception threshold | F13: Period | G13: Project_Budget_FY | H13: Programme_Budget_FY | I13: Programme_Forecast_FY | J13: Programme_Secured_FY | K13: Programme_Actual_YTD | L13: Other_Budget_FY | M13: Other_Forecast_FY | N13: Other_Actual_YTD | O13: Update_Note | P13: Programme_Invoicing_YTD | Q13: Programme_Income_YTD
A14: Default pipeline probability | B14: 0.7 | C14: % | D14: Applied where source notes say contract not signed | F14: 2026-Q1 | G14: 9794783.6 | H14: 3341189.8 | I14: 3341190 | J14: 3341190 | K14: 725884.66 | L14: 1426884.1 | M14: 1426884.1 | N14: 105344.75 | O14: Pilot data loaded | P14: 0 | Q14: 0
A15: Project income budget | B15: =IFERROR(VLOOKUP($B$30,$F$14:$N$17,2,FALSE()),0) -> 9794783.6 | C15: GHS | D15: Selected-period value from Quarterly Management Inputs | F15: 2026-Q2 | G15: 9794783.6 | H15: 3341189.8 | L15: 1426884.1 | O15: Awaiting Q2 update | P15: 0 | Q15: 0
A16: Programme income budget | B16: =IFERROR(VLOOKUP($B$30,$F$14:$N$17,3,FALSE()),0) -> 3341189.8 | C16: GHS | D16: Selected-period value from Quarterly Management Inputs | F16: 2026-Q3 | G16: 9794783.6 | H16: 3341189.8 | L16: 1426884.1 | O16: Awaiting Q3 update | P16: 0 | Q16: 0
A17: Programme forecast | B17: =IFERROR(VLOOKUP($B$30,$F$14:$N$17,4,FALSE()),0) -> 0 | C17: GHS | D17: Selected-period value from Quarterly Management Inputs | F17: 2026-Q4 | G17: 9794783.6 | H17: 3341189.8 | L17: 1426884.1 | O17: Awaiting Q4 update | P17: 0 | Q17: 0
A18: Programme secured | B18: =IFERROR(VLOOKUP($B$30,$F$14:$N$17,5,FALSE()),0) -> 0 | C18: GHS | D18: Selected-period value from Quarterly Management Inputs
A19: Programme WIP YTD | B19: =IFERROR(VLOOKUP($B$30,$F$14:$N$17,6,FALSE()),0) -> 0 | C19: GHS | D19: Selected-period value from Quarterly Management Inputs
A20: Other income budget | B20: =IFERROR(VLOOKUP($B$30,$F$14:$N$17,7,FALSE()),0) -> 1426884.1 | C20: GHS | D20: Selected-period value from Quarterly Management Inputs
A21: Other income forecast | B21: =IFERROR(VLOOKUP($B$30,$F$14:$N$17,8,FALSE()),0) -> 0 | C21: GHS | D21: Selected-period value from Quarterly Management Inputs
A22: Other income actual YTD | B22: =IFERROR(VLOOKUP($B$30,$F$14:$N$17,9,FALSE()),0) -> 0 | C22: GHS | D22: Selected-period value from Quarterly Management Inputs
A23: Approval status | B23: Draft | C23: Status | D23: Finance approver changes to Approved
A24: Finance approver | B24: Finance Lead | C24: Role | D24: Publication authority
A25: Workbook version | B25: v2.5 | C25: Version | D25: v2.5 2026-08-13: (1) Balance_Sheet — Selected Quarter Opening/Closing block (H:K): Opening = prior-quarter TB closing balance, derived automatically from the reporting quarter in Controls (falls back to the selected snapshot’s TB opening column when the prior-quarter TB is not loaded; Q1 uses the Q1 TB opening balances); Closing = the selected quarter’s own TB closing position. Historical Q1-Q4 columns (B:E) are unchanged and stay fixed per quarter. QMR_Report movement column repointed to the new block; opening balance-sheet and continuity checks added (Checks rows 42-43); row-39 continuity formula repaired to compare asset-line TB openings against prior-quarter closing assets (previously it summed the whole TB, which nets to zero). (2) PA_TB_Recon rebuilt — reconciles Project_Activity (actual project accounting activity) against the Trial_Balance by nominal code, YTD to the comparison quarter: PA total vs TB total, variance, RECONCILED/VARIANCE/INFO status with tolerance input, completeness row for unmapped codes, and a Project × Nominal Code × Period drill-down. Projects Forecast is no longer part of this reconciliation. | v2.4 2026-07-27: (1) Balance_Sheet quarter cols rebuilt as period-driven SUMIFS on the account-code mapping implied by the entered formulas (closing balance, natural TB signs); Master_Mappings extended, movement cols repaired. (2) Next-quarter-opening fallback removed — unloaded quarters show "-". (3) Project_Forecast rebuilt on INDEX/MATCH by Project_ID, capacity MM_Income rows 5-204 → PF rows 2-201, S4/S8/S9 repaired. (4) PA_TB_Recon col D re-sourced to Project_Forecast flow-group columns. (5) QMR_Inputs block 6: project income budgets by portfolio and type, wired to QMR_Report S1/S4 and Project_Output. (6) Programme table: Invoicing + YTD columns, wired to QMR_Report and Controls P/Q. Follow-up 2026-07-27: TB snapshot period corrected 2026-Q1→2026-Q2 (openings = 31-Mar = NA YTD-to-Q1 per code; closings = 30-Jun); TBC placeholder IDs uniquified (TBC-01..08); QMR_Inputs Unallocated rows made self-balancing; PA_TB_Recon statuses made Flow_Group-aware.
A26: Source refresh date | B26: 46203 | C26: Date | D26: Latest source data date
A27: PCGH average FX to GHS | B27: 1 | C27: Rate | D27: GHS reporting entity
A28: PCGH closing FX to GHS | B28: 1 | C28: Rate | D28: GHS reporting entity
A29: Publication scope | B29: Entity QMR | C29: Scope | D29: Choose Entity QMR or Consolidated QMR
A30: Selected period key | B30: =B5&"-"&B6 -> 2026-Q2 | C30: System generated | D30: Used by all selected-period reports
A31: Entity and FX Master | H31: Exchange Rate Control Table (to GHS)
H32: Currency | I32: Rate_to_GHS | J32: Source | K32: As_Of
A33: Entity_ID | B33: Entity_Name | C33: Local_Currency | D33: Average_FX_to_GHS | E33: Closing_FX_to_GHS | F33: Data_Status | H33: GHS | I33: 1 | J33: Reporting currency | K33: 2026-03-31
A34: PCGH | B34: PC Ghana | C34: GHS | D34: 1 | E34: 1 | F34: Pilot populated | H34: USD | I34: 10.7 | J34: Requirements doc §1.3 | K34: 2026-03-31
A35: PFI | B35: Proforest Initiative | C35: TBC | F35: Awaiting source pack | H35: GBP | I35: 14.45 | J35: Requirements doc §1.3 | K35: 2026-03-31
A36: PFCD | B36: Proforest Co-develop | C36: TBC | F36: Awaiting source pack | H36: EUR | I36: 10.1215 | J36: Requirements doc §1.3 | K36: 2026-03-31
A37: PFCM | B37: Proforest Cameroon | C37: TBC | F37: Awaiting source pack
A39: QUARTERLY UPDATE CHECKLIST — refresh in this order:
A40: 1. Controls!B4 — set the reporting period end (drives FY, quarter and every report).
A41: 2. Paste the quarter's source packs: Project_Activity, Nominal_Activity, Trial_Balance (append rows).
A42: 3. MM_Income — maintain the yellow inputs: Status (E), contract value and inclusive fees/expenses (K:N), Forecast_Class/Probability (U:V); add new or pipeline projects as ordinary rows (Status=Pipeline, Probability<1).
A43: 4. Project_Forecast — enter the quarter's WIP % (yellow V/X/Z/AB) and Management_Review/Comments.
A44: 5. Controls F13:Q17 — update the quarterly management inputs row for the new period (incl. programme invoicing and income YTD).
A45: 6. Checks — clear every FAIL before publishing; FixedCost_Output!B92 is the amount to invoice PIGH this quarter.

Sheet QMR_Dashboard
A1: ="Executive QMR Dashboard — "&Controls!$B$8&" — "&Controls!$B$30 -> Executive QMR Dashboard — PC Ghana — 2026-Q2
A2: ="All values GHS '000 unless stated | Live view of the selected quarter | Detail on the domain dashboards" -> All values GHS '000 unless stated | Live view of the selected quarter | Detail on the domain dashboards
A4: INCOME · FY FORECAST | C4: FIXED COSTS · YTD | E4: SURPLUS · FY FORECAST | G4: SECURED vs BUDGET | I4: MONTHS OF COST COVER | K4: DATA QUALITY
A5: =QMR_Report!$C$29/1000 -> 18393.381 | C5: =QMR_Report!$F$47/1000 -> 5801.7136 | E5: =QMR_Report!$C$56/1000 -> 4619.009 | G5: =QMR_Report!$G$29 -> 4.4498661 | I5: =IFERROR(--INDEX(Balance_Sheet!$C$36:$F$36,1,VALUE(MID(Controls!$B$6,2,1))),0) -> 5.7737739 | K5: =Checks!$B$3 -> PASS WITH REVIEW
A6: ="vs budget "&TEXT(QMR_Report!$B$29/1000,"#,##0") -> vs budget 3,341 | C6: ="vs YTD budget "&TEXT(FixedCost_Output!$E$3/1000,"#,##0")&" ("&TEXT(FixedCost_Output!$B$5,"0%")&")" -> vs YTD budget 6,887 (84%) | E6: ="vs budget "&TEXT(QMR_Report!$B$56/1000,"#,##0") -> vs budget -9,006 | G6: ="WIP YTD "&TEXT(QMR_Report!$E$29/1000,"#,##0") -> WIP YTD 8,798 | I6: ="target 3.0 | WC "&TEXT(IFERROR(--INDEX(Balance_Sheet!$C$34:$F$34,1,VALUE(MID(Controls!$B$6,2,1))),0)/1000,"#,##0") -> target 3.0 | WC 5,711 | K6: ="fails "&COUNTIF(Checks!$F$8:$F$41,"FAIL")&" | reviews "&COUNTIF(Checks!$F$8:$F$41,"REVIEW") -> fails 0 | reviews 5
H7: INCOME vs COST BY QUARTER (GHS '000)
A8: QUARTERLY PROFILE — INCOME vs COST (GHS '000)
B9: Q1 | C9: Q2 | D9: Q3 | E9: Q4 | F9: FY
A10: Income (WIP basis) | B10: =Project_Output!B30/1000 -> 4910.7961 | C10: =Project_Output!B31/1000 -> 2548.4044 | D10: =Project_Output!B32/1000 -> 2136.143 | E10: =Project_Output!B33/1000 -> 1831.1564 | F10: =SUM(B10:E10) -> 11426.5
A11: Invoiced | B11: =-SUMIFS(Project_Activity!$P$2:$P$2991,Project_Activity!$U$2:$U$2991,"Invoiced Income",Project_Activity!$H$2:$H$2991,">="&DATE(Controls!$B$5,1,1),Project_Activity!$H$2:$H$2991,"<="&EOMONTH(DATE(Controls!$B$5,3,1),0),Project_Activity!$A$2:$A$2991,Controls!$B$7)/1000 -> 2701.8936 | C11: =-SUMIFS(Project_Activity!$P$2:$P$2991,Project_Activity!$U$2:$U$2991,"Invoiced Income",Project_Activity!$H$2:$H$2991,">="&DATE(Controls!$B$5,4,1),Project_Activity!$H$2:$H$2991,"<="&EOMONTH(DATE(Controls!$B$5,6,1),0),Project_Activity!$A$2:$A$2991,Controls!$B$7)/1000 -> 4369.6242 | D11: =-SUMIFS(Project_Activity!$P$2:$P$2991,Project_Activity!$U$2:$U$2991,"Invoiced Income",Project_Activity!$H$2:$H$2991,">="&DATE(Controls!$B$5,7,1),Project_Activity!$H$2:$H$2991,"<="&EOMONTH(DATE(Controls!$B$5,9,1),0),Project_Activity!$A$2:$A$2991,Controls!$B$7)/1000 -> 0 | E11: =-SUMIFS(Project_Activity!$P$2:$P$2991,Project_Activity!$U$2:$U$2991,"Invoiced Income",Project_Activity!$H$2:$H$2991,">="&DATE(Controls!$B$5,10,1),Project_Activity!$H$2:$H$2991,"<="&EOMONTH(DATE(Controls!$B$5,12,1),0),Project_Activity!$A$2:$A$2991,Controls!$B$7)/1000 -> 0 | F11: =SUM(B11:E11) -> 7071.5179
A12: Fixed costs | B12: =SUMIFS(Nominal_Activity!$M$2:$M$3000,Nominal_Activity!$N$2:$N$3000,"<>Excluded — Project/Other",Nominal_Activity!$G$2:$G$3000,">="&DATE(Controls!$B$5,1,1),Nominal_Activity!$G$2:$G$3000,"<="&EOMONTH(DATE(Controls!$B$5,3,1),0),Nominal_Activity!$A$2:$A$3000,Controls!$B$7)/1000 -> 2779.3613 | C12: =SUMIFS(Nominal_Activity!$M$2:$M$3000,Nominal_Activity!$N$2:$N$3000,"<>Excluded — Project/Other",Nominal_Activity!$G$2:$G$3000,">="&DATE(Controls!$B$5,4,1),Nominal_Activity!$G$2:$G$3000,"<="&EOMONTH(DATE(Controls!$B$5,6,1),0),Nominal_Activity!$A$2:$A$3000,Controls!$B$7)/1000 -> 3022.3522 | D12: =SUMIFS(Nominal_Activity!$M$2:$M$3000,Nominal_Activity!$N$2:$N$3000,"<>Excluded — Project/Other",Nominal_Activity!$G$2:$G$3000,">="&DATE(Controls!$B$5,7,1),Nominal_Activity!$G$2:$G$3000,"<="&EOMONTH(DATE(Controls!$B$5,9,1),0),Nominal_Activity!$A$2:$A$3000,Controls!$B$7)/1000 -> 0 | E12: =SUMIFS(Nominal_Activity!$M$2:$M$3000,Nominal_Activity!$N$2:$N$3000,"<>Excluded — Project/Other",Nominal_Activity!$G$2:$G$3000,">="&DATE(Controls!$B$5,10,1),Nominal_Activity!$G$2:$G$3000,"<="&EOMONTH(DATE(Controls!$B$5,12,1),0),Nominal_Activity!$A$2:$A$3000,Controls!$B$7)/1000 -> 0 | F12: =SUM(B12:E12) -> 5801.7136
A13: Surplus | B13: =B10-B12 -> 2131.4348 | C13: =C10-C12 -> -473.94785 | D13: =D10-D12 -> 2136.143 | E13: =E10-E12 -> 1831.1564 | F13: =SUM(B13:E13) -> 5624.7863
A14: Quarters after the selected one show forecast WIP and zero cost until data is loaded.
A17: STATUS SUMMARY
A18: Domain | B18: Metric | C18: Value | D18: Target | E18: Status
A19: Income | B19: Secured vs annual budget | C19: =QMR_Report!$G$29 -> 4.4498661 | D19: ≥ 90% | E19: =IF(QMR_Report!$G$29>=0.9,"OK",IF(QMR_Report!$G$29>=0.7,"REVIEW","FAIL")) -> OK
A20: Costs | B20: Spend vs YTD budget | C20: =FixedCost_Output!$B$5 -> 0.84239249 | D20: 85–110% | E20: =IF(AND(FixedCost_Output!$B$5>=0.85,FixedCost_Output!$B$5<=1.1),"OK","REVIEW") -> REVIEW | H20: BUDGET vs ACTUAL YTD BY CATEGORY (GHS)
A21: Liquidity | B21: Months of core cover | C21: =IFERROR(--INDEX(Balance_Sheet!$C$36:$F$36,1,VALUE(MID(Controls!$B$6,2,1))),0) -> 5.7737739 | D21: ≥ 3.0 | E21: =IF(IFERROR(--INDEX(Balance_Sheet!$C$36:$F$36,1,VALUE(MID(Controls!$B$6,2,1))),0)>=3,"OK",IF(IFERROR(--INDEX(Balance_Sheet!$C$36:$F$36,1,VALUE(MID(Controls!$B$6,2,1))),0)>=1.5,"REVIEW","FAIL")) -> OK
A22: Working capital | B22: Working capital (GHS 000) | C22: =IFERROR(--INDEX(Balance_Sheet!$C$34:$F$34,1,VALUE(MID(Controls!$B$6,2,1))),0)/1000 -> 5711.2079 | D22: > 0 | E22: =IF(IFERROR(--INDEX(Balance_Sheet!$C$34:$F$34,1,VALUE(MID(Controls!$B$6,2,1))),0)>0,"OK","FAIL") -> OK
A23: Balance sheet | B23: A − L − E | C23: =INDEX(Balance_Sheet!$C$30:$F$30,1,VALUE(MID(Controls!$B$6,2,1))) -> 0 | D23: 0 | E23: =IF(ABS(N(INDEX(Balance_Sheet!$C$30:$F$30,1,VALUE(MID(Controls!$B$6,2,1)))))<=1,"OK","FAIL") -> OK
A24: Data quality | B24: Checks banner | C24: =Checks!$B$3 -> PASS WITH REVIEW | D24: PASS | E24: =IF(Checks!$B$3="PASS","OK",IF(Checks!$B$3="FAIL","FAIL","REVIEW")) -> REVIEW
A27: ENTITY VIEW (GHS '000)
A28: Entity | B28: Income (TOI) | C28: Fixed costs | D28: Surplus YTD | E28: Working capital | F28: Status
A29: =Consolidation!B6 -> PC Ghana | B29: =IF(Consolidation!F6="","-",Consolidation!F6/1000) -> 15545.818 | C29: =IF(Consolidation!G6="","-",Consolidation!G6/1000) -> 5801.7136 | D29: =IF(Consolidation!H6="","-",Consolidation!H6/1000) -> 1657.4869 | E29: =IF(Consolidation!I6="","-",Consolidation!I6/1000) -> 5711.2079 | F29: =Consolidation!J6 -> Populated
A30: =Consolidation!B7 -> Proforest Initiative | B30: =IF(Consolidation!F7="","-",Consolidation!F7/1000) -> - | C30: =IF(Consolidation!G7="","-",Consolidation!G7/1000) -> - | D30: =IF(Consolidation!H7="","-",Consolidation!H7/1000) -> - | E30: =IF(Consolidation!I7="","-",Consolidation!I7/1000) -> - | F30: =Consolidation!J7 -> Awaiting source pack
A31: =Consolidation!B8 -> Proforest Co-develop | B31: =IF(Consolidation!F8="","-",Consolidation!F8/1000) -> - | C31: =IF(Consolidation!G8="","-",Consolidation!G8/1000) -> - | D31: =IF(Consolidation!H8="","-",Consolidation!H8/1000) -> - | E31: =IF(Consolidation!I8="","-",Consolidation!I8/1000) -> - | F31: =Consolidation!J8 -> Awaiting source pack
A32: =Consolidation!B9 -> Proforest Cameroon | B32: =IF(Consolidation!F9="","-",Consolidation!F9/1000) -> - | C32: =IF(Consolidation!G9="","-",Consolidation!G9/1000) -> - | D32: =IF(Consolidation!H9="","-",Consolidation!H9/1000) -> - | E32: =IF(Consolidation!I9="","-",Consolidation!I9/1000) -> - | F32: =Consolidation!J9 -> Awaiting source pack
A35: COMMENTARY — OPEN ITEMS (maintained on Mgmt_Commentary)
A36: 1. | B36: =IFERROR(INDEX(Mgmt_Commentary!$A:$A,_xlfn.AGGREGATE(15,6,ROW(Mgmt_Commentary!$I$5:$I$34)/(Mgmt_Commentary!$I$5:$I$34="Open"),1))&": "&INDEX(Mgmt_Commentary!$B:$B,_xlfn.AGGREGATE(15,6,ROW(Mgmt_Commentary!$I$5:$I$34)/(Mgmt_Commentary!$I$5:$I$34="Open"),1))&" → "&INDEX(Mgmt_Commentary!$F:$F,_xlfn.AGGREGATE(15,6,ROW(Mgmt_Commentary!$I$5:$I$34)/(Mgmt_Commentary!$I$5:$I$34="Open"),1))&" ["&INDEX(Mgmt_Commentary!$G:$G,_xlfn.AGGREGATE(15,6,ROW(Mgmt_Commentary!$I$5:$I$34)/(Mgmt_Commentary!$I$5:$I$34="Open"),1))&"]","—") -> Fixed Costs: YTD spend GHS 2.78m is 664k below phased budget (81% of YTD budget) → Confirm monthly phasing with budget holders; replace even phasing if a profile is approved [Finance]
A37: 2. | B37: =IFERROR(INDEX(Mgmt_Commentary!$A:$A,_xlfn.AGGREGATE(15,6,ROW(Mgmt_Commentary!$I$5:$I$34)/(Mgmt_Commentary!$I$5:$I$34="Open"),2))&": "&INDEX(Mgmt_Commentary!$B:$B,_xlfn.AGGREGATE(15,6,ROW(Mgmt_Commentary!$I$5:$I$34)/(Mgmt_Commentary!$I$5:$I$34="Open"),2))&" → "&INDEX(Mgmt_Commentary!$F:$F,_xlfn.AGGREGATE(15,6,ROW(Mgmt_Commentary!$I$5:$I$34)/(Mgmt_Commentary!$I$5:$I$34="Open"),2))&" ["&INDEX(Mgmt_Commentary!$G:$G,_xlfn.AGGREGATE(15,6,ROW(Mgmt_Commentary!$I$5:$I$34)/(Mgmt_Commentary!$I$5:$I$34="Open"),2))&"]","—") -> Project Income: PCGH767 (Presco scoping) WIP at 147% of net forecast → PM to true-up gross forecast in MM_Income for completed projects [Project Leads]
A38: 3. | B38: =IFERROR(INDEX(Mgmt_Commentary!$A:$A,_xlfn.AGGREGATE(15,6,ROW(Mgmt_Commentary!$I$5:$I$34)/(Mgmt_Commentary!$I$5:$I$34="Open"),3))&": "&INDEX(Mgmt_Commentary!$B:$B,_xlfn.AGGREGATE(15,6,ROW(Mgmt_Commentary!$I$5:$I$34)/(Mgmt_Commentary!$I$5:$I$34="Open"),3))&" → "&INDEX(Mgmt_Commentary!$F:$F,_xlfn.AGGREGATE(15,6,ROW(Mgmt_Commentary!$I$5:$I$34)/(Mgmt_Commentary!$I$5:$I$34="Open"),3))&" ["&INDEX(Mgmt_Commentary!$G:$G,_xlfn.AGGREGATE(15,6,ROW(Mgmt_Commentary!$I$5:$I$34)/(Mgmt_Commentary!$I$5:$I$34="Open"),3))&"]","—") -> Executive: Programme income (GHS 3.34m budget) not yet split by portfolio → Provide portfolio split on QMR_Inputs block 1 [Finance Lead]
A39: 4. | B39: =IFERROR(INDEX(Mgmt_Commentary!$A:$A,_xlfn.AGGREGATE(15,6,ROW(Mgmt_Commentary!$I$5:$I$34)/(Mgmt_Commentary!$I$5:$I$34="Open"),4))&": "&INDEX(Mgmt_Commentary!$B:$B,_xlfn.AGGREGATE(15,6,ROW(Mgmt_Commentary!$I$5:$I$34)/(Mgmt_Commentary!$I$5:$I$34="Open"),4))&" → "&INDEX(Mgmt_Commentary!$F:$F,_xlfn.AGGREGATE(15,6,ROW(Mgmt_Commentary!$I$5:$I$34)/(Mgmt_Commentary!$I$5:$I$34="Open"),4))&" ["&INDEX(Mgmt_Commentary!$G:$G,_xlfn.AGGREGATE(15,6,ROW(Mgmt_Commentary!$I$5:$I$34)/(Mgmt_Commentary!$I$5:$I$34="Open"),4))&"]","—") -> —

Sheet QMR_Report
A1: ="Quarterly Management Report — "&Controls!$B$8&" — "&Controls!$B$30 -> Quarterly Management Report — PC Ghana — 2026-Q2
A2: ="All figures GHS unless stated | Data: staging tabs + master mappings | Inputs live on QMR_Inputs only" -> All figures GHS unless stated | Data: staging tabs + master mappings | Inputs live on QMR_Inputs only
A4: SECTION 1 — INCOME AND EXPENDITURE
A5: Line | B5: Annual Budget | C5: FY Forecast | D5: Secured Net | E5: WIP YTD | F5: Invoiced / Actual YTD | G5: Secured vs Budget | H5: WIP vs Budget | I5: Inv&Act vs Budget
A6: Project Income — External
A7: Responsible Sourcing | C7: =SUMIFS(Project_Forecast!$N$2:$N$393,Project_Forecast!$E$2:$E$393,"Responsible Sourcing",Project_Forecast!$G$2:$G$393,"External",Project_Forecast!$B$2:$B$393,Controls!$B$30,Project_Forecast!$A$2:$A$393,Controls!$B$7) -> 0 | D7: =SUMIFS(Project_Forecast!$N$2:$N$393,Project_Forecast!$E$2:$E$393,"Responsible Sourcing",Project_Forecast!$G$2:$G$393,"External",Project_Forecast!$L$2:$L$393,"Secured",Project_Forecast!$B$2:$B$393,Controls!$B$30,Project_Forecast!$A$2:$A$393,Controls!$B$7) -> 0 | E7: =SUMIFS(Project_Forecast!$AD$2:$AD$393,Project_Forecast!$E$2:$E$393,"Responsible Sourcing",Project_Forecast!$G$2:$G$393,"External",Project_Forecast!$B$2:$B$393,Controls!$B$30,Project_Forecast!$A$2:$A$393,Controls!$B$7) -> 0 | F7: =SUMIFS(Project_Forecast!$O$2:$O$393,Project_Forecast!$E$2:$E$393,"Responsible Sourcing",Project_Forecast!$G$2:$G$393,"External",Project_Forecast!$B$2:$B$393,Controls!$B$30,Project_Forecast!$A$2:$A$393,Controls!$B$7) -> 0
A8: Responsible Production | C8: =SUMIFS(Project_Forecast!$N$2:$N$393,Project_Forecast!$E$2:$E$393,"Responsible Production",Project_Forecast!$G$2:$G$393,"External",Project_Forecast!$B$2:$B$393,Controls!$B$30,Project_Forecast!$A$2:$A$393,Controls!$B$7) -> 9760078 | D8: =SUMIFS(Project_Forecast!$N$2:$N$393,Project_Forecast!$E$2:$E$393,"Responsible Production",Project_Forecast!$G$2:$G$393,"External",Project_Forecast!$L$2:$L$393,"Secured",Project_Forecast!$B$2:$B$393,Controls!$B$30,Project_Forecast!$A$2:$A$393,Controls!$B$7) -> 6643820.7 | E8: =SUMIFS(Project_Forecast!$AD$2:$AD$393,Project_Forecast!$E$2:$E$393,"Responsible Production",Project_Forecast!$G$2:$G$393,"External",Project_Forecast!$B$2:$B$393,Controls!$B$30,Project_Forecast!$A$2:$A$393,Controls!$B$7) -> 4656235.4 | F8: =SUMIFS(Project_Forecast!$O$2:$O$393,Project_Forecast!$E$2:$E$393,"Responsible Production",Project_Forecast!$G$2:$G$393,"External",Project_Forecast!$B$2:$B$393,Controls!$B$30,Project_Forecast!$A$2:$A$393,Controls!$B$7) -> 3852516.1
A9: Responsible Finance | C9: =SUMIFS(Project_Forecast!$N$2:$N$393,Project_Forecast!$E$2:$E$393,"Responsible Finance",Project_Forecast!$G$2:$G$393,"External",Project_Forecast!$B$2:$B$393,Controls!$B$30,Project_Forecast!$A$2:$A$393,Controls!$B$7) -> 913245 | D9: =SUMIFS(Project_Forecast!$N$2:$N$393,Project_Forecast!$E$2:$E$393,"Responsible Finance",Project_Forecast!$G$2:$G$393,"External",Project_Forecast!$L$2:$L$393,"Secured",Project_Forecast!$B$2:$B$393,Controls!$B$30,Project_Forecast!$A$2:$A$393,Controls!$B$7) -> 913245 | E9: =SUMIFS(Project_Forecast!$AD$2:$AD$393,Project_Forecast!$E$2:$E$393,"Responsible Finance",Project_Forecast!$G$2:$G$393,"External",Project_Forecast!$B$2:$B$393,Controls!$B$30,Project_Forecast!$A$2:$A$393,Controls!$B$7) -> 696184.8 | F9: =SUMIFS(Project_Forecast!$O$2:$O$393,Project_Forecast!$E$2:$E$393,"Responsible Finance",Project_Forecast!$G$2:$G$393,"External",Project_Forecast!$B$2:$B$393,Controls!$B$30,Project_Forecast!$A$2:$A$393,Controls!$B$7) -> 801822.68
A10: Collaboration | C10: =SUMIFS(Project_Forecast!$N$2:$N$393,Project_Forecast!$E$2:$E$393,"Collaboration",Project_Forecast!$G$2:$G$393,"External",Project_Forecast!$B$2:$B$393,Controls!$B$30,Project_Forecast!$A$2:$A$393,Controls!$B$7) -> 128400 | D10: =SUMIFS(Project_Forecast!$N$2:$N$393,Project_Forecast!$E$2:$E$393,"Collaboration",Project_Forecast!$G$2:$G$393,"External",Project_Forecast!$L$2:$L$393,"Secured",Project_Forecast!$B$2:$B$393,Controls!$B$30,Project_Forecast!$A$2:$A$393,Controls!$B$7) -> 128400 | E10: =SUMIFS(Project_Forecast!$AD$2:$AD$393,Project_Forecast!$E$2:$E$393,"Collaboration",Project_Forecast!$G$2:$G$393,"External",Project_Forecast!$B$2:$B$393,Controls!$B$30,Project_Forecast!$A$2:$A$393,Controls!$B$7) -> 64200 | F10: =SUMIFS(Project_Forecast!$O$2:$O$393,Project_Forecast!$E$2:$E$393,"Collaboration",Project_Forecast!$G$2:$G$393,"External",Project_Forecast!$B$2:$B$393,Controls!$B$30,Project_Forecast!$A$2:$A$393,Controls!$B$7) -> 0
A11: Production Landscape | C11: =SUMIFS(Project_Forecast!$N$2:$N$393,Project_Forecast!$E$2:$E$393,"Production Landscape",Project_Forecast!$G$2:$G$393,"External",Project_Forecast!$B$2:$B$393,Controls!$B$30,Project_Forecast!$A$2:$A$393,Controls!$B$7) -> 0 | D11: =SUMIFS(Project_Forecast!$N$2:$N$393,Project_Forecast!$E$2:$E$393,"Production Landscape",Project_Forecast!$G$2:$G$393,"External",Project_Forecast!$L$2:$L$393,"Secured",Project_Forecast!$B$2:$B$393,Controls!$B$30,Project_Forecast!$A$2:$A$393,Controls!$B$7) -> 0 | E11: =SUMIFS(Project_Forecast!$AD$2:$AD$393,Project_Forecast!$E$2:$E$393,"Production Landscape",Project_Forecast!$G$2:$G$393,"External",Project_Forecast!$B$2:$B$393,Controls!$B$30,Project_Forecast!$A$2:$A$393,Controls!$B$7) -> 0 | F11: =SUMIFS(Project_Forecast!$O$2:$O$393,Project_Forecast!$E$2:$E$393,"Production Landscape",Project_Forecast!$G$2:$G$393,"External",Project_Forecast!$B$2:$B$393,Controls!$B$30,Project_Forecast!$A$2:$A$393,Controls!$B$7) -> 0
A12: Policy & Regulation | C12: =SUMIFS(Project_Forecast!$N$2:$N$393,Project_Forecast!$E$2:$E$393,"Policy & Regulation",Project_Forecast!$G$2:$G$393,"External",Project_Forecast!$B$2:$B$393,Controls!$B$30,Project_Forecast!$A$2:$A$393,Controls!$B$7) -> 0 | D12: =SUMIFS(Project_Forecast!$N$2:$N$393,Project_Forecast!$E$2:$E$393,"Policy & Regulation",Project_Forecast!$G$2:$G$393,"External",Project_Forecast!$L$2:$L$393,"Secured",Project_Forecast!$B$2:$B$393,Controls!$B$30,Project_Forecast!$A$2:$A$393,Controls!$B$7) -> 0 | E12: =SUMIFS(Project_Forecast!$AD$2:$AD$393,Project_Forecast!$E$2:$E$393,"Policy & Regulation",Project_Forecast!$G$2:$G$393,"External",Project_Forecast!$B$2:$B$393,Controls!$B$30,Project_Forecast!$A$2:$A$393,Controls!$B$7) -> 0 | F12: =SUMIFS(Project_Forecast!$O$2:$O$393,Project_Forecast!$E$2:$E$393,"Policy & Regulation",Project_Forecast!$G$2:$G$393,"External",Project_Forecast!$B$2:$B$393,Controls!$B$30,Project_Forecast!$A$2:$A$393,Controls!$B$7) -> 0
A13: Subtotal — External Project Income | B13: =QMR_Inputs!$B$51 -> 0 | C13: =SUM(C7:C12) -> 10801723 | D13: =SUM(D7:D12) -> 7685465.7 | E13: =SUM(E7:E12) -> 5416620.2 | F13: =SUM(F7:F12) -> 4654338.8
A14: Project Income — Internal (via other Proforest entities)
A15: Responsible Sourcing | C15: =SUMIFS(Project_Forecast!$N$2:$N$393,Project_Forecast!$E$2:$E$393,"Responsible Sourcing",Project_Forecast!$G$2:$G$393,"Internal",Project_Forecast!$B$2:$B$393,Controls!$B$30,Project_Forecast!$A$2:$A$393,Controls!$B$7) -> 4090375 | D15: =SUMIFS(Project_Forecast!$N$2:$N$393,Project_Forecast!$E$2:$E$393,"Responsible Sourcing",Project_Forecast!$G$2:$G$393,"Internal",Project_Forecast!$L$2:$L$393,"Secured",Project_Forecast!$B$2:$B$393,Controls!$B$30,Project_Forecast!$A$2:$A$393,Controls!$B$7) -> 4090375 | E15: =SUMIFS(Project_Forecast!$AD$2:$AD$393,Project_Forecast!$E$2:$E$393,"Responsible Sourcing",Project_Forecast!$G$2:$G$393,"Internal",Project_Forecast!$B$2:$B$393,Controls!$B$30,Project_Forecast!$A$2:$A$393,Controls!$B$7) -> 1847024.7 | F15: =SUMIFS(Project_Forecast!$O$2:$O$393,Project_Forecast!$E$2:$E$393,"Responsible Sourcing",Project_Forecast!$G$2:$G$393,"Internal",Project_Forecast!$B$2:$B$393,Controls!$B$30,Project_Forecast!$A$2:$A$393,Controls!$B$7) -> 2294991.8
A16: Responsible Production | C16: =SUMIFS(Project_Forecast!$N$2:$N$393,Project_Forecast!$E$2:$E$393,"Responsible Production",Project_Forecast!$G$2:$G$393,"Internal",Project_Forecast!$B$2:$B$393,Controls!$B$30,Project_Forecast!$A$2:$A$393,Controls!$B$7) -> 0 | D16: =SUMIFS(Project_Forecast!$N$2:$N$393,Project_Forecast!$E$2:$E$393,"Responsible Production",Project_Forecast!$G$2:$G$393,"Internal",Project_Forecast!$L$2:$L$393,"Secured",Project_Forecast!$B$2:$B$393,Controls!$B$30,Project_Forecast!$A$2:$A$393,Controls!$B$7) -> 0 | E16: =SUMIFS(Project_Forecast!$AD$2:$AD$393,Project_Forecast!$E$2:$E$393,"Responsible Production",Project_Forecast!$G$2:$G$393,"Internal",Project_Forecast!$B$2:$B$393,Controls!$B$30,Project_Forecast!$A$2:$A$393,Controls!$B$7) -> 0 | F16: =SUMIFS(Project_Forecast!$O$2:$O$393,Project_Forecast!$E$2:$E$393,"Responsible Production",Project_Forecast!$G$2:$G$393,"Internal",Project_Forecast!$B$2:$B$393,Controls!$B$30,Project_Forecast!$A$2:$A$393,Controls!$B$7) -> 0
A17: Responsible Finance | C17: =SUMIFS(Project_Forecast!$N$2:$N$393,Project_Forecast!$E$2:$E$393,"Responsible Finance",Project_Forecast!$G$2:$G$393,"Internal",Project_Forecast!$B$2:$B$393,Controls!$B$30,Project_Forecast!$A$2:$A$393,Controls!$B$7) -> 653719.44 | D17: =SUMIFS(Project_Forecast!$N$2:$N$393,Project_Forecast!$E$2:$E$393,"Responsible Finance",Project_Forecast!$G$2:$G$393,"Internal",Project_Forecast!$L$2:$L$393,"Secured",Project_Forecast!$B$2:$B$393,Controls!$B$30,Project_Forecast!$A$2:$A$393,Controls!$B$7) -> 244444.44 | E17: =SUMIFS(Project_Forecast!$AD$2:$AD$393,Project_Forecast!$E$2:$E$393,"Responsible Finance",Project_Forecast!$G$2:$G$393,"Internal",Project_Forecast!$B$2:$B$393,Controls!$B$30,Project_Forecast!$A$2:$A$393,Controls!$B$7) -> 195555.55 | F17: =SUMIFS(Project_Forecast!$O$2:$O$393,Project_Forecast!$E$2:$E$393,"Responsible Finance",Project_Forecast!$G$2:$G$393,"Internal",Project_Forecast!$B$2:$B$393,Controls!$B$30,Project_Forecast!$A$2:$A$393,Controls!$B$7) -> 122187.25
A18: Collaboration | C18: =SUMIFS(Project_Forecast!$N$2:$N$393,Project_Forecast!$E$2:$E$393,"Collaboration",Project_Forecast!$G$2:$G$393,"Internal",Project_Forecast!$B$2:$B$393,Controls!$B$30,Project_Forecast!$A$2:$A$393,Controls!$B$7) -> 0 | D18: =SUMIFS(Project_Forecast!$N$2:$N$393,Project_Forecast!$E$2:$E$393,"Collaboration",Project_Forecast!$G$2:$G$393,"Internal",Project_Forecast!$L$2:$L$393,"Secured",Project_Forecast!$B$2:$B$393,Controls!$B$30,Project_Forecast!$A$2:$A$393,Controls!$B$7) -> 0 | E18: =SUMIFS(Project_Forecast!$AD$2:$AD$393,Project_Forecast!$E$2:$E$393,"Collaboration",Project_Forecast!$G$2:$G$393,"Internal",Project_Forecast!$B$2:$B$393,Controls!$B$30,Project_Forecast!$A$2:$A$393,Controls!$B$7) -> 0 | F18: =SUMIFS(Project_Forecast!$O$2:$O$393,Project_Forecast!$E$2:$E$393,"Collaboration",Project_Forecast!$G$2:$G$393,"Internal",Project_Forecast!$B$2:$B$393,Controls!$B$30,Project_Forecast!$A$2:$A$393,Controls!$B$7) -> 0
A19: Production Landscape | C19: =SUMIFS(Project_Forecast!$N$2:$N$393,Project_Forecast!$E$2:$E$393,"Production Landscape",Project_Forecast!$G$2:$G$393,"Internal",Project_Forecast!$B$2:$B$393,Controls!$B$30,Project_Forecast!$A$2:$A$393,Controls!$B$7) -> 0 | D19: =SUMIFS(Project_Forecast!$N$2:$N$393,Project_Forecast!$E$2:$E$393,"Production Landscape",Project_Forecast!$G$2:$G$393,"Internal",Project_Forecast!$L$2:$L$393,"Secured",Project_Forecast!$B$2:$B$393,Controls!$B$30,Project_Forecast!$A$2:$A$393,Controls!$B$7) -> 0 | E19: =SUMIFS(Project_Forecast!$AD$2:$AD$393,Project_Forecast!$E$2:$E$393,"Production Landscape",Project_Forecast!$G$2:$G$393,"Internal",Project_Forecast!$B$2:$B$393,Controls!$B$30,Project_Forecast!$A$2:$A$393,Controls!$B$7) -> 0 | F19: =SUMIFS(Project_Forecast!$O$2:$O$393,Project_Forecast!$E$2:$E$393,"Production Landscape",Project_Forecast!$G$2:$G$393,"Internal",Project_Forecast!$B$2:$B$393,Controls!$B$30,Project_Forecast!$A$2:$A$393,Controls!$B$7) -> 0
A20: Policy & Regulation | C20: =SUMIFS(Project_Forecast!$N$2:$N$393,Project_Forecast!$E$2:$E$393,"Policy & Regulation",Project_Forecast!$G$2:$G$393,"Internal",Project_Forecast!$B$2:$B$393,Controls!$B$30,Project_Forecast!$A$2:$A$393,Controls!$B$7) -> 0 | D20: =SUMIFS(Project_Forecast!$N$2:$N$393,Project_Forecast!$E$2:$E$393,"Policy & Regulation",Project_Forecast!$G$2:$G$393,"Internal",Project_Forecast!$L$2:$L$393,"Secured",Project_Forecast!$B$2:$B$393,Controls!$B$30,Project_Forecast!$A$2:$A$393,Controls!$B$7) -> 0 | E20: =SUMIFS(Project_Forecast!$AD$2:$AD$393,Project_Forecast!$E$2:$E$393,"Policy & Regulation",Project_Forecast!$G$2:$G$393,"Internal",Project_Forecast!$B$2:$B$393,Controls!$B$30,Project_Forecast!$A$2:$A$393,Controls!$B$7) -> 0 | F20: =SUMIFS(Project_Forecast!$O$2:$O$393,Project_Forecast!$E$2:$E$393,"Policy & Regulation",Project_Forecast!$G$2:$G$393,"Internal",Project_Forecast!$B$2:$B$393,Controls!$B$30,Project_Forecast!$A$2:$A$393,Controls!$B$7) -> 0
A21: Subtotal — Internal Project Income | B21: =QMR_Inputs!$B$52 -> 0 | C21: =SUM(C15:C20) -> 4744094.5 | D21: =SUM(D15:D20) -> 4334819.5 | E21: =SUM(E15:E20) -> 2042580.3 | F21: =SUM(F15:F20) -> 2417179.1
A22: Other / unmapped projects | C22: =SUMIFS(Project_Forecast!$N$2:$N$393,Project_Forecast!$B$2:$B$393,Controls!$B$30,Project_Forecast!$A$2:$A$393,Controls!$B$7)-C13-C21 -> 0 | D22: =SUMIFS(Project_Forecast!$N$2:$N$393,Project_Forecast!$L$2:$L$393,"Secured",Project_Forecast!$B$2:$B$393,Controls!$B$30,Project_Forecast!$A$2:$A$393,Controls!$B$7)-D13-D21 -> 0 | E22: =SUMIFS(Project_Forecast!$AD$2:$AD$393,Project_Forecast!$B$2:$B$393,Controls!$B$30,Project_Forecast!$A$2:$A$393,Controls!$B$7)-E13-E21 -> 0 | F22: =SUMIFS(Project_Forecast!$O$2:$O$393,Project_Forecast!$B$2:$B$393,Controls!$B$30,Project_Forecast!$A$2:$A$393,Controls!$B$7)-F13-F21 -> 0
A23: Total Project Income | B23: =B13+B21 -> 0 | C23: =C13+C21+C22 -> 15545818 | D23: =D13+D21+D22 -> 12020285 | E23: =E13+E21+E22 -> 7459200.5 | F23: =F13+F21+F22 -> 7071517.9 | G23: =IFERROR(D23/B23,0) -> 0 | H23: =IFERROR(E23/B23,0) -> 0 | I23: =IFERROR(F23/B23,0) -> 0
A24: Programme Income (by Portfolio)
A25: Production Landscape | B25: =QMR_Inputs!B6 -> 2347805 | C25: =QMR_Inputs!C6 -> 2347805 | D25: =QMR_Inputs!D6 -> 2347805 | E25: =QMR_Inputs!E6 -> 945514 | F25: =QMR_Inputs!G6 -> 0
A26: Collaboration | B26: =QMR_Inputs!B7 -> 993385 | C26: =QMR_Inputs!C7 -> 499758 | D26: =QMR_Inputs!D7 -> 499758 | E26: =QMR_Inputs!E7 -> 393304 | F26: =QMR_Inputs!G7 -> 0
A27: Policy & Regulation | B27: =QMR_Inputs!B8 -> 0 | C27: =QMR_Inputs!C8 -> 0 | D27: =QMR_Inputs!D8 -> 0 | E27: =QMR_Inputs!E8 -> 0 | F27: =QMR_Inputs!G8 -> 0
A28: Total Programme Income | B28: =SUM(B25:B27) -> 3341190 | C28: =SUM(C25:C27) -> 2847563 | D28: =SUM(D25:D27) -> 2847563 | E28: =SUM(E25:E27) -> 1338818 | F28: =SUM(F25:F27) -> 0 | G28: =IFERROR(D28/B28,0) -> 0.85226012 | H28: =IFERROR(E28/B28,0) -> 0.40070095 | I28: =IFERROR(F28/B28,0) -> 0
A29: TOTAL OPERATING INCOME | B29: =B23+B28 -> 3341190 | C29: =C23+C28 -> 18393381 | D29: =D23+D28 -> 14867848 | E29: =E23+E28 -> 8798018.5 | F29: =F23+F28 -> 7071517.9 | G29: =IFERROR(D29/B29,0) -> 4.4498661 | H29: =IFERROR(E29/B29,0) -> 2.6331991 | I29: =IFERROR(F29/B29,0) -> 2.1164669
A31: Expenditure
A32: Direct Technical Costs | B32: =SUMIFS(MM_FixedCost!$F$5:$F$78,MM_FixedCost!$C$5:$C$78,"Direct technical costs") -> 7230077.7 | C32: =B32 -> 7230077.7 | D32: =F32 -> 3229268.5 | E32: =F32 -> 3229268.5 | F32: =SUMIFS(Nominal_Activity!$M$2:$M$3000,Nominal_Activity!$N$2:$N$3000,"Direct technical costs",Nominal_Activity!$G$2:$G$3000,">="&DATE(Controls!$B$5,1,1),Nominal_Activity!$G$2:$G$3000,"<="&Controls!$B$4,Nominal_Activity!$A$2:$A$3000,Controls!$B$7) -> 3229268.5
A33: Contribution from Group re Global Roles (Technical) | B33: =QMR_Inputs!B19 -> 0 | C33: =B33 -> 0 | D33: =F33 -> 0 | E33: =F33 -> 0 | F33: =QMR_Inputs!C19 -> 0
A34: Direct FinOps Costs | B34: =SUMIFS(MM_FixedCost!$F$5:$F$78,MM_FixedCost!$C$5:$C$78,"Direct support costs") -> 2322680 | C34: =B34 -> 2322680 | D34: =F34 -> 1287623.6 | E34: =F34 -> 1287623.6 | F34: =SUMIFS(Nominal_Activity!$M$2:$M$3000,Nominal_Activity!$N$2:$N$3000,"Direct support costs",Nominal_Activity!$G$2:$G$3000,">="&DATE(Controls!$B$5,1,1),Nominal_Activity!$G$2:$G$3000,"<="&Controls!$B$4,Nominal_Activity!$A$2:$A$3000,Controls!$B$7) -> 1287623.6
A35: Contribution from Group re Global Roles (FinOps) | B35: =QMR_Inputs!B20 -> 0 | C35: =B35 -> 0 | D35: =F35 -> 0 | E35: =F35 -> 0 | F35: =QMR_Inputs!C20 -> 0
A36: Indirect Costs from Group Payroll (Global Roles) | B36: =QMR_Inputs!B21 -> 0 | C36: =B36 -> 0 | D36: =F36 -> 0 | E36: =F36 -> 0 | F36: =QMR_Inputs!C21 -> 0
A37: Total Personnel Costs | B37: =SUM(B32:B36) -> 9552757.7 | C37: =SUM(C32:C36) -> 9552757.7 | D37: =SUM(D32:D36) -> 4516892.2 | E37: =SUM(E32:E36) -> 4516892.2 | F37: =SUM(F32:F36) -> 4516892.2
A38: Recruitment and Benefits | B38: =SUMIFS(MM_FixedCost!$F$5:$F$78,MM_FixedCost!$C$5:$C$78,"Recruitment, Benefits") -> 321500 | C38: =B38 -> 321500 | D38: =F38 -> 89499.71 | E38: =F38 -> 89499.71 | F38: =SUMIFS(Nominal_Activity!$M$2:$M$3000,Nominal_Activity!$N$2:$N$3000,"Recruitment, Benefits",Nominal_Activity!$G$2:$G$3000,">="&DATE(Controls!$B$5,1,1),Nominal_Activity!$G$2:$G$3000,"<="&Controls!$B$4,Nominal_Activity!$A$2:$A$3000,Controls!$B$7) -> 89499.71
A39: Professional Development and Training | B39: =SUMIFS(MM_FixedCost!$F$5:$F$78,MM_FixedCost!$C$5:$C$78,"Professional development and Training") -> 1217997 | C39: =B39 -> 1217997 | D39: =F39 -> 201138.6 | E39: =F39 -> 201138.6 | F39: =SUMIFS(Nominal_Activity!$M$2:$M$3000,Nominal_Activity!$N$2:$N$3000,"Professional development and Training",Nominal_Activity!$G$2:$G$3000,">="&DATE(Controls!$B$5,1,1),Nominal_Activity!$G$2:$G$3000,"<="&Controls!$B$4,Nominal_Activity!$A$2:$A$3000,Controls!$B$7) -> 201138.6
A40: Business Development and Comms | B40: =SUMIFS(MM_FixedCost!$F$5:$F$78,MM_FixedCost!$C$5:$C$78,"Business development and Comms") -> 247369.45 | C40: =B40 -> 247369.45 | D40: =F40 -> 99295.87 | E40: =F40 -> 99295.87 | F40: =SUMIFS(Nominal_Activity!$M$2:$M$3000,Nominal_Activity!$N$2:$N$3000,"Business development and Comms",Nominal_Activity!$G$2:$G$3000,">="&DATE(Controls!$B$5,1,1),Nominal_Activity!$G$2:$G$3000,"<="&Controls!$B$4,Nominal_Activity!$A$2:$A$3000,Controls!$B$7) -> 99295.87
A41: Internal Events and Meetings | B41: =SUMIFS(MM_FixedCost!$F$5:$F$78,MM_FixedCost!$C$5:$C$78,"Internal events and meetings") -> 439040 | C41: =B41 -> 439040 | D41: =F41 -> 33622.84 | E41: =F41 -> 33622.84 | F41: =SUMIFS(Nominal_Activity!$M$2:$M$3000,Nominal_Activity!$N$2:$N$3000,"Internal events and meetings",Nominal_Activity!$G$2:$G$3000,">="&DATE(Controls!$B$5,1,1),Nominal_Activity!$G$2:$G$3000,"<="&Controls!$B$4,Nominal_Activity!$A$2:$A$3000,Controls!$B$7) -> 33622.84
A42: Professional Services and Governance | B42: =SUMIFS(MM_FixedCost!$F$5:$F$78,MM_FixedCost!$C$5:$C$78,"Professional services and governance") -> 1028561.7 | C42: =B42 -> 1028561.7 | D42: =F42 -> 684241.87 | E42: =F42 -> 684241.87 | F42: =SUMIFS(Nominal_Activity!$M$2:$M$3000,Nominal_Activity!$N$2:$N$3000,"Professional services and governance",Nominal_Activity!$G$2:$G$3000,">="&DATE(Controls!$B$5,1,1),Nominal_Activity!$G$2:$G$3000,"<="&Controls!$B$4,Nominal_Activity!$A$2:$A$3000,Controls!$B$7) -> 684241.87
A43: IT and Data | B43: =SUMIFS(MM_FixedCost!$F$5:$F$78,MM_FixedCost!$C$5:$C$78,"IT and Data") -> 423770.5 | C43: =B43 -> 423770.5 | D43: =F43 -> 71930.54 | E43: =F43 -> 71930.54 | F43: =SUMIFS(Nominal_Activity!$M$2:$M$3000,Nominal_Activity!$N$2:$N$3000,"IT and Data",Nominal_Activity!$G$2:$G$3000,">="&DATE(Controls!$B$5,1,1),Nominal_Activity!$G$2:$G$3000,"<="&Controls!$B$4,Nominal_Activity!$A$2:$A$3000,Controls!$B$7) -> 71930.54
A44: Office Running Costs | B44: =SUMIFS(MM_FixedCost!$F$5:$F$78,MM_FixedCost!$C$5:$C$78,"Office Running costs") -> 498375.13 | C44: =B44 -> 498375.13 | D44: =F44 -> 194888.67 | E44: =F44 -> 194888.67 | F44: =SUMIFS(Nominal_Activity!$M$2:$M$3000,Nominal_Activity!$N$2:$N$3000,"Office Running costs",Nominal_Activity!$G$2:$G$3000,">="&DATE(Controls!$B$5,1,1),Nominal_Activity!$G$2:$G$3000,"<="&Controls!$B$4,Nominal_Activity!$A$2:$A$3000,Controls!$B$7) -> 194888.67
A45: Financial Charges | B45: =SUMIFS(MM_FixedCost!$F$5:$F$78,MM_FixedCost!$C$5:$C$78,"Financial Charges") -> 45000 | C45: =B45 -> 45000 | D45: =F45 -> 26331.8 | E45: =F45 -> 26331.8 | F45: =SUMIFS(Nominal_Activity!$M$2:$M$3000,Nominal_Activity!$N$2:$N$3000,"Financial Charges",Nominal_Activity!$G$2:$G$3000,">="&DATE(Controls!$B$5,1,1),Nominal_Activity!$G$2:$G$3000,"<="&Controls!$B$4,Nominal_Activity!$A$2:$A$3000,Controls!$B$7) -> 26331.8
A46: Foreign Exchange Losses / (Gains) | B46: =SUMIFS(MM_FixedCost!$F$5:$F$78,MM_FixedCost!$C$5:$C$78,"Foreign Exchange Losses / (Gains)") -> 0 | C46: =B46 -> 0 | D46: =F46 -> -116128.53 | E46: =F46 -> -116128.53 | F46: =SUMIFS(Nominal_Activity!$M$2:$M$3000,Nominal_Activity!$N$2:$N$3000,"Foreign Exchange Losses / (Gains)",Nominal_Activity!$G$2:$G$3000,">="&DATE(Controls!$B$5,1,1),Nominal_Activity!$G$2:$G$3000,"<="&Controls!$B$4,Nominal_Activity!$A$2:$A$3000,Controls!$B$7) -> -116128.53
A47: TOTAL OPERATING COSTS | B47: =B37+SUM(B38:B46) -> 13774372 | C47: =C37+SUM(C38:C46) -> 13774372 | D47: =D37+SUM(D38:D46) -> 5801713.6 | E47: =E37+SUM(E38:E46) -> 5801713.6 | F47: =F37+SUM(F38:F46) -> 5801713.6 | I47: =IFERROR(F47/B47,0) -> 0.42119625
A49: Other Income
A50: Cost Recovery from Regions | D50: =F50 -> 0 | E50: =F50 -> 0 | F50: =-SUMIFS(Nominal_Activity!$M$2:$M$3000,Nominal_Activity!$R$2:$R$3000,"Other Income — Cost Recovery",Nominal_Activity!$G$2:$G$3000,">="&DATE(Controls!$B$5,1,1),Nominal_Activity!$G$2:$G$3000,"<="&Controls!$B$4,Nominal_Activity!$A$2:$A$3000,Controls!$B$7) -> 0
A51: Interest Received | B51: =QMR_Inputs!B15 -> 0 | D51: =F51 -> 0 | E51: =F51 -> 0 | F51: =QMR_Inputs!C15 -> 0
A52: Miscellaneous Income (programme contributions to office costs) | D52: =F52 -> 186796.18 | E52: =F52 -> 186796.18 | F52: =-SUMIFS(Nominal_Activity!$M$2:$M$3000,Nominal_Activity!$R$2:$R$3000,"Other Income — Miscellaneous",Nominal_Activity!$G$2:$G$3000,">="&DATE(Controls!$B$5,1,1),Nominal_Activity!$G$2:$G$3000,"<="&Controls!$B$4,Nominal_Activity!$A$2:$A$3000,Controls!$B$7) -> 186796.18
A53: Total Other Income | B53: =Controls!$B$20 -> 1426884.1 | C53: =Controls!$B$21 -> 0 | D53: =SUM(D50:D52) -> 186796.18 | E53: =SUM(E50:E52) -> 186796.18 | F53: =SUM(F50:F52) -> 186796.18
A55: Net Result
A56: Net Deficit / Surplus (before Depreciation and Tax) | B56: =B29-B47+B53 -> -9006297.4 | C56: =C29-C47+C53 -> 4619009 | D56: =D29-D47+D53 -> 9252930.8 | E56: =E29-E47+E53 -> 3183101.1 | F56: =F29-F47+F53 -> 1456600.5
A57: Depreciation and Amortisation | B57: 0 | C57: 0 | D57: =F57 -> 0 | E57: =F57 -> 0 | F57: =IF(QMR_Inputs!$B$25<>0,QMR_Inputs!$B$25,SUMIFS(Trial_Balance!$H$2:$H$995,Trial_Balance!$M$2:$M$995,"Depreciation",Trial_Balance!$B$2:$B$995,Controls!$B$30,Trial_Balance!$A$2:$A$995,Controls!$B$7)+SUMIFS(Trial_Balance!$H$2:$H$995,Trial_Balance!$M$2:$M$995,"Amortisation",Trial_Balance!$B$2:$B$995,Controls!$B$30,Trial_Balance!$A$2:$A$995,Controls!$B$7)) -> 0
A58: Tax | B58: 0 | C58: 0 | D58: =F58 -> 0 | E58: =F58 -> 0 | F58: =QMR_Inputs!$B$26 -> 0
A59: Net Deficit / Surplus (after Depreciation and Tax) | B59: =B56-B57-B58 -> -9006297.4 | C59: =C56-C57-C58 -> 4619009 | D59: =D56-D57-D58 -> 9252930.8 | E59: =E56-E57-E58 -> 3183101.1 | F59: =F56-F57-F58 -> 1456600.5
A60: % Surplus (of Total Operating Income) | B60: =IFERROR(B59/B29,0) -> -2.6955358 | C60: =IFERROR(C59/C29,0) -> 0.25112344 | D60: =IFERROR(D59/D29,0) -> 0.62234499 | E60: =IFERROR(E59/E29,0) -> 0.3617975 | F60: =IFERROR(F59/F29,0) -> 0.20598131
A61: Net Fixed Costs + Depreciation + Tax as % of Total Operating Income | B61: =IFERROR((B47-B53+B57+B58)/B29,0) -> 3.6955358 | C61: =IFERROR((C47-C53+C57+C58)/C29,0) -> 0.74887656 | D61: =IFERROR((D47-D53+D57+D58)/D29,0) -> 0.37765501 | E61: =IFERROR((E47-E53+E57+E58)/E29,0) -> 0.6382025 | F61: =IFERROR((F47-F53+F57+F58)/F29,0) -> 0.79401869
A63: SECTION 2 — BALANCE SHEET
A64: Summary of the approved Balance Sheet output — full statement, quarters and charts on the Balance_Sheet tab.
A65: Line | B65: Selected Quarter | C65: Movement vs Prior
A66: Total Fixed Assets | B66: =INDEX(Balance_Sheet!$B$8:$E$8,1,VALUE(MID(Controls!$B$6,2,1))) -> 2304264.8 | C66: =Balance_Sheet!$J$8 -> 108944.17
A67: Total Current Assets | B67: =INDEX(Balance_Sheet!$B$13:$E$13,1,VALUE(MID(Controls!$B$6,2,1))) -> 8953156.5 | C67: =Balance_Sheet!$J$13 -> 1334505.7
A68: Total Assets | B68: =INDEX(Balance_Sheet!$B$17:$E$17,1,VALUE(MID(Controls!$B$6,2,1))) -> 11257421 | C68: =Balance_Sheet!$J$17 -> 1443449.9
A69: Total Current Liabilities | B69: =INDEX(Balance_Sheet!$B$18:$E$18,1,VALUE(MID(Controls!$B$6,2,1))) -> -3241948.6 | C69: =Balance_Sheet!$J$18 -> -85263.18
A70: Long Term Liabilities | B70: =INDEX(Balance_Sheet!$B$21:$E$21,1,VALUE(MID(Controls!$B$6,2,1))) -> -0.33 | C70: =Balance_Sheet!$J$21 -> 0
A71: Total Liabilities | B71: =INDEX(Balance_Sheet!$B$23:$E$23,1,VALUE(MID(Controls!$B$6,2,1))) -> -3241949 | C71: =Balance_Sheet!$J$23 -> -85263.18
A72: Total Assets Less Liabilities | B72: =INDEX(Balance_Sheet!$B$24:$E$24,1,VALUE(MID(Controls!$B$6,2,1))) -> 8015472.3 | C72: =Balance_Sheet!$J$24 -> 1358186.7
A73: Total Capital and Reserves | B73: =INDEX(Balance_Sheet!$B$25:$E$25,1,VALUE(MID(Controls!$B$6,2,1))) -> -8015472.3 | C73: =Balance_Sheet!$J$25 -> -1358186.7
A74: Current Ratio | B74: =INDEX(Balance_Sheet!$C$33:$F$33,1,VALUE(MID(Controls!$B$6,2,1))) -> 2.761659
A75: Working Capital | B75: =INDEX(Balance_Sheet!$C$34:$F$34,1,VALUE(MID(Controls!$B$6,2,1))) -> 5711207.9
A76: Months of Core Cost Cover | B76: =INDEX(Balance_Sheet!$C$36:$F$36,1,VALUE(MID(Controls!$B$6,2,1))) -> 5.7737739
A77: Intercompany Net Position | B77: =INDEX(Balance_Sheet!$C$37:$F$37,1,VALUE(MID(Controls!$B$6,2,1))) -> 134284.6
A79: SECTION 3 — GROUP COSTS
A80: Group costs by function (source: Group finance pack — entered on QMR_Inputs block 5).
A81: Function | B81: Personnel | C81: Purchases | D81: Total
A82: =QMR_Inputs!A30 -> FinOps | B82: =QMR_Inputs!B30 -> 0 | C82: =QMR_Inputs!C30 -> 0 | D82: =QMR_Inputs!D30 -> 0
A83: =QMR_Inputs!A31 -> Business Development | B83: =QMR_Inputs!B31 -> 0 | C83: =QMR_Inputs!C31 -> 0 | D83: =QMR_Inputs!D31 -> 0
A84: =QMR_Inputs!A32 -> Comms | B84: =QMR_Inputs!B32 -> 0 | C84: =QMR_Inputs!C32 -> 0 | D84: =QMR_Inputs!D32 -> 0
A85: =QMR_Inputs!A33 -> Data | B85: =QMR_Inputs!B33 -> 0 | C85: =QMR_Inputs!C33 -> 0 | D85: =QMR_Inputs!D33 -> 0
A86: =QMR_Inputs!A34 -> IT | B86: =QMR_Inputs!B34 -> 0 | C86: =QMR_Inputs!C34 -> 0 | D86: =QMR_Inputs!D34 -> 0
A87: =QMR_Inputs!A35 -> Training | B87: =QMR_Inputs!B35 -> 0 | C87: =QMR_Inputs!C35 -> 0 | D87: =QMR_Inputs!D35 -> 0
A88: Total Group Costs | B88: =QMR_Inputs!B36 -> 0 | C88: =QMR_Inputs!C36 -> 0 | D88: =QMR_Inputs!D36 -> 0
A89: Total Group Budget | B89: =QMR_Inputs!B37 -> 0
A91: Notes: FY Forecast for cost lines = Annual Budget (no reforecast maintained). Project income budgets by portfolio and type are maintained on QMR_Inputs block 6 (see Section 4); the budget column at subtotal level comes from those inputs. Group contribution and payroll lines are inputs pending a group data feed.
A93: SECTION 4 — PROJECT INCOME: BUDGET VS ACTUAL
A94: Budgets entered on QMR_Inputs block 6; forecast and net invoiced YTD from Project_Forecast for the selected period.
A95: Portfolio | B95: Annual_Budget | C95: Net_Forecast | D95: Net_Invoiced_YTD | E95: Fcst_vs_Budget | F95: Inv_vs_Budget_%
A96: =QMR_Inputs!A41 -> Responsible Production | B96: =QMR_Inputs!B41 -> 0 | C96: =SUMIFS(Project_Forecast!$N$2:$N$393,Project_Forecast!$E$2:$E$393,$A96,Project_Forecast!$B$2:$B$393,Controls!$B$30,Project_Forecast!$A$2:$A$393,Controls!$B$7) -> 9760078 | D96: =SUMIFS(Project_Forecast!$S$2:$S$393,Project_Forecast!$E$2:$E$393,$A96,Project_Forecast!$B$2:$B$393,Controls!$B$30,Project_Forecast!$A$2:$A$393,Controls!$B$7) -> 3453417.1 | E96: =C96-B96 -> 9760078 | F96: =IFERROR(D96/B96,"-") -> -
A97: =QMR_Inputs!A42 -> Responsible Sourcing | B97: =QMR_Inputs!B42 -> 0 | C97: =SUMIFS(Project_Forecast!$N$2:$N$393,Project_Forecast!$E$2:$E$393,$A97,Project_Forecast!$B$2:$B$393,Controls!$B$30,Project_Forecast!$A$2:$A$393,Controls!$B$7) -> 4090375 | D97: =SUMIFS(Project_Forecast!$S$2:$S$393,Project_Forecast!$E$2:$E$393,$A97,Project_Forecast!$B$2:$B$393,Controls!$B$30,Project_Forecast!$A$2:$A$393,Controls!$B$7) -> 2115791.8 | E97: =C97-B97 -> 4090375 | F97: =IFERROR(D97/B97,"-") -> -
A98: =QMR_Inputs!A43 -> Responsible Finance | B98: =QMR_Inputs!B43 -> 0 | C98: =SUMIFS(Project_Forecast!$N$2:$N$393,Project_Forecast!$E$2:$E$393,$A98,Project_Forecast!$B$2:$B$393,Controls!$B$30,Project_Forecast!$A$2:$A$393,Controls!$B$7) -> 1566964.4 | D98: =SUMIFS(Project_Forecast!$S$2:$S$393,Project_Forecast!$E$2:$E$393,$A98,Project_Forecast!$B$2:$B$393,Controls!$B$30,Project_Forecast!$A$2:$A$393,Controls!$B$7) -> 926510.29 | E98: =C98-B98 -> 1566964.4 | F98: =IFERROR(D98/B98,"-") -> -
A99: =QMR_Inputs!A44 -> Collaboration | B99: =QMR_Inputs!B44 -> 0 | C99: =SUMIFS(Project_Forecast!$N$2:$N$393,Project_Forecast!$E$2:$E$393,$A99,Project_Forecast!$B$2:$B$393,Controls!$B$30,Project_Forecast!$A$2:$A$393,Controls!$B$7) -> 128400 | D99: =SUMIFS(Project_Forecast!$S$2:$S$393,Project_Forecast!$E$2:$E$393,$A99,Project_Forecast!$B$2:$B$393,Controls!$B$30,Project_Forecast!$A$2:$A$393,Controls!$B$7) -> 0 | E99: =C99-B99 -> 128400 | F99: =IFERROR(D99/B99,"-") -> -
A100: =QMR_Inputs!A45 -> Production Landscape | B100: =QMR_Inputs!B45 -> 0 | C100: =SUMIFS(Project_Forecast!$N$2:$N$393,Project_Forecast!$E$2:$E$393,$A100,Project_Forecast!$B$2:$B$393,Controls!$B$30,Project_Forecast!$A$2:$A$393,Controls!$B$7) -> 0 | D100: =SUMIFS(Project_Forecast!$S$2:$S$393,Project_Forecast!$E$2:$E$393,$A100,Project_Forecast!$B$2:$B$393,Controls!$B$30,Project_Forecast!$A$2:$A$393,Controls!$B$7) -> 0 | E100: =C100-B100 -> 0 | F100: =IFERROR(D100/B100,"-") -> -
A101: =QMR_Inputs!A46 -> Policy & Regulation | B101: =QMR_Inputs!B46 -> 0 | C101: =SUMIFS(Project_Forecast!$N$2:$N$393,Project_Forecast!$E$2:$E$393,$A101,Project_Forecast!$B$2:$B$393,Controls!$B$30,Project_Forecast!$A$2:$A$393,Controls!$B$7) -> 0 | D101: =SUMIFS(Project_Forecast!$S$2:$S$393,Project_Forecast!$E$2:$E$393,$A101,Project_Forecast!$B$2:$B$393,Controls!$B$30,Project_Forecast!$A$2:$A$393,Controls!$B$7) -> 0 | E101: =C101-B101 -> 0 | F101: =IFERROR(D101/B101,"-") -> -
A102: =QMR_Inputs!A47 -> Other | B102: =QMR_Inputs!B47 -> 0 | C102: =SUMIFS(Project_Forecast!$N$2:$N$393,Project_Forecast!$E$2:$E$393,$A102,Project_Forecast!$B$2:$B$393,Controls!$B$30,Project_Forecast!$A$2:$A$393,Controls!$B$7) -> 0 | D102: =SUMIFS(Project_Forecast!$S$2:$S$393,Project_Forecast!$E$2:$E$393,$A102,Project_Forecast!$B$2:$B$393,Controls!$B$30,Project_Forecast!$A$2:$A$393,Controls!$B$7) -> 0 | E102: =C102-B102 -> 0 | F102: =IFERROR(D102/B102,"-") -> -
A103: Total by Portfolio | B103: =SUM(B96:B102) -> 0 | C103: =SUM(C96:C102) -> 15545818 | D103: =SUM(D96:D102) -> 6495719.3 | E103: =C103-B103 -> 15545818 | F103: =IFERROR(D103/B103,"-") -> -
A104: By Project Type
A105: =QMR_Inputs!A51 -> External | B105: =QMR_Inputs!B51 -> 0 | C105: =SUMIFS(Project_Forecast!$N$2:$N$393,Project_Forecast!$G$2:$G$393,$A105,Project_Forecast!$B$2:$B$393,Controls!$B$30,Project_Forecast!$A$2:$A$393,Controls!$B$7) -> 10801723 | D105: =SUMIFS(Project_Forecast!$S$2:$S$393,Project_Forecast!$G$2:$G$393,$A105,Project_Forecast!$B$2:$B$393,Controls!$B$30,Project_Forecast!$A$2:$A$393,Controls!$B$7) -> 4257740.2 | E105: =C105-B105 -> 10801723 | F105: =IFERROR(D105/B105,"-") -> -
A106: =QMR_Inputs!A52 -> Internal | B106: =QMR_Inputs!B52 -> 0 | C106: =SUMIFS(Project_Forecast!$N$2:$N$393,Project_Forecast!$G$2:$G$393,$A106,Project_Forecast!$B$2:$B$393,Controls!$B$30,Project_Forecast!$A$2:$A$393,Controls!$B$7) -> 4744094.5 | D106: =SUMIFS(Project_Forecast!$S$2:$S$393,Project_Forecast!$G$2:$G$393,$A106,Project_Forecast!$B$2:$B$393,Controls!$B$30,Project_Forecast!$A$2:$A$393,Controls!$B$7) -> 2237979.1 | E106: =C106-B106 -> 4744094.5 | F106: =IFERROR(D106/B106,"-") -> -
A107: Total by Type | B107: =SUM(B105:B106) -> 0 | C107: =SUM(C105:C106) -> 15545818 | D107: =SUM(D105:D106) -> 6495719.3 | E107: =C107-B107 -> 15545818 | F107: =IFERROR(D107/B107,"-") -> -

Sheet Slide_Pack
A1: ="QMR Slide Pack — "&Controls!$B$8&" — "&Controls!$B$30&" (GHS 000)" -> QMR Slide Pack — PC Ghana — 2026-Q2 (GHS 000)
A2: All figures link to QMR_Report / Balance_Sheet. Copy tables and charts into the slide template.
A4: Slide 1 — Overview (GHS 000)
A5: Line | B5: Budget (FY) | C5: Forecast (FY) | D5: Secured (YTD) | E5: WIP (YTD) | F5: Secured vs higher of Budget/Forecast | G5: WIP vs higher of Budget/Forecast
A6: Total Project Income | B6: =QMR_Report!B23/1000 -> 0 | C6: =QMR_Report!C23/1000 -> 15545.818 | D6: =QMR_Report!D23/1000 -> 12020.285 | E6: =QMR_Report!E23/1000 -> 7459.2005 | F6: =IFERROR(D6/MAX(B6,C6),0) -> 0.77321667 | G6: =IFERROR(E6/MAX(B6,C6),0) -> 0.47982041
A7: Total Programme Income | B7: =QMR_Report!B28/1000 -> 3341.19 | C7: =QMR_Report!C28/1000 -> 2847.563 | D7: =QMR_Report!D28/1000 -> 2847.563 | E7: =QMR_Report!E28/1000 -> 1338.818 | F7: =IFERROR(D7/MAX(B7,C7),0) -> 0.85226012 | G7: =IFERROR(E7/MAX(B7,C7),0) -> 0.40070095
A8: TOTAL INCOME | B8: =QMR_Report!B29/1000 -> 3341.19 | C8: =QMR_Report!C29/1000 -> 18393.381 | D8: =QMR_Report!D29/1000 -> 14867.848 | E8: =QMR_Report!E29/1000 -> 8798.0185 | F8: =IFERROR(D8/MAX(B8,C8),0) -> 0.80832603 | G8: =IFERROR(E8/MAX(B8,C8),0) -> 0.47832526
A9: Fixed Costs | B9: =QMR_Report!B47/1000 -> 13774.372 | C9: =QMR_Report!C47/1000 -> 13774.372 | D9: =QMR_Report!F47/1000 -> 5801.7136 | E9: =QMR_Report!F47/1000 -> 5801.7136 | F9: =IFERROR(D9/MAX(B9,C9),0) -> 0.42119625 | G9: =IFERROR(E9/MAX(B9,C9),0) -> 0.42119625
A10: Other Income | B10: =QMR_Report!B53/1000 -> 1426.8842 | C10: =QMR_Report!C53/1000 -> 0 | D10: =QMR_Report!F53/1000 -> 186.79618 | E10: =QMR_Report!F53/1000 -> 186.79618 | F10: =IFERROR(D10/MAX(B10,C10),0) -> 0.13091195 | G10: =IFERROR(E10/MAX(B10,C10),0) -> 0.13091195
A11: TOTAL FIXED COSTS (after other income) | B11: =B9-B10 -> 12347.487 | C11: =C9-C10 -> 13774.372 | D11: =D9-D10 -> 5614.9174 | E11: =E9-E10 -> 5614.9174 | F11: =IFERROR(D11/MAX(B11,C11),0) -> 0.40763511 | G11: =IFERROR(E11/MAX(B11,C11),0) -> 0.40763511
A12: (Deficit)/Surplus (before depreciation and tax) | B12: =B8-B11 -> -9006.2974 | C12: =C8-C11 -> 4619.009 | D12: =D8-D11 -> 9252.9308 | E12: =E8-E11 -> 3183.1011 | F12: =IFERROR(D12/MAX(B12,C12),0) -> 2.0032286 | G12: =IFERROR(E12/MAX(B12,C12),0) -> 0.68913075
A13: (Deficit)/Surplus (after depreciation and tax) | B13: =B12-(QMR_Report!B57+QMR_Report!B58)/1000 -> -9006.2974 | C13: =C12-(QMR_Report!C57+QMR_Report!C58)/1000 -> 4619.009 | D13: =D12-(QMR_Report!F57+QMR_Report!F58)/1000 -> 9252.9308 | E13: =E12-(QMR_Report!F57+QMR_Report!F58)/1000 -> 3183.1011 | F13: =IFERROR(D13/MAX(B13,C13),0) -> 2.0032286 | G13: =IFERROR(E13/MAX(B13,C13),0) -> 0.68913075
A14: (Deficit)/Surplus % | B14: =IFERROR(B13/B8,0) -> -2.6955358 | C14: =IFERROR(C13/C8,0) -> 0.25112344 | D14: =IFERROR(D13/D8,0) -> 0.62234499 | E14: =IFERROR(E13/E8,0) -> 0.3617975
A15: Notes: "Forecast (FY)" for fixed-cost lines = Annual Budget (no separate fixed-cost reforecast is maintained — requirement 2.4 removed Forecast FY). Quarters not yet loaded show "-".
A17: Slide 2 — Fixed Costs (GHS 000) — chart & pie version
A18: Cost category | B18: Budget (FY) | C18: Forecast (FY) | D18: Actual (YTD) | E18: Actual vs Budget | F18: Actual vs Forecast | G18: % of total Budget | H18: % of total Actuals
A19: Direct Technical Costs | B19: =SUMIFS(FixedCost_Output!$C$12:$C$22,FixedCost_Output!$B$12:$B$22,$A19)/1000 -> 7230.0777 | C19: =B19 -> 7230.0777 | D19: =SUMIFS(FixedCost_Output!$E$12:$E$22,FixedCost_Output!$B$12:$B$22,$A19)/1000 -> 3229.2685 | E19: =IFERROR(D19/B19,0) -> 0.44664369 | F19: =IFERROR(D19/C19,0) -> 0.44664369 | G19: =IFERROR(B19/B$22,0) -> 0.52489347 | H19: =IFERROR(D19/D$22,0) -> 0.55660599
A20: Direct FinOps Costs | B20: =SUMIFS(FixedCost_Output!$C$12:$C$22,FixedCost_Output!$B$12:$B$22,$A20)/1000 -> 2322.68 | C20: =B20 -> 2322.68 | D20: =SUMIFS(FixedCost_Output!$E$12:$E$22,FixedCost_Output!$B$12:$B$22,$A20)/1000 -> 1287.6236 | E20: =IFERROR(D20/B20,0) -> 0.5543698 | F20: =IFERROR(D20/C20,0) -> 0.5543698 | G20: =IFERROR(B20/B$22,0) -> 0.1686233 | H20: =IFERROR(D20/D$22,0) -> 0.22193851
A21: Other Fixed Costs | B21: =SUMIFS(FixedCost_Output!$C$12:$C$22,FixedCost_Output!$B$12:$B$22,$A21)/1000 -> 4221.6138 | C21: =B21 -> 4221.6138 | D21: =SUMIFS(FixedCost_Output!$E$12:$E$22,FixedCost_Output!$B$12:$B$22,$A21)/1000 -> 1284.8214 | E21: =IFERROR(D21/B21,0) -> 0.30434365 | F21: =IFERROR(D21/C21,0) -> 0.30434365 | G21: =IFERROR(B21/B$22,0) -> 0.30648323 | H21: =IFERROR(D21/D$22,0) -> 0.2214555
A22: TOTAL | B22: =SUM(B19:B21) -> 13774.372 | C22: =SUM(C19:C21) -> 13774.372 | D22: =SUM(D19:D21) -> 5801.7136 | E22: =IFERROR(D22/B22,0) -> 0.42119625 | F22: =IFERROR(D22/C22,0) -> 0.42119625 | G22: =IFERROR(B22/B22,0) -> 1 | H22: =IFERROR(D22/D22,0) -> 1
A23: Note: Actual (YTD) reflects nominal activity through the selected quarter end only.
A25: Slide 3 — Working Capital
A26: Metric | B26: Value | C26: Note
A27: Current Ratio | B27: =INDEX(Balance_Sheet!$C$33:$F$33,1,VALUE(MID(Controls!$B$6,2,1))) -> 2.761659 | C27: 1 or more is considered good — if below 1, explain
A28: Total Current Assets ('000) | B28: =IFERROR(INDEX(Balance_Sheet!$B$13:$E$13,1,VALUE(MID(Controls!$B$6,2,1)))/1000,"-") -> 8953.1565
A29: Total Current Liabilities ('000) | B29: =IFERROR(INDEX(Balance_Sheet!$B$18:$E$18,1,VALUE(MID(Controls!$B$6,2,1)))/1000,"-") -> -3241.9486
A30: Working Capital ('000) | B30: =IFERROR(INDEX(Balance_Sheet!$C$34:$F$34,1,VALUE(MID(Controls!$B$6,2,1)))/1000,"-") -> 5711.2079 | C30: Total Current Assets less Total Current Liabilities
A31: Core Costs per Month ('000) | B31: =IFERROR(INDEX(Balance_Sheet!$C$35:$F$35,1,VALUE(MID(Controls!$B$6,2,1)))/1000,"-") -> 989.16376
A32: No. of Months' Cover | B32: =INDEX(Balance_Sheet!$C$36:$F$36,1,VALUE(MID(Controls!$B$6,2,1))) -> 5.7737739 | C32: Initial target is 3 months
A33: Core Fixed Costs ('000) | B33: =SUMIFS(MM_FixedCost!$F$5:$F$78,MM_FixedCost!$E$5:$E$78,"Core")/1000 -> 11869.965
A34: Discretionary Fixed Costs ('000) | B34: =SUMIFS(MM_FixedCost!$F$5:$F$78,MM_FixedCost!$E$5:$E$78,"Discretionary")/1000 -> 1904.4065
A35: Total Fixed Costs ('000) | B35: =FixedCost_Output!$B$3/1000 -> 13774.372
A38: Data Set 5 — Balance Sheet extract feeding Working Capital (GHS 000)
A39: Balance sheet line | B39: GHS '000
A40: Total Fixed Assets | B40: =IFERROR(INDEX(Balance_Sheet!$B$8:$E$8,1,VALUE(MID(Controls!$B$6,2,1)))/1000,"-") -> 2304.2648
A41: Total Current Assets | B41: =IFERROR(INDEX(Balance_Sheet!$B$13:$E$13,1,VALUE(MID(Controls!$B$6,2,1)))/1000,"-") -> 8953.1565
A42: Total Current Liabilities | B42: =IFERROR(INDEX(Balance_Sheet!$B$18:$E$18,1,VALUE(MID(Controls!$B$6,2,1)))/1000,"-") -> -3241.9486
A43: Long Term Liabilities | B43: =IFERROR(INDEX(Balance_Sheet!$B$21:$E$21,1,VALUE(MID(Controls!$B$6,2,1)))/1000,"-") -> -0.00033
A44: Total Assets Less Liabilities | B44: =IFERROR(INDEX(Balance_Sheet!$B$24:$E$24,1,VALUE(MID(Controls!$B$6,2,1)))/1000,"-") -> 8015.4724
A45: Total Capital and Reserves | B45: =IFERROR(INDEX(Balance_Sheet!$B$25:$E$25,1,VALUE(MID(Controls!$B$6,2,1)))/1000,"-") -> -8015.4724
A47: Note: values show "-" until the selected quarter's trial balance is loaded.

Sheet Project_Output
A1: ="Project Income and Forecast — "&Controls!$B$8 -> Project Income and Forecast — PC Ghana
A2: ="Selected period: "&Controls!$B$30&" | Net income forecast, secured position, WIP and invoicing" -> Selected period: 2026-Q2 | Net income forecast, secured position, WIP and invoicing
A3: Gross Forecast (GHS) | B3: =SUM(MM_Income!$P$5:$P$204) -> 16502775 | D3: Net Forecast (GHS) | E3: =SUMIFS(Project_Forecast!$N$2:$N$393,Project_Forecast!$B$2:$B$393,Controls!$B$30,Project_Forecast!$A$2:$A$393,Controls!$B$7) -> 15545818 | G3: Secured Net Forecast (GHS) | H3: =SUMIFS(Project_Forecast!$N$2:$N$393,Project_Forecast!$L$2:$L$393,"Secured",Project_Forecast!$B$2:$B$393,Controls!$B$30,Project_Forecast!$A$2:$A$393,Controls!$B$7) -> 12020285 | J3: WIP YTD (GHS) | K3: =SUMIFS(Project_Forecast!$AD$2:$AD$393,Project_Forecast!$B$2:$B$393,Controls!$B$30,Project_Forecast!$A$2:$A$393,Controls!$B$7) -> 7459200.5
A5: Net Invoiced YTD (GHS) | B5: =SUMIFS(Project_Forecast!$S$2:$S$393,Project_Forecast!$B$2:$B$393,Controls!$B$30,Project_Forecast!$A$2:$A$393,Controls!$B$7) -> 6495719.3 | D5: Forecast WIP — remaining qtrs | E5: =SUMIFS(Project_Forecast!$AE$2:$AE$393,Project_Forecast!$B$2:$B$393,Controls!$B$30,Project_Forecast!$A$2:$A$393,Controls!$B$7) -> 3967299.4 | G5: Management Exceptions | H5: =COUNTIFS(Project_Forecast!$AI$2:$AI$393,"REVIEW",Project_Forecast!$B$2:$B$393,Controls!$B$30,Project_Forecast!$A$2:$A$393,Controls!$B$7) -> 16 | J5: Secured vs Budget | K5: =IFERROR(H3/Controls!$B$15,0) -> 1.227213
A6: FY Gross (incl pipeline) | B6: =SUM(MM_Income!$P$5:$P$204) -> 16502775 | D6: FY Net (incl pipeline) | E6: =SUM(MM_Income!$T$5:$T$204) -> 15545818 | G6: FY Secured Net | H6: =SUMIFS(MM_Income!$T$5:$T$204,MM_Income!$U$5:$U$204,"Secured") -> 12020285 | J6: FY Pipeline Net | K6: =SUMIFS(MM_Income!$T$5:$T$204,MM_Income!$U$5:$U$204,"Pipeline") -> 3525532.3
A7: FY Weighted Net (× Prob) | B7: =SUM(MM_Income!$W$5:$W$204) -> 15146686 | D7: Full-year view from MM_Income (incl pipeline). Row 3 shows the selected reporting period.
A8: Income by Project Type and Portfolio — selected period
A9: Project_Type | B9: Portfolio | C9: Gross_Forecast | D9: Net_Forecast | E9: Secured_Net | F9: WIP_Current_Qtr | G9: WIP_Cum_YTD | H9: WIP_Fcst_Remaining | I9: Net_Invoiced_YTD | J9: WIP_Q1 | K9: WIP_Q2 | L9: WIP_Q3 | M9: WIP_Q4 | N9: Portfolio | O9: Net_Forecast | P9: Annual_Budget | Q9: Fcst_vs_Budget
A10: External | B10: Responsible Sourcing | C10: =SUMIFS(MM_Income!$P$5:$P$204,MM_Income!$C$5:$C$204,$B10,MM_Income!$G$5:$G$204,$A10) -> 0 | D10: =SUMIFS(Project_Forecast!$N$2:$N$393,Project_Forecast!$E$2:$E$393,$B10,Project_Forecast!$G$2:$G$393,$A10,Project_Forecast!$B$2:$B$393,Controls!$B$30,Project_Forecast!$A$2:$A$393,Controls!$B$7) -> 0 | E10: =SUMIFS(Project_Forecast!$N$2:$N$393,Project_Forecast!$E$2:$E$393,$B10,Project_Forecast!$G$2:$G$393,$A10,Project_Forecast!$L$2:$L$393,"Secured",Project_Forecast!$B$2:$B$393,Controls!$B$30,Project_Forecast!$A$2:$A$393,Controls!$B$7) -> 0 | F10: =CHOOSE(VALUE(MID(Controls!$B$6,2,1)),SUMIFS(Project_Forecast!$W$2:$W$393,Project_Forecast!$E$2:$E$393,$B10,Project_Forecast!$G$2:$G$393,$A10,Project_Forecast!$B$2:$B$393,Controls!$B$30,Project_Forecast!$A$2:$A$393,Controls!$B$7),SUMIFS(Project_Forecast!$Y$2:$Y$393,Project_Forecast!$E$2:$E$393,$B10,Project_Forecast!$G$2:$G$393,$A10,Project_Forecast!$B$2:$B$393,Controls!$B$30,Project_Forecast!$A$2:$A$393,Controls!$B$7),SUMIFS(Project_Forecast!$AA$2:$AA$393,Project_Forecast!$E$2:$E$393,$B10,Project_Forecast!$G$2:$G$393,$A10,Project_Forecast!$B$2:$B$393,Controls!$B$30,Project_Forecast!$A$2:$A$393,Controls!$B$7),SUMIFS(Project_Forecast!$AC$2:$AC$393,Project_Forecast!$E$2:$E$393,$B10,Project_Forecast!$G$2:$G$393,$A10,Project_Forecast!$B$2:$B$393,Controls!$B$30,Project_Forecast!$A$2:$A$393,Controls!$B$7)) -> 0 | G10: =SUMIFS(Project_Forecast!$AD$2:$AD$393,Project_Forecast!$E$2:$E$393,$B10,Project_Forecast!$G$2:$G$393,$A10,Project_Forecast!$B$2:$B$393,Controls!$B$30,Project_Forecast!$A$2:$A$393,Controls!$B$7) -> 0 | H10: =SUMIFS(Project_Forecast!$AE$2:$AE$393,Project_Forecast!$E$2:$E$393,$B10,Project_Forecast!$G$2:$G$393,$A10,Project_Forecast!$B$2:$B$393,Controls!$B$30,Project_Forecast!$A$2:$A$393,Controls!$B$7) -> 0 | I10: =SUMIFS(Project_Forecast!$S$2:$S$393,Project_Forecast!$E$2:$E$393,$B10,Project_Forecast!$G$2:$G$393,$A10,Project_Forecast!$B$2:$B$393,Controls!$B$30,Project_Forecast!$A$2:$A$393,Controls!$B$7) -> 0 | J10: =SUMIFS(Project_Forecast!$W$2:$W$393,Project_Forecast!$E$2:$E$393,$B10,Project_Forecast!$G$2:$G$393,$A10,Project_Forecast!$B$2:$B$393,Controls!$B$30,Project_Forecast!$A$2:$A$393,Controls!$B$7) -> 0 | K10: =SUMIFS(Project_Forecast!$Y$2:$Y$393,Project_Forecast!$E$2:$E$393,$B10,Project_Forecast!$G$2:$G$393,$A10,Project_Forecast!$B$2:$B$393,Controls!$B$30,Project_Forecast!$A$2:$A$393,Controls!$B$7) -> 0 | L10: =SUMIFS(Project_Forecast!$AA$2:$AA$393,Project_Forecast!$E$2:$E$393,$B10,Project_Forecast!$G$2:$G$393,$A10,Project_Forecast!$B$2:$B$393,Controls!$B$30,Project_Forecast!$A$2:$A$393,Controls!$B$7) -> 0 | M10: =SUMIFS(Project_Forecast!$AC$2:$AC$393,Project_Forecast!$E$2:$E$393,$B10,Project_Forecast!$G$2:$G$393,$A10,Project_Forecast!$B$2:$B$393,Controls!$B$30,Project_Forecast!$A$2:$A$393,Controls!$B$7) -> 0 | N10: Responsible Sourcing | O10: =SUMIFS(Project_Forecast!$N$2:$N$393,Project_Forecast!$E$2:$E$393,$N10,Project_Forecast!$B$2:$B$393,Controls!$B$30,Project_Forecast!$A$2:$A$393,Controls!$B$7) -> 4090375 | P10: =IFERROR(INDEX(QMR_Inputs!$B$41:$B$47,MATCH($N10,QMR_Inputs!$A$41:$A$47,0)),0) -> 0 | Q10: =O10-P10 -> 4090375
A11: External | B11: Responsible Production | C11: =SUMIFS(MM_Income!$P$5:$P$204,MM_Income!$C$5:$C$204,$B11,MM_Income!$G$5:$G$204,$A11) -> 10453806 | D11: =SUMIFS(Project_Forecast!$N$2:$N$393,Project_Forecast!$E$2:$E$393,$B11,Project_Forecast!$G$2:$G$393,$A11,Project_Forecast!$B$2:$B$393,Controls!$B$30,Project_Forecast!$A$2:$A$393,Controls!$B$7) -> 9760078 | E11: =SUMIFS(Project_Forecast!$N$2:$N$393,Project_Forecast!$E$2:$E$393,$B11,Project_Forecast!$G$2:$G$393,$A11,Project_Forecast!$L$2:$L$393,"Secured",Project_Forecast!$B$2:$B$393,Controls!$B$30,Project_Forecast!$A$2:$A$393,Controls!$B$7) -> 6643820.7 | F11: =CHOOSE(VALUE(MID(Controls!$B$6,2,1)),SUMIFS(Project_Forecast!$W$2:$W$393,Project_Forecast!$E$2:$E$393,$B11,Project_Forecast!$G$2:$G$393,$A11,Project_Forecast!$B$2:$B$393,Controls!$B$30,Project_Forecast!$A$2:$A$393,Controls!$B$7),SUMIFS(Project_Forecast!$Y$2:$Y$393,Project_Forecast!$E$2:$E$393,$B11,Project_Forecast!$G$2:$G$393,$A11,Project_Forecast!$B$2:$B$393,Controls!$B$30,Project_Forecast!$A$2:$A$393,Controls!$B$7),SUMIFS(Project_Forecast!$AA$2:$AA$393,Project_Forecast!$E$2:$E$393,$B11,Project_Forecast!$G$2:$G$393,$A11,Project_Forecast!$B$2:$B$393,Controls!$B$30,Project_Forecast!$A$2:$A$393,Controls!$B$7),SUMIFS(Project_Forecast!$AC$2:$AC$393,Project_Forecast!$E$2:$E$393,$B11,Project_Forecast!$G$2:$G$393,$A11,Project_Forecast!$B$2:$B$393,Controls!$B$30,Project_Forecast!$A$2:$A$393,Controls!$B$7)) -> 1597445.6 | G11: =SUMIFS(Project_Forecast!$AD$2:$AD$393,Project_Forecast!$E$2:$E$393,$B11,Project_Forecast!$G$2:$G$393,$A11,Project_Forecast!$B$2:$B$393,Controls!$B$30,Project_Forecast!$A$2:$A$393,Controls!$B$7) -> 4656235.4 | H11: =SUMIFS(Project_Forecast!$AE$2:$AE$393,Project_Forecast!$E$2:$E$393,$B11,Project_Forecast!$G$2:$G$393,$A11,Project_Forecast!$B$2:$B$393,Controls!$B$30,Project_Forecast!$A$2:$A$393,Controls!$B$7) -> 1865512.9 | I11: =SUMIFS(Project_Forecast!$S$2:$S$393,Project_Forecast!$E$2:$E$393,$B11,Project_Forecast!$G$2:$G$393,$A11,Project_Forecast!$B$2:$B$393,Controls!$B$30,Project_Forecast!$A$2:$A$393,Controls!$B$7) -> 3453417.1 | J11: =SUMIFS(Project_Forecast!$W$2:$W$393,Project_Forecast!$E$2:$E$393,$B11,Project_Forecast!$G$2:$G$393,$A11,Project_Forecast!$B$2:$B$393,Controls!$B$30,Project_Forecast!$A$2:$A$393,Controls!$B$7) -> 3058789.8 | K11: =SUMIFS(Project_Forecast!$Y$2:$Y$393,Project_Forecast!$E$2:$E$393,$B11,Project_Forecast!$G$2:$G$393,$A11,Project_Forecast!$B$2:$B$393,Controls!$B$30,Project_Forecast!$A$2:$A$393,Controls!$B$7) -> 1597445.6 | L11: =SUMIFS(Project_Forecast!$AA$2:$AA$393,Project_Forecast!$E$2:$E$393,$B11,Project_Forecast!$G$2:$G$393,$A11,Project_Forecast!$B$2:$B$393,Controls!$B$30,Project_Forecast!$A$2:$A$393,Controls!$B$7) -> 977984.14 | M11: =SUMIFS(Project_Forecast!$AC$2:$AC$393,Project_Forecast!$E$2:$E$393,$B11,Project_Forecast!$G$2:$G$393,$A11,Project_Forecast!$B$2:$B$393,Controls!$B$30,Project_Forecast!$A$2:$A$393,Controls!$B$7) -> 887528.73 | N11: Responsible Production | O11: =SUMIFS(Project_Forecast!$N$2:$N$393,Project_Forecast!$E$2:$E$393,$N11,Project_Forecast!$B$2:$B$393,Controls!$B$30,Project_Forecast!$A$2:$A$393,Controls!$B$7) -> 9760078 | P11: =IFERROR(INDEX(QMR_Inputs!$B$41:$B$47,MATCH($N11,QMR_Inputs!$A$41:$A$47,0)),0) -> 0 | Q11: =O11-P11 -> 9760078
A12: External | B12: Responsible Finance | C12: =SUMIFS(MM_Income!$P$5:$P$204,MM_Income!$C$5:$C$204,$B12,MM_Income!$G$5:$G$204,$A12) -> 913245 | D12: =SUMIFS(Project_Forecast!$N$2:$N$393,Project_Forecast!$E$2:$E$393,$B12,Project_Forecast!$G$2:$G$393,$A12,Project_Forecast!$B$2:$B$393,Controls!$B$30,Project_Forecast!$A$2:$A$393,Controls!$B$7) -> 913245 | E12: =SUMIFS(Project_Forecast!$N$2:$N$393,Project_Forecast!$E$2:$E$393,$B12,Project_Forecast!$G$2:$G$393,$A12,Project_Forecast!$L$2:$L$393,"Secured",Project_Forecast!$B$2:$B$393,Controls!$B$30,Project_Forecast!$A$2:$A$393,Controls!$B$7) -> 913245 | F12: =CHOOSE(VALUE(MID(Controls!$B$6,2,1)),SUMIFS(Project_Forecast!$W$2:$W$393,Project_Forecast!$E$2:$E$393,$B12,Project_Forecast!$G$2:$G$393,$A12,Project_Forecast!$B$2:$B$393,Controls!$B$30,Project_Forecast!$A$2:$A$393,Controls!$B$7),SUMIFS(Project_Forecast!$Y$2:$Y$393,Project_Forecast!$E$2:$E$393,$B12,Project_Forecast!$G$2:$G$393,$A12,Project_Forecast!$B$2:$B$393,Controls!$B$30,Project_Forecast!$A$2:$A$393,Controls!$B$7),SUMIFS(Project_Forecast!$AA$2:$AA$393,Project_Forecast!$E$2:$E$393,$B12,Project_Forecast!$G$2:$G$393,$A12,Project_Forecast!$B$2:$B$393,Controls!$B$30,Project_Forecast!$A$2:$A$393,Controls!$B$7),SUMIFS(Project_Forecast!$AC$2:$AC$393,Project_Forecast!$E$2:$E$393,$B12,Project_Forecast!$G$2:$G$393,$A12,Project_Forecast!$B$2:$B$393,Controls!$B$30,Project_Forecast!$A$2:$A$393,Controls!$B$7)) -> 61166.55 | G12: =SUMIFS(Project_Forecast!$AD$2:$AD$393,Project_Forecast!$E$2:$E$393,$B12,Project_Forecast!$G$2:$G$393,$A12,Project_Forecast!$B$2:$B$393,Controls!$B$30,Project_Forecast!$A$2:$A$393,Controls!$B$7) -> 696184.8 | H12: =SUMIFS(Project_Forecast!$AE$2:$AE$393,Project_Forecast!$E$2:$E$393,$B12,Project_Forecast!$G$2:$G$393,$A12,Project_Forecast!$B$2:$B$393,Controls!$B$30,Project_Forecast!$A$2:$A$393,Controls!$B$7) -> 217060.2 | I12: =SUMIFS(Project_Forecast!$S$2:$S$393,Project_Forecast!$E$2:$E$393,$B12,Project_Forecast!$G$2:$G$393,$A12,Project_Forecast!$B$2:$B$393,Controls!$B$30,Project_Forecast!$A$2:$A$393,Controls!$B$7) -> 804323.04 | J12: =SUMIFS(Project_Forecast!$W$2:$W$393,Project_Forecast!$E$2:$E$393,$B12,Project_Forecast!$G$2:$G$393,$A12,Project_Forecast!$B$2:$B$393,Controls!$B$30,Project_Forecast!$A$2:$A$393,Controls!$B$7) -> 635018.25 | K12: =SUMIFS(Project_Forecast!$Y$2:$Y$393,Project_Forecast!$E$2:$E$393,$B12,Project_Forecast!$G$2:$G$393,$A12,Project_Forecast!$B$2:$B$393,Controls!$B$30,Project_Forecast!$A$2:$A$393,Controls!$B$7) -> 61166.55 | L12: =SUMIFS(Project_Forecast!$AA$2:$AA$393,Project_Forecast!$E$2:$E$393,$B12,Project_Forecast!$G$2:$G$393,$A12,Project_Forecast!$B$2:$B$393,Controls!$B$30,Project_Forecast!$A$2:$A$393,Controls!$B$7) -> 124034.4 | M12: =SUMIFS(Project_Forecast!$AC$2:$AC$393,Project_Forecast!$E$2:$E$393,$B12,Project_Forecast!$G$2:$G$393,$A12,Project_Forecast!$B$2:$B$393,Controls!$B$30,Project_Forecast!$A$2:$A$393,Controls!$B$7) -> 93025.8 | N12: Responsible Finance | O12: =SUMIFS(Project_Forecast!$N$2:$N$393,Project_Forecast!$E$2:$E$393,$N12,Project_Forecast!$B$2:$B$393,Controls!$B$30,Project_Forecast!$A$2:$A$393,Controls!$B$7) -> 1566964.4 | P12: =IFERROR(INDEX(QMR_Inputs!$B$41:$B$47,MATCH($N12,QMR_Inputs!$A$41:$A$47,0)),0) -> 0 | Q12: =O12-P12 -> 1566964.4
A13: External | B13: Collaboration | C13: =SUMIFS(MM_Income!$P$5:$P$204,MM_Income!$C$5:$C$204,$B13,MM_Income!$G$5:$G$204,$A13) -> 128400 | D13: =SUMIFS(Project_Forecast!$N$2:$N$393,Project_Forecast!$E$2:$E$393,$B13,Project_Forecast!$G$2:$G$393,$A13,Project_Forecast!$B$2:$B$393,Controls!$B$30,Project_Forecast!$A$2:$A$393,Controls!$B$7) -> 128400 | E13: =SUMIFS(Project_Forecast!$N$2:$N$393,Project_Forecast!$E$2:$E$393,$B13,Project_Forecast!$G$2:$G$393,$A13,Project_Forecast!$L$2:$L$393,"Secured",Project_Forecast!$B$2:$B$393,Controls!$B$30,Project_Forecast!$A$2:$A$393,Controls!$B$7) -> 128400 | F13: =CHOOSE(VALUE(MID(Controls!$B$6,2,1)),SUMIFS(Project_Forecast!$W$2:$W$393,Project_Forecast!$E$2:$E$393,$B13,Project_Forecast!$G$2:$G$393,$A13,Project_Forecast!$B$2:$B$393,Controls!$B$30,Project_Forecast!$A$2:$A$393,Controls!$B$7),SUMIFS(Project_Forecast!$Y$2:$Y$393,Project_Forecast!$E$2:$E$393,$B13,Project_Forecast!$G$2:$G$393,$A13,Project_Forecast!$B$2:$B$393,Controls!$B$30,Project_Forecast!$A$2:$A$393,Controls!$B$7),SUMIFS(Project_Forecast!$AA$2:$AA$393,Project_Forecast!$E$2:$E$393,$B13,Project_Forecast!$G$2:$G$393,$A13,Project_Forecast!$B$2:$B$393,Controls!$B$30,Project_Forecast!$A$2:$A$393,Controls!$B$7),SUMIFS(Project_Forecast!$AC$2:$AC$393,Project_Forecast!$E$2:$E$393,$B13,Project_Forecast!$G$2:$G$393,$A13,Project_Forecast!$B$2:$B$393,Controls!$B$30,Project_Forecast!$A$2:$A$393,Controls!$B$7)) -> 64200 | G13: =SUMIFS(Project_Forecast!$AD$2:$AD$393,Project_Forecast!$E$2:$E$393,$B13,Project_Forecast!$G$2:$G$393,$A13,Project_Forecast!$B$2:$B$393,Controls!$B$30,Project_Forecast!$A$2:$A$393,Controls!$B$7) -> 64200 | H13: =SUMIFS(Project_Forecast!$AE$2:$AE$393,Project_Forecast!$E$2:$E$393,$B13,Project_Forecast!$G$2:$G$393,$A13,Project_Forecast!$B$2:$B$393,Controls!$B$30,Project_Forecast!$A$2:$A$393,Controls!$B$7) -> 64200 | I13: =SUMIFS(Project_Forecast!$S$2:$S$393,Project_Forecast!$E$2:$E$393,$B13,Project_Forecast!$G$2:$G$393,$A13,Project_Forecast!$B$2:$B$393,Controls!$B$30,Project_Forecast!$A$2:$A$393,Controls!$B$7) -> 0 | J13: =SUMIFS(Project_Forecast!$W$2:$W$393,Project_Forecast!$E$2:$E$393,$B13,Project_Forecast!$G$2:$G$393,$A13,Project_Forecast!$B$2:$B$393,Controls!$B$30,Project_Forecast!$A$2:$A$393,Controls!$B$7) -> 0 | K13: =SUMIFS(Project_Forecast!$Y$2:$Y$393,Project_Forecast!$E$2:$E$393,$B13,Project_Forecast!$G$2:$G$393,$A13,Project_Forecast!$B$2:$B$393,Controls!$B$30,Project_Forecast!$A$2:$A$393,Controls!$B$7) -> 64200 | L13: =SUMIFS(Project_Forecast!$AA$2:$AA$393,Project_Forecast!$E$2:$E$393,$B13,Project_Forecast!$G$2:$G$393,$A13,Project_Forecast!$B$2:$B$393,Controls!$B$30,Project_Forecast!$A$2:$A$393,Controls!$B$7) -> 32100 | M13: =SUMIFS(Project_Forecast!$AC$2:$AC$393,Project_Forecast!$E$2:$E$393,$B13,Project_Forecast!$G$2:$G$393,$A13,Project_Forecast!$B$2:$B$393,Controls!$B$30,Project_Forecast!$A$2:$A$393,Controls!$B$7) -> 32100 | N13: Collaboration | O13: =SUMIFS(Project_Forecast!$N$2:$N$393,Project_Forecast!$E$2:$E$393,$N13,Project_Forecast!$B$2:$B$393,Controls!$B$30,Project_Forecast!$A$2:$A$393,Controls!$B$7) -> 128400 | P13: =IFERROR(INDEX(QMR_Inputs!$B$41:$B$47,MATCH($N13,QMR_Inputs!$A$41:$A$47,0)),0) -> 0 | Q13: =O13-P13 -> 128400
A14: External | B14: Production Landscape | C14: =SUMIFS(MM_Income!$P$5:$P$204,MM_Income!$C$5:$C$204,$B14,MM_Income!$G$5:$G$204,$A14) -> 0 | D14: =SUMIFS(Project_Forecast!$N$2:$N$393,Project_Forecast!$E$2:$E$393,$B14,Project_Forecast!$G$2:$G$393,$A14,Project_Forecast!$B$2:$B$393,Controls!$B$30,Project_Forecast!$A$2:$A$393,Controls!$B$7) -> 0 | E14: =SUMIFS(Project_Forecast!$N$2:$N$393,Project_Forecast!$E$2:$E$393,$B14,Project_Forecast!$G$2:$G$393,$A14,Project_Forecast!$L$2:$L$393,"Secured",Project_Forecast!$B$2:$B$393,Controls!$B$30,Project_Forecast!$A$2:$A$393,Controls!$B$7) -> 0 | F14: =CHOOSE(VALUE(MID(Controls!$B$6,2,1)),SUMIFS(Project_Forecast!$W$2:$W$393,Project_Forecast!$E$2:$E$393,$B14,Project_Forecast!$G$2:$G$393,$A14,Project_Forecast!$B$2:$B$393,Controls!$B$30,Project_Forecast!$A$2:$A$393,Controls!$B$7),SUMIFS(Project_Forecast!$Y$2:$Y$393,Project_Forecast!$E$2:$E$393,$B14,Project_Forecast!$G$2:$G$393,$A14,Project_Forecast!$B$2:$B$393,Controls!$B$30,Project_Forecast!$A$2:$A$393,Controls!$B$7),SUMIFS(Project_Forecast!$AA$2:$AA$393,Project_Forecast!$E$2:$E$393,$B14,Project_Forecast!$G$2:$G$393,$A14,Project_Forecast!$B$2:$B$393,Controls!$B$30,Project_Forecast!$A$2:$A$393,Controls!$B$7),SUMIFS(Project_Forecast!$AC$2:$AC$393,Project_Forecast!$E$2:$E$393,$B14,Project_Forecast!$G$2:$G$393,$A14,Project_Forecast!$B$2:$B$393,Controls!$B$30,Project_Forecast!$A$2:$A$393,Controls!$B$7)) -> 0 | G14: =SUMIFS(Project_Forecast!$AD$2:$AD$393,Project_Forecast!$E$2:$E$393,$B14,Project_Forecast!$G$2:$G$393,$A14,Project_Forecast!$B$2:$B$393,Controls!$B$30,Project_Forecast!$A$2:$A$393,Controls!$B$7) -> 0 | H14: =SUMIFS(Project_Forecast!$AE$2:$AE$393,Project_Forecast!$E$2:$E$393,$B14,Project_Forecast!$G$2:$G$393,$A14,Project_Forecast!$B$2:$B$393,Controls!$B$30,Project_Forecast!$A$2:$A$393,Controls!$B$7) -> 0 | I14: =SUMIFS(Project_Forecast!$S$2:$S$393,Project_Forecast!$E$2:$E$393,$B14,Project_Forecast!$G$2:$G$393,$A14,Project_Forecast!$B$2:$B$393,Controls!$B$30,Project_Forecast!$A$2:$A$393,Controls!$B$7) -> 0 | J14: =SUMIFS(Project_Forecast!$W$2:$W$393,Project_Forecast!$E$2:$E$393,$B14,Project_Forecast!$G$2:$G$393,$A14,Project_Forecast!$B$2:$B$393,Controls!$B$30,Project_Forecast!$A$2:$A$393,Controls!$B$7) -> 0 | K14: =SUMIFS(Project_Forecast!$Y$2:$Y$393,Project_Forecast!$E$2:$E$393,$B14,Project_Forecast!$G$2:$G$393,$A14,Project_Forecast!$B$2:$B$393,Controls!$B$30,Project_Forecast!$A$2:$A$393,Controls!$B$7) -> 0 | L14: =SUMIFS(Project_Forecast!$AA$2:$AA$393,Project_Forecast!$E$2:$E$393,$B14,Project_Forecast!$G$2:$G$393,$A14,Project_Forecast!$B$2:$B$393,Controls!$B$30,Project_Forecast!$A$2:$A$393,Controls!$B$7) -> 0 | M14: =SUMIFS(Project_Forecast!$AC$2:$AC$393,Project_Forecast!$E$2:$E$393,$B14,Project_Forecast!$G$2:$G$393,$A14,Project_Forecast!$B$2:$B$393,Controls!$B$30,Project_Forecast!$A$2:$A$393,Controls!$B$7) -> 0 | N14: Production Landscape | O14: =SUMIFS(Project_Forecast!$N$2:$N$393,Project_Forecast!$E$2:$E$393,$N14,Project_Forecast!$B$2:$B$393,Controls!$B$30,Project_Forecast!$A$2:$A$393,Controls!$B$7) -> 0 | P14: =IFERROR(INDEX(QMR_Inputs!$B$41:$B$47,MATCH($N14,QMR_Inputs!$A$41:$A$47,0)),0) -> 0 | Q14: =O14-P14 -> 0
A15: External | B15: Policy & Regulation | C15: =SUMIFS(MM_Income!$P$5:$P$204,MM_Income!$C$5:$C$204,$B15,MM_Income!$G$5:$G$204,$A15) -> 0 | D15: =SUMIFS(Project_Forecast!$N$2:$N$393,Project_Forecast!$E$2:$E$393,$B15,Project_Forecast!$G$2:$G$393,$A15,Project_Forecast!$B$2:$B$393,Controls!$B$30,Project_Forecast!$A$2:$A$393,Controls!$B$7) -> 0 | E15: =SUMIFS(Project_Forecast!$N$2:$N$393,Project_Forecast!$E$2:$E$393,$B15,Project_Forecast!$G$2:$G$393,$A15,Project_Forecast!$L$2:$L$393,"Secured",Project_Forecast!$B$2:$B$393,Controls!$B$30,Project_Forecast!$A$2:$A$393,Controls!$B$7) -> 0 | F15: =CHOOSE(VALUE(MID(Controls!$B$6,2,1)),SUMIFS(Project_Forecast!$W$2:$W$393,Project_Forecast!$E$2:$E$393,$B15,Project_Forecast!$G$2:$G$393,$A15,Project_Forecast!$B$2:$B$393,Controls!$B$30,Project_Forecast!$A$2:$A$393,Controls!$B$7),SUMIFS(Project_Forecast!$Y$2:$Y$393,Project_Forecast!$E$2:$E$393,$B15,Project_Forecast!$G$2:$G$393,$A15,Project_Forecast!$B$2:$B$393,Controls!$B$30,Project_Forecast!$A$2:$A$393,Controls!$B$7),SUMIFS(Project_Forecast!$AA$2:$AA$393,Project_Forecast!$E$2:$E$393,$B15,Project_Forecast!$G$2:$G$393,$A15,Project_Forecast!$B$2:$B$393,Controls!$B$30,Project_Forecast!$A$2:$A$393,Controls!$B$7),SUMIFS(Project_Forecast!$AC$2:$AC$393,Project_Forecast!$E$2:$E$393,$B15,Project_Forecast!$G$2:$G$393,$A15,Project_Forecast!$B$2:$B$393,Controls!$B$30,Project_Forecast!$A$2:$A$393,Controls!$B$7)) -> 0 | G15: =SUMIFS(Project_Forecast!$AD$2:$AD$393,Project_Forecast!$E$2:$E$393,$B15,Project_Forecast!$G$2:$G$393,$A15,Project_Forecast!$B$2:$B$393,Controls!$B$30,Project_Forecast!$A$2:$A$393,Controls!$B$7) -> 0 | H15: =SUMIFS(Project_Forecast!$AE$2:$AE$393,Project_Forecast!$E$2:$E$393,$B15,Project_Forecast!$G$2:$G$393,$A15,Project_Forecast!$B$2:$B$393,Controls!$B$30,Project_Forecast!$A$2:$A$393,Controls!$B$7) -> 0 | I15: =SUMIFS(Project_Forecast!$S$2:$S$393,Project_Forecast!$E$2:$E$393,$B15,Project_Forecast!$G$2:$G$393,$A15,Project_Forecast!$B$2:$B$393,Controls!$B$30,Project_Forecast!$A$2:$A$393,Controls!$B$7) -> 0 | J15: =SUMIFS(Project_Forecast!$W$2:$W$393,Project_Forecast!$E$2:$E$393,$B15,Project_Forecast!$G$2:$G$393,$A15,Project_Forecast!$B$2:$B$393,Controls!$B$30,Project_Forecast!$A$2:$A$393,Controls!$B$7) -> 0 | K15: =SUMIFS(Project_Forecast!$Y$2:$Y$393,Project_Forecast!$E$2:$E$393,$B15,Project_Forecast!$G$2:$G$393,$A15,Project_Forecast!$B$2:$B$393,Controls!$B$30,Project_Forecast!$A$2:$A$393,Controls!$B$7) -> 0 | L15: =SUMIFS(Project_Forecast!$AA$2:$AA$393,Project_Forecast!$E$2:$E$393,$B15,Project_Forecast!$G$2:$G$393,$A15,Project_Forecast!$B$2:$B$393,Controls!$B$30,Project_Forecast!$A$2:$A$393,Controls!$B$7) -> 0 | M15: =SUMIFS(Project_Forecast!$AC$2:$AC$393,Project_Forecast!$E$2:$E$393,$B15,Project_Forecast!$G$2:$G$393,$A15,Project_Forecast!$B$2:$B$393,Controls!$B$30,Project_Forecast!$A$2:$A$393,Controls!$B$7) -> 0 | N15: Policy & Regulation | O15: =SUMIFS(Project_Forecast!$N$2:$N$393,Project_Forecast!$E$2:$E$393,$N15,Project_Forecast!$B$2:$B$393,Controls!$B$30,Project_Forecast!$A$2:$A$393,Controls!$B$7) -> 0 | P15: =IFERROR(INDEX(QMR_Inputs!$B$41:$B$47,MATCH($N15,QMR_Inputs!$A$41:$A$47,0)),0) -> 0 | Q15: =O15-P15 -> 0
B16: Subtotal — External | C16: =SUM(C10:C15) -> 11495451 | D16: =SUM(D10:D15) -> 10801723 | E16: =SUM(E10:E15) -> 7685465.7 | F16: =SUM(F10:F15) -> 1722812.2 | G16: =SUM(G10:G15) -> 5416620.2 | H16: =SUM(H10:H15) -> 2146773.1 | I16: =SUM(I10:I15) -> 4257740.2 | J16: =SUM(J10:J15) -> 3693808 | ... M16: =SUM(M10:M15) -> 1012654.5 | N16: Other | O16: =E25-SUM(O10:O15) -> -3525532.3 | P16: =IFERROR(INDEX(QMR_Inputs!$B$41:$B$47,MATCH($N16,QMR_Inputs!$A$41:$A$47,0)),0) -> 0 | Q16: =O16-P16 -> -3525532.3
A17: Internal | B17: Responsible Sourcing | C17: =SUMIFS(MM_Income!$P$5:$P$204,MM_Income!$C$5:$C$204,$B17,MM_Income!$G$5:$G$204,$A17) -> 4353604 | D17: =SUMIFS(Project_Forecast!$N$2:$N$393,Project_Forecast!$E$2:$E$393,$B17,Project_Forecast!$G$2:$G$393,$A17,Project_Forecast!$B$2:$B$393,Controls!$B$30,Project_Forecast!$A$2:$A$393,Controls!$B$7) -> 4090375 | E17: =SUMIFS(Project_Forecast!$N$2:$N$393,Project_Forecast!$E$2:$E$393,$B17,Project_Forecast!$G$2:$G$393,$A17,Project_Forecast!$L$2:$L$393,"Secured",Project_Forecast!$B$2:$B$393,Controls!$B$30,Project_Forecast!$A$2:$A$393,Controls!$B$7) -> 4090375 | F17: =CHOOSE(VALUE(MID(Controls!$B$6,2,1)),SUMIFS(Project_Forecast!$W$2:$W$393,Project_Forecast!$E$2:$E$393,$B17,Project_Forecast!$G$2:$G$393,$A17,Project_Forecast!$B$2:$B$393,Controls!$B$30,Project_Forecast!$A$2:$A$393,Controls!$B$7),SUMIFS(Project_Forecast!$Y$2:$Y$393,Project_Forecast!$E$2:$E$393,$B17,Project_Forecast!$G$2:$G$393,$A17,Project_Forecast!$B$2:$B$393,Controls!$B$30,Project_Forecast!$A$2:$A$393,Controls!$B$7),SUMIFS(Project_Forecast!$AA$2:$AA$393,Project_Forecast!$E$2:$E$393,$B17,Project_Forecast!$G$2:$G$393,$A17,Project_Forecast!$B$2:$B$393,Controls!$B$30,Project_Forecast!$A$2:$A$393,Controls!$B$7),SUMIFS(Project_Forecast!$AC$2:$AC$393,Project_Forecast!$E$2:$E$393,$B17,Project_Forecast!$G$2:$G$393,$A17,Project_Forecast!$B$2:$B$393,Controls!$B$30,Project_Forecast!$A$2:$A$393,Controls!$B$7)) -> 630036.64 | G17: =SUMIFS(Project_Forecast!$AD$2:$AD$393,Project_Forecast!$E$2:$E$393,$B17,Project_Forecast!$G$2:$G$393,$A17,Project_Forecast!$B$2:$B$393,Controls!$B$30,Project_Forecast!$A$2:$A$393,Controls!$B$7) -> 1847024.7 | H17: =SUMIFS(Project_Forecast!$AE$2:$AE$393,Project_Forecast!$E$2:$E$393,$B17,Project_Forecast!$G$2:$G$393,$A17,Project_Forecast!$B$2:$B$393,Controls!$B$30,Project_Forecast!$A$2:$A$393,Controls!$B$7) -> 1771637.4 | I17: =SUMIFS(Project_Forecast!$S$2:$S$393,Project_Forecast!$E$2:$E$393,$B17,Project_Forecast!$G$2:$G$393,$A17,Project_Forecast!$B$2:$B$393,Controls!$B$30,Project_Forecast!$A$2:$A$393,Controls!$B$7) -> 2115791.8 | J17: =SUMIFS(Project_Forecast!$W$2:$W$393,Project_Forecast!$E$2:$E$393,$B17,Project_Forecast!$G$2:$G$393,$A17,Project_Forecast!$B$2:$B$393,Controls!$B$30,Project_Forecast!$A$2:$A$393,Controls!$B$7) -> 1216988.1 | K17: =SUMIFS(Project_Forecast!$Y$2:$Y$393,Project_Forecast!$E$2:$E$393,$B17,Project_Forecast!$G$2:$G$393,$A17,Project_Forecast!$B$2:$B$393,Controls!$B$30,Project_Forecast!$A$2:$A$393,Controls!$B$7) -> 630036.64 | L17: =SUMIFS(Project_Forecast!$AA$2:$AA$393,Project_Forecast!$E$2:$E$393,$B17,Project_Forecast!$G$2:$G$393,$A17,Project_Forecast!$B$2:$B$393,Controls!$B$30,Project_Forecast!$A$2:$A$393,Controls!$B$7) -> 953135.55 | M17: =SUMIFS(Project_Forecast!$AC$2:$AC$393,Project_Forecast!$E$2:$E$393,$B17,Project_Forecast!$G$2:$G$393,$A17,Project_Forecast!$B$2:$B$393,Controls!$B$30,Project_Forecast!$A$2:$A$393,Controls!$B$7) -> 818501.87
A18: Internal | B18: Responsible Production | C18: =SUMIFS(MM_Income!$P$5:$P$204,MM_Income!$C$5:$C$204,$B18,MM_Income!$G$5:$G$204,$A18) -> 0 | D18: =SUMIFS(Project_Forecast!$N$2:$N$393,Project_Forecast!$E$2:$E$393,$B18,Project_Forecast!$G$2:$G$393,$A18,Project_Forecast!$B$2:$B$393,Controls!$B$30,Project_Forecast!$A$2:$A$393,Controls!$B$7) -> 0 | E18: =SUMIFS(Project_Forecast!$N$2:$N$393,Project_Forecast!$E$2:$E$393,$B18,Project_Forecast!$G$2:$G$393,$A18,Project_Forecast!$L$2:$L$393,"Secured",Project_Forecast!$B$2:$B$393,Controls!$B$30,Project_Forecast!$A$2:$A$393,Controls!$B$7) -> 0 | F18: =CHOOSE(VALUE(MID(Controls!$B$6,2,1)),SUMIFS(Project_Forecast!$W$2:$W$393,Project_Forecast!$E$2:$E$393,$B18,Project_Forecast!$G$2:$G$393,$A18,Project_Forecast!$B$2:$B$393,Controls!$B$30,Project_Forecast!$A$2:$A$393,Controls!$B$7),SUMIFS(Project_Forecast!$Y$2:$Y$393,Project_Forecast!$E$2:$E$393,$B18,Project_Forecast!$G$2:$G$393,$A18,Project_Forecast!$B$2:$B$393,Controls!$B$30,Project_Forecast!$A$2:$A$393,Controls!$B$7),SUMIFS(Project_Forecast!$AA$2:$AA$393,Project_Forecast!$E$2:$E$393,$B18,Project_Forecast!$G$2:$G$393,$A18,Project_Forecast!$B$2:$B$393,Controls!$B$30,Project_Forecast!$A$2:$A$393,Controls!$B$7),SUMIFS(Project_Forecast!$AC$2:$AC$393,Project_Forecast!$E$2:$E$393,$B18,Project_Forecast!$G$2:$G$393,$A18,Project_Forecast!$B$2:$B$393,Controls!$B$30,Project_Forecast!$A$2:$A$393,Controls!$B$7)) -> 0 | G18: =SUMIFS(Project_Forecast!$AD$2:$AD$393,Project_Forecast!$E$2:$E$393,$B18,Project_Forecast!$G$2:$G$393,$A18,Project_Forecast!$B$2:$B$393,Controls!$B$30,Project_Forecast!$A$2:$A$393,Controls!$B$7) -> 0 | H18: =SUMIFS(Project_Forecast!$AE$2:$AE$393,Project_Forecast!$E$2:$E$393,$B18,Project_Forecast!$G$2:$G$393,$A18,Project_Forecast!$B$2:$B$393,Controls!$B$30,Project_Forecast!$A$2:$A$393,Controls!$B$7) -> 0 | I18: =SUMIFS(Project_Forecast!$S$2:$S$393,Project_Forecast!$E$2:$E$393,$B18,Project_Forecast!$G$2:$G$393,$A18,Project_Forecast!$B$2:$B$393,Controls!$B$30,Project_Forecast!$A$2:$A$393,Controls!$B$7) -> 0 | J18: =SUMIFS(Project_Forecast!$W$2:$W$393,Project_Forecast!$E$2:$E$393,$B18,Project_Forecast!$G$2:$G$393,$A18,Project_Forecast!$B$2:$B$393,Controls!$B$30,Project_Forecast!$A$2:$A$393,Controls!$B$7) -> 0 | K18: =SUMIFS(Project_Forecast!$Y$2:$Y$393,Project_Forecast!$E$2:$E$393,$B18,Project_Forecast!$G$2:$G$393,$A18,Project_Forecast!$B$2:$B$393,Controls!$B$30,Project_Forecast!$A$2:$A$393,Controls!$B$7) -> 0 | L18: =SUMIFS(Project_Forecast!$AA$2:$AA$393,Project_Forecast!$E$2:$E$393,$B18,Project_Forecast!$G$2:$G$393,$A18,Project_Forecast!$B$2:$B$393,Controls!$B$30,Project_Forecast!$A$2:$A$393,Controls!$B$7) -> 0 | M18: =SUMIFS(Project_Forecast!$AC$2:$AC$393,Project_Forecast!$E$2:$E$393,$B18,Project_Forecast!$G$2:$G$393,$A18,Project_Forecast!$B$2:$B$393,Controls!$B$30,Project_Forecast!$A$2:$A$393,Controls!$B$7) -> 0
A19: Internal | B19: Responsible Finance | C19: =SUMIFS(MM_Income!$P$5:$P$204,MM_Income!$C$5:$C$204,$B19,MM_Income!$G$5:$G$204,$A19) -> 653719.44 | D19: =SUMIFS(Project_Forecast!$N$2:$N$393,Project_Forecast!$E$2:$E$393,$B19,Project_Forecast!$G$2:$G$393,$A19,Project_Forecast!$B$2:$B$393,Controls!$B$30,Project_Forecast!$A$2:$A$393,Controls!$B$7) -> 653719.44 | E19: =SUMIFS(Project_Forecast!$N$2:$N$393,Project_Forecast!$E$2:$E$393,$B19,Project_Forecast!$G$2:$G$393,$A19,Project_Forecast!$L$2:$L$393,"Secured",Project_Forecast!$B$2:$B$393,Controls!$B$30,Project_Forecast!$A$2:$A$393,Controls!$B$7) -> 244444.44 | F19: =CHOOSE(VALUE(MID(Controls!$B$6,2,1)),SUMIFS(Project_Forecast!$W$2:$W$393,Project_Forecast!$E$2:$E$393,$B19,Project_Forecast!$G$2:$G$393,$A19,Project_Forecast!$B$2:$B$393,Controls!$B$30,Project_Forecast!$A$2:$A$393,Controls!$B$7),SUMIFS(Project_Forecast!$Y$2:$Y$393,Project_Forecast!$E$2:$E$393,$B19,Project_Forecast!$G$2:$G$393,$A19,Project_Forecast!$B$2:$B$393,Controls!$B$30,Project_Forecast!$A$2:$A$393,Controls!$B$7),SUMIFS(Project_Forecast!$AA$2:$AA$393,Project_Forecast!$E$2:$E$393,$B19,Project_Forecast!$G$2:$G$393,$A19,Project_Forecast!$B$2:$B$393,Controls!$B$30,Project_Forecast!$A$2:$A$393,Controls!$B$7),SUMIFS(Project_Forecast!$AC$2:$AC$393,Project_Forecast!$E$2:$E$393,$B19,Project_Forecast!$G$2:$G$393,$A19,Project_Forecast!$B$2:$B$393,Controls!$B$30,Project_Forecast!$A$2:$A$393,Controls!$B$7)) -> 195555.55 | G19: =SUMIFS(Project_Forecast!$AD$2:$AD$393,Project_Forecast!$E$2:$E$393,$B19,Project_Forecast!$G$2:$G$393,$A19,Project_Forecast!$B$2:$B$393,Controls!$B$30,Project_Forecast!$A$2:$A$393,Controls!$B$7) -> 195555.55 | H19: =SUMIFS(Project_Forecast!$AE$2:$AE$393,Project_Forecast!$E$2:$E$393,$B19,Project_Forecast!$G$2:$G$393,$A19,Project_Forecast!$B$2:$B$393,Controls!$B$30,Project_Forecast!$A$2:$A$393,Controls!$B$7) -> 48888.887 | I19: =SUMIFS(Project_Forecast!$S$2:$S$393,Project_Forecast!$E$2:$E$393,$B19,Project_Forecast!$G$2:$G$393,$A19,Project_Forecast!$B$2:$B$393,Controls!$B$30,Project_Forecast!$A$2:$A$393,Controls!$B$7) -> 122187.25 | J19: =SUMIFS(Project_Forecast!$W$2:$W$393,Project_Forecast!$E$2:$E$393,$B19,Project_Forecast!$G$2:$G$393,$A19,Project_Forecast!$B$2:$B$393,Controls!$B$30,Project_Forecast!$A$2:$A$393,Controls!$B$7) -> 0 | K19: =SUMIFS(Project_Forecast!$Y$2:$Y$393,Project_Forecast!$E$2:$E$393,$B19,Project_Forecast!$G$2:$G$393,$A19,Project_Forecast!$B$2:$B$393,Controls!$B$30,Project_Forecast!$A$2:$A$393,Controls!$B$7) -> 195555.55 | L19: =SUMIFS(Project_Forecast!$AA$2:$AA$393,Project_Forecast!$E$2:$E$393,$B19,Project_Forecast!$G$2:$G$393,$A19,Project_Forecast!$B$2:$B$393,Controls!$B$30,Project_Forecast!$A$2:$A$393,Controls!$B$7) -> 48888.887 | M19: =SUMIFS(Project_Forecast!$AC$2:$AC$393,Project_Forecast!$E$2:$E$393,$B19,Project_Forecast!$G$2:$G$393,$A19,Project_Forecast!$B$2:$B$393,Controls!$B$30,Project_Forecast!$A$2:$A$393,Controls!$B$7) -> 0
A20: Internal | B20: Collaboration | C20: =SUMIFS(MM_Income!$P$5:$P$204,MM_Income!$C$5:$C$204,$B20,MM_Income!$G$5:$G$204,$A20) -> 0 | D20: =SUMIFS(Project_Forecast!$N$2:$N$393,Project_Forecast!$E$2:$E$393,$B20,Project_Forecast!$G$2:$G$393,$A20,Project_Forecast!$B$2:$B$393,Controls!$B$30,Project_Forecast!$A$2:$A$393,Controls!$B$7) -> 0 | E20: =SUMIFS(Project_Forecast!$N$2:$N$393,Project_Forecast!$E$2:$E$393,$B20,Project_Forecast!$G$2:$G$393,$A20,Project_Forecast!$L$2:$L$393,"Secured",Project_Forecast!$B$2:$B$393,Controls!$B$30,Project_Forecast!$A$2:$A$393,Controls!$B$7) -> 0 | F20: =CHOOSE(VALUE(MID(Controls!$B$6,2,1)),SUMIFS(Project_Forecast!$W$2:$W$393,Project_Forecast!$E$2:$E$393,$B20,Project_Forecast!$G$2:$G$393,$A20,Project_Forecast!$B$2:$B$393,Controls!$B$30,Project_Forecast!$A$2:$A$393,Controls!$B$7),SUMIFS(Project_Forecast!$Y$2:$Y$393,Project_Forecast!$E$2:$E$393,$B20,Project_Forecast!$G$2:$G$393,$A20,Project_Forecast!$B$2:$B$393,Controls!$B$30,Project_Forecast!$A$2:$A$393,Controls!$B$7),SUMIFS(Project_Forecast!$AA$2:$AA$393,Project_Forecast!$E$2:$E$393,$B20,Project_Forecast!$G$2:$G$393,$A20,Project_Forecast!$B$2:$B$393,Controls!$B$30,Project_Forecast!$A$2:$A$393,Controls!$B$7),SUMIFS(Project_Forecast!$AC$2:$AC$393,Project_Forecast!$E$2:$E$393,$B20,Project_Forecast!$G$2:$G$393,$A20,Project_Forecast!$B$2:$B$393,Controls!$B$30,Project_Forecast!$A$2:$A$393,Controls!$B$7)) -> 0 | G20: =SUMIFS(Project_Forecast!$AD$2:$AD$393,Project_Forecast!$E$2:$E$393,$B20,Project_Forecast!$G$2:$G$393,$A20,Project_Forecast!$B$2:$B$393,Controls!$B$30,Project_Forecast!$A$2:$A$393,Controls!$B$7) -> 0 | H20: =SUMIFS(Project_Forecast!$AE$2:$AE$393,Project_Forecast!$E$2:$E$393,$B20,Project_Forecast!$G$2:$G$393,$A20,Project_Forecast!$B$2:$B$393,Controls!$B$30,Project_Forecast!$A$2:$A$393,Controls!$B$7) -> 0 | I20: =SUMIFS(Project_Forecast!$S$2:$S$393,Project_Forecast!$E$2:$E$393,$B20,Project_Forecast!$G$2:$G$393,$A20,Project_Forecast!$B$2:$B$393,Controls!$B$30,Project_Forecast!$A$2:$A$393,Controls!$B$7) -> 0 | J20: =SUMIFS(Project_Forecast!$W$2:$W$393,Project_Forecast!$E$2:$E$393,$B20,Project_Forecast!$G$2:$G$393,$A20,Project_Forecast!$B$2:$B$393,Controls!$B$30,Project_Forecast!$A$2:$A$393,Controls!$B$7) -> 0 | K20: =SUMIFS(Project_Forecast!$Y$2:$Y$393,Project_Forecast!$E$2:$E$393,$B20,Project_Forecast!$G$2:$G$393,$A20,Project_Forecast!$B$2:$B$393,Controls!$B$30,Project_Forecast!$A$2:$A$393,Controls!$B$7) -> 0 | L20: =SUMIFS(Project_Forecast!$AA$2:$AA$393,Project_Forecast!$E$2:$E$393,$B20,Project_Forecast!$G$2:$G$393,$A20,Project_Forecast!$B$2:$B$393,Controls!$B$30,Project_Forecast!$A$2:$A$393,Controls!$B$7) -> 0 | M20: =SUMIFS(Project_Forecast!$AC$2:$AC$393,Project_Forecast!$E$2:$E$393,$B20,Project_Forecast!$G$2:$G$393,$A20,Project_Forecast!$B$2:$B$393,Controls!$B$30,Project_Forecast!$A$2:$A$393,Controls!$B$7) -> 0
A21: Internal | B21: Production Landscape | C21: =SUMIFS(MM_Income!$P$5:$P$204,MM_Income!$C$5:$C$204,$B21,MM_Income!$G$5:$G$204,$A21) -> 0 | D21: =SUMIFS(Project_Forecast!$N$2:$N$393,Project_Forecast!$E$2:$E$393,$B21,Project_Forecast!$G$2:$G$393,$A21,Project_Forecast!$B$2:$B$393,Controls!$B$30,Project_Forecast!$A$2:$A$393,Controls!$B$7) -> 0 | E21: =SUMIFS(Project_Forecast!$N$2:$N$393,Project_Forecast!$E$2:$E$393,$B21,Project_Forecast!$G$2:$G$393,$A21,Project_Forecast!$L$2:$L$393,"Secured",Project_Forecast!$B$2:$B$393,Controls!$B$30,Project_Forecast!$A$2:$A$393,Controls!$B$7) -> 0 | F21: =CHOOSE(VALUE(MID(Controls!$B$6,2,1)),SUMIFS(Project_Forecast!$W$2:$W$393,Project_Forecast!$E$2:$E$393,$B21,Project_Forecast!$G$2:$G$393,$A21,Project_Forecast!$B$2:$B$393,Controls!$B$30,Project_Forecast!$A$2:$A$393,Controls!$B$7),SUMIFS(Project_Forecast!$Y$2:$Y$393,Project_Forecast!$E$2:$E$393,$B21,Project_Forecast!$G$2:$G$393,$A21,Project_Forecast!$B$2:$B$393,Controls!$B$30,Project_Forecast!$A$2:$A$393,Controls!$B$7),SUMIFS(Project_Forecast!$AA$2:$AA$393,Project_Forecast!$E$2:$E$393,$B21,Project_Forecast!$G$2:$G$393,$A21,Project_Forecast!$B$2:$B$393,Controls!$B$30,Project_Forecast!$A$2:$A$393,Controls!$B$7),SUMIFS(Project_Forecast!$AC$2:$AC$393,Project_Forecast!$E$2:$E$393,$B21,Project_Forecast!$G$2:$G$393,$A21,Project_Forecast!$B$2:$B$393,Controls!$B$30,Project_Forecast!$A$2:$A$393,Controls!$B$7)) -> 0 | G21: =SUMIFS(Project_Forecast!$AD$2:$AD$393,Project_Forecast!$E$2:$E$393,$B21,Project_Forecast!$G$2:$G$393,$A21,Project_Forecast!$B$2:$B$393,Controls!$B$30,Project_Forecast!$A$2:$A$393,Controls!$B$7) -> 0 | H21: =SUMIFS(Project_Forecast!$AE$2:$AE$393,Project_Forecast!$E$2:$E$393,$B21,Project_Forecast!$G$2:$G$393,$A21,Project_Forecast!$B$2:$B$393,Controls!$B$30,Project_Forecast!$A$2:$A$393,Controls!$B$7) -> 0 | I21: =SUMIFS(Project_Forecast!$S$2:$S$393,Project_Forecast!$E$2:$E$393,$B21,Project_Forecast!$G$2:$G$393,$A21,Project_Forecast!$B$2:$B$393,Controls!$B$30,Project_Forecast!$A$2:$A$393,Controls!$B$7) -> 0 | J21: =SUMIFS(Project_Forecast!$W$2:$W$393,Project_Forecast!$E$2:$E$393,$B21,Project_Forecast!$G$2:$G$393,$A21,Project_Forecast!$B$2:$B$393,Controls!$B$30,Project_Forecast!$A$2:$A$393,Controls!$B$7) -> 0 | K21: =SUMIFS(Project_Forecast!$Y$2:$Y$393,Project_Forecast!$E$2:$E$393,$B21,Project_Forecast!$G$2:$G$393,$A21,Project_Forecast!$B$2:$B$393,Controls!$B$30,Project_Forecast!$A$2:$A$393,Controls!$B$7) -> 0 | L21: =SUMIFS(Project_Forecast!$AA$2:$AA$393,Project_Forecast!$E$2:$E$393,$B21,Project_Forecast!$G$2:$G$393,$A21,Project_Forecast!$B$2:$B$393,Controls!$B$30,Project_Forecast!$A$2:$A$393,Controls!$B$7) -> 0 | M21: =SUMIFS(Project_Forecast!$AC$2:$AC$393,Project_Forecast!$E$2:$E$393,$B21,Project_Forecast!$G$2:$G$393,$A21,Project_Forecast!$B$2:$B$393,Controls!$B$30,Project_Forecast!$A$2:$A$393,Controls!$B$7) -> 0
A22: Internal | B22: Policy & Regulation | C22: =SUMIFS(MM_Income!$P$5:$P$204,MM_Income!$C$5:$C$204,$B22,MM_Income!$G$5:$G$204,$A22) -> 0 | D22: =SUMIFS(Project_Forecast!$N$2:$N$393,Project_Forecast!$E$2:$E$393,$B22,Project_Forecast!$G$2:$G$393,$A22,Project_Forecast!$B$2:$B$393,Controls!$B$30,Project_Forecast!$A$2:$A$393,Controls!$B$7) -> 0 | E22: =SUMIFS(Project_Forecast!$N$2:$N$393,Project_Forecast!$E$2:$E$393,$B22,Project_Forecast!$G$2:$G$393,$A22,Project_Forecast!$L$2:$L$393,"Secured",Project_Forecast!$B$2:$B$393,Controls!$B$30,Project_Forecast!$A$2:$A$393,Controls!$B$7) -> 0 | F22: =CHOOSE(VALUE(MID(Controls!$B$6,2,1)),SUMIFS(Project_Forecast!$W$2:$W$393,Project_Forecast!$E$2:$E$393,$B22,Project_Forecast!$G$2:$G$393,$A22,Project_Forecast!$B$2:$B$393,Controls!$B$30,Project_Forecast!$A$2:$A$393,Controls!$B$7),SUMIFS(Project_Forecast!$Y$2:$Y$393,Project_Forecast!$E$2:$E$393,$B22,Project_Forecast!$G$2:$G$393,$A22,Project_Forecast!$B$2:$B$393,Controls!$B$30,Project_Forecast!$A$2:$A$393,Controls!$B$7),SUMIFS(Project_Forecast!$AA$2:$AA$393,Project_Forecast!$E$2:$E$393,$B22,Project_Forecast!$G$2:$G$393,$A22,Project_Forecast!$B$2:$B$393,Controls!$B$30,Project_Forecast!$A$2:$A$393,Controls!$B$7),SUMIFS(Project_Forecast!$AC$2:$AC$393,Project_Forecast!$E$2:$E$393,$B22,Project_Forecast!$G$2:$G$393,$A22,Project_Forecast!$B$2:$B$393,Controls!$B$30,Project_Forecast!$A$2:$A$393,Controls!$B$7)) -> 0 | G22: =SUMIFS(Project_Forecast!$AD$2:$AD$393,Project_Forecast!$E$2:$E$393,$B22,Project_Forecast!$G$2:$G$393,$A22,Project_Forecast!$B$2:$B$393,Controls!$B$30,Project_Forecast!$A$2:$A$393,Controls!$B$7) -> 0 | H22: =SUMIFS(Project_Forecast!$AE$2:$AE$393,Project_Forecast!$E$2:$E$393,$B22,Project_Forecast!$G$2:$G$393,$A22,Project_Forecast!$B$2:$B$393,Controls!$B$30,Project_Forecast!$A$2:$A$393,Controls!$B$7) -> 0 | I22: =SUMIFS(Project_Forecast!$S$2:$S$393,Project_Forecast!$E$2:$E$393,$B22,Project_Forecast!$G$2:$G$393,$A22,Project_Forecast!$B$2:$B$393,Controls!$B$30,Project_Forecast!$A$2:$A$393,Controls!$B$7) -> 0 | J22: =SUMIFS(Project_Forecast!$W$2:$W$393,Project_Forecast!$E$2:$E$393,$B22,Project_Forecast!$G$2:$G$393,$A22,Project_Forecast!$B$2:$B$393,Controls!$B$30,Project_Forecast!$A$2:$A$393,Controls!$B$7) -> 0 | K22: =SUMIFS(Project_Forecast!$Y$2:$Y$393,Project_Forecast!$E$2:$E$393,$B22,Project_Forecast!$G$2:$G$393,$A22,Project_Forecast!$B$2:$B$393,Controls!$B$30,Project_Forecast!$A$2:$A$393,Controls!$B$7) -> 0 | L22: =SUMIFS(Project_Forecast!$AA$2:$AA$393,Project_Forecast!$E$2:$E$393,$B22,Project_Forecast!$G$2:$G$393,$A22,Project_Forecast!$B$2:$B$393,Controls!$B$30,Project_Forecast!$A$2:$A$393,Controls!$B$7) -> 0 | M22: =SUMIFS(Project_Forecast!$AC$2:$AC$393,Project_Forecast!$E$2:$E$393,$B22,Project_Forecast!$G$2:$G$393,$A22,Project_Forecast!$B$2:$B$393,Controls!$B$30,Project_Forecast!$A$2:$A$393,Controls!$B$7) -> 0
B23: Subtotal — Internal | C23: =SUM(C17:C22) -> 5007323.5 | D23: =SUM(D17:D22) -> 4744094.5 | E23: =SUM(E17:E22) -> 4334819.5 | F23: =SUM(F17:F22) -> 825592.19 | G23: =SUM(G17:G22) -> 2042580.3 | H23: =SUM(H17:H22) -> 1820526.3 | I23: =SUM(I17:I22) -> 2237979.1 | J23: =SUM(J17:J22) -> 1216988.1 | ... M23: =SUM(M17:M22) -> 818501.87
A24: Other / Unmapped | B24: (not in portfolio/type lists) | C24: =SUM(MM_Income!$P$5:$P$204)-C16-C23 -> 0 | D24: =SUMIFS(Project_Forecast!$N$2:$N$393,Project_Forecast!$B$2:$B$393,Controls!$B$30,Project_Forecast!$A$2:$A$393,Controls!$B$7)-D16-D23 -> 0 | E24: =SUMIFS(Project_Forecast!$N$2:$N$393,Project_Forecast!$L$2:$L$393,"Secured",Project_Forecast!$B$2:$B$393,Controls!$B$30,Project_Forecast!$A$2:$A$393,Controls!$B$7)-E16-E23 -> 0 | F24: =CHOOSE(VALUE(MID(Controls!$B$6,2,1)),SUMIFS(Project_Forecast!$W$2:$W$393,Project_Forecast!$B$2:$B$393,Controls!$B$30,Project_Forecast!$A$2:$A$393,Controls!$B$7),SUMIFS(Project_Forecast!$Y$2:$Y$393,Project_Forecast!$B$2:$B$393,Controls!$B$30,Project_Forecast!$A$2:$A$393,Controls!$B$7),SUMIFS(Project_Forecast!$AA$2:$AA$393,Project_Forecast!$B$2:$B$393,Controls!$B$30,Project_Forecast!$A$2:$A$393,Controls!$B$7),SUMIFS(Project_Forecast!$AC$2:$AC$393,Project_Forecast!$B$2:$B$393,Controls!$B$30,Project_Forecast!$A$2:$A$393,Controls!$B$7))-F16-F23 -> 0 | G24: =SUMIFS(Project_Forecast!$AD$2:$AD$393,Project_Forecast!$B$2:$B$393,Controls!$B$30,Project_Forecast!$A$2:$A$393,Controls!$B$7)-G16-G23 -> 0 | H24: =SUMIFS(Project_Forecast!$AE$2:$AE$393,Project_Forecast!$B$2:$B$393,Controls!$B$30,Project_Forecast!$A$2:$A$393,Controls!$B$7)-H16-H23 -> 0 | I24: =SUMIFS(Project_Forecast!$O$2:$O$393,Project_Forecast!$B$2:$B$393,Controls!$B$30,Project_Forecast!$A$2:$A$393,Controls!$B$7)-I16-I23 -> 575798.62 | J24: =SUMIFS(Project_Forecast!$W$2:$W$393,Project_Forecast!$B$2:$B$393,Controls!$B$30,Project_Forecast!$A$2:$A$393,Controls!$B$7)-J16-J23 -> 0 | K24: =SUMIFS(Project_Forecast!$Y$2:$Y$393,Project_Forecast!$B$2:$B$393,Controls!$B$30,Project_Forecast!$A$2:$A$393,Controls!$B$7)-K16-K23 -> 0 | L24: =SUMIFS(Project_Forecast!$AA$2:$AA$393,Project_Forecast!$B$2:$B$393,Controls!$B$30,Project_Forecast!$A$2:$A$393,Controls!$B$7)-L16-L23 -> 0 | M24: =SUMIFS(Project_Forecast!$AC$2:$AC$393,Project_Forecast!$B$2:$B$393,Controls!$B$30,Project_Forecast!$A$2:$A$393,Controls!$B$7)-M16-M23 -> 0
B25: TOTAL PROJECT INCOME | C25: =C16+C23+C24 -> 16502775 | D25: =D16+D23+D24 -> 15545818 | E25: =E16+E23+E24 -> 12020285 | F25: =F16+F23+F24 -> 2548404.4 | G25: =G16+G23+G24 -> 7459200.5 | H25: =H16+H23+H24 -> 3967299.4 | I25: =I16+I23+I24 -> 7071517.9 | J25: =J16+J23+J24 -> 4910796.1 | ... M25: =M16+M23+M24 -> 1831156.4
A28: WIP by Quarter — selected period snapshot
A29: Quarter | B29: WIP_Value | C29: Cumulative | D29: Basis
A30: Q1 | B30: =SUMIFS(Project_Forecast!$W$2:$W$393,Project_Forecast!$B$2:$B$393,Controls!$B$30,Project_Forecast!$A$2:$A$393,Controls!$B$7) -> 4910796.1 | C30: =SUM(B30:B30) -> 4910796.1 | D30: =IF(1<=VALUE(MID(Controls!$B$6,2,1)),"Reported","Forecast") -> Reported
A31: Q2 | B31: =SUMIFS(Project_Forecast!$Y$2:$Y$393,Project_Forecast!$B$2:$B$393,Controls!$B$30,Project_Forecast!$A$2:$A$393,Controls!$B$7) -> 2548404.4 | C31: =SUM(B30:B31) -> 7459200.5 | D31: =IF(2<=VALUE(MID(Controls!$B$6,2,1)),"Reported","Forecast") -> Reported
A32: Q3 | B32: =SUMIFS(Project_Forecast!$AA$2:$AA$393,Project_Forecast!$B$2:$B$393,Controls!$B$30,Project_Forecast!$A$2:$A$393,Controls!$B$7) -> 2136143 | C32: =SUM(B30:B32) -> 9595343.5 | D32: =IF(3<=VALUE(MID(Controls!$B$6,2,1)),"Reported","Forecast") -> Forecast
A33: Q4 | B33: =SUMIFS(Project_Forecast!$AC$2:$AC$393,Project_Forecast!$B$2:$B$393,Controls!$B$30,Project_Forecast!$A$2:$A$393,Controls!$B$7) -> 1831156.4 | C33: =SUM(B30:B33) -> 11426500 | D33: =IF(4<=VALUE(MID(Controls!$B$6,2,1)),"Reported","Forecast") -> Forecast
A36: Income by Commodity | G36: Income by Client
A37: Commodity | B37: Net_Forecast | C37: Secured_Net | D37: WIP_YTD | E37: Invoiced_YTD | G37: Client | H37: Net_Forecast | I37: Secured_Net | J37: WIP_YTD | K37: Invoiced_YTD
A38: Oil Palm | B38: =SUMIFS(Project_Forecast!$N$2:$N$393,Project_Forecast!$H$2:$H$393,$A38,Project_Forecast!$B$2:$B$393,Controls!$B$30,Project_Forecast!$A$2:$A$393,Controls!$B$7) -> 4382580.9 | C38: =SUMIFS(Project_Forecast!$N$2:$N$393,Project_Forecast!$H$2:$H$393,$A38,Project_Forecast!$L$2:$L$393,"Secured",Project_Forecast!$B$2:$B$393,Controls!$B$30,Project_Forecast!$A$2:$A$393,Controls!$B$7) -> 3090288.4 | D38: =SUMIFS(Project_Forecast!$AD$2:$AD$393,Project_Forecast!$H$2:$H$393,$A38,Project_Forecast!$B$2:$B$393,Controls!$B$30,Project_Forecast!$A$2:$A$393,Controls!$B$7) -> 2015200.6 | E38: =SUMIFS(Project_Forecast!$O$2:$O$393,Project_Forecast!$H$2:$H$393,$A38,Project_Forecast!$B$2:$B$393,Controls!$B$30,Project_Forecast!$A$2:$A$393,Controls!$B$7) -> 1330085.9 | G38: Barnsley | H38: =SUMIFS(Project_Forecast!$N$2:$N$393,Project_Forecast!$I$2:$I$393,$G38,Project_Forecast!$B$2:$B$393,Controls!$B$30,Project_Forecast!$A$2:$A$393,Controls!$B$7) -> 851741.4 | I38: =SUMIFS(Project_Forecast!$N$2:$N$393,Project_Forecast!$I$2:$I$393,$G38,Project_Forecast!$L$2:$L$393,"Secured",Project_Forecast!$B$2:$B$393,Controls!$B$30,Project_Forecast!$A$2:$A$393,Controls!$B$7) -> 851741.4 | J38: =SUMIFS(Project_Forecast!$AD$2:$AD$393,Project_Forecast!$I$2:$I$393,$G38,Project_Forecast!$B$2:$B$393,Controls!$B$30,Project_Forecast!$A$2:$A$393,Controls!$B$7) -> 563948.85 | K38: =SUMIFS(Project_Forecast!$O$2:$O$393,Project_Forecast!$I$2:$I$393,$G38,Project_Forecast!$B$2:$B$393,Controls!$B$30,Project_Forecast!$A$2:$A$393,Controls!$B$7) -> 196496.06
A39: Sugar | B39: =SUMIFS(Project_Forecast!$N$2:$N$393,Project_Forecast!$H$2:$H$393,$A39,Project_Forecast!$B$2:$B$393,Controls!$B$30,Project_Forecast!$A$2:$A$393,Controls!$B$7) -> 3999459.3 | C39: =SUMIFS(Project_Forecast!$N$2:$N$393,Project_Forecast!$H$2:$H$393,$A39,Project_Forecast!$L$2:$L$393,"Secured",Project_Forecast!$B$2:$B$393,Controls!$B$30,Project_Forecast!$A$2:$A$393,Controls!$B$7) -> 3201196.5 | D39: =SUMIFS(Project_Forecast!$AD$2:$AD$393,Project_Forecast!$H$2:$H$393,$A39,Project_Forecast!$B$2:$B$393,Controls!$B$30,Project_Forecast!$A$2:$A$393,Controls!$B$7) -> 1285712.5 | E39: =SUMIFS(Project_Forecast!$O$2:$O$393,Project_Forecast!$H$2:$H$393,$A39,Project_Forecast!$B$2:$B$393,Controls!$B$30,Project_Forecast!$A$2:$A$393,Controls!$B$7) -> 1389380.9 | G39: Sucrivoire | H39: =SUMIFS(Project_Forecast!$N$2:$N$393,Project_Forecast!$I$2:$I$393,$G39,Project_Forecast!$B$2:$B$393,Controls!$B$30,Project_Forecast!$A$2:$A$393,Controls!$B$7) -> 44911.901 | I39: =SUMIFS(Project_Forecast!$N$2:$N$393,Project_Forecast!$I$2:$I$393,$G39,Project_Forecast!$L$2:$L$393,"Secured",Project_Forecast!$B$2:$B$393,Controls!$B$30,Project_Forecast!$A$2:$A$393,Controls!$B$7) -> 44911.901 | J39: =SUMIFS(Project_Forecast!$AD$2:$AD$393,Project_Forecast!$I$2:$I$393,$G39,Project_Forecast!$B$2:$B$393,Controls!$B$30,Project_Forecast!$A$2:$A$393,Controls!$B$7) -> 22455.95 | K39: =SUMIFS(Project_Forecast!$O$2:$O$393,Project_Forecast!$I$2:$I$393,$G39,Project_Forecast!$B$2:$B$393,Controls!$B$30,Project_Forecast!$A$2:$A$393,Controls!$B$7) -> 0
A40: Cocoa | B40: =SUMIFS(Project_Forecast!$N$2:$N$393,Project_Forecast!$H$2:$H$393,$A40,Project_Forecast!$B$2:$B$393,Controls!$B$30,Project_Forecast!$A$2:$A$393,Controls!$B$7) -> 1087349.5 | C40: =SUMIFS(Project_Forecast!$N$2:$N$393,Project_Forecast!$H$2:$H$393,$A40,Project_Forecast!$L$2:$L$393,"Secured",Project_Forecast!$B$2:$B$393,Controls!$B$30,Project_Forecast!$A$2:$A$393,Controls!$B$7) -> 678074.49 | D40: =SUMIFS(Project_Forecast!$AD$2:$AD$393,Project_Forecast!$H$2:$H$393,$A40,Project_Forecast!$B$2:$B$393,Controls!$B$30,Project_Forecast!$A$2:$A$393,Controls!$B$7) -> 629185.6 | E40: =SUMIFS(Project_Forecast!$O$2:$O$393,Project_Forecast!$H$2:$H$393,$A40,Project_Forecast!$B$2:$B$393,Controls!$B$30,Project_Forecast!$A$2:$A$393,Controls!$B$7) -> 736266.19 | G40: GVL | H40: =SUMIFS(Project_Forecast!$N$2:$N$393,Project_Forecast!$I$2:$I$393,$G40,Project_Forecast!$B$2:$B$393,Controls!$B$30,Project_Forecast!$A$2:$A$393,Controls!$B$7) -> 1141155 | I40: =SUMIFS(Project_Forecast!$N$2:$N$393,Project_Forecast!$I$2:$I$393,$G40,Project_Forecast!$L$2:$L$393,"Secured",Project_Forecast!$B$2:$B$393,Controls!$B$30,Project_Forecast!$A$2:$A$393,Controls!$B$7) -> 1141155 | J40: =SUMIFS(Project_Forecast!$AD$2:$AD$393,Project_Forecast!$I$2:$I$393,$G40,Project_Forecast!$B$2:$B$393,Controls!$B$30,Project_Forecast!$A$2:$A$393,Controls!$B$7) -> 684693 | K40: =SUMIFS(Project_Forecast!$O$2:$O$393,Project_Forecast!$I$2:$I$393,$G40,Project_Forecast!$B$2:$B$393,Controls!$B$30,Project_Forecast!$A$2:$A$393,Controls!$B$7) -> 510225.54
A41: Cashew | B41: =SUMIFS(Project_Forecast!$N$2:$N$393,Project_Forecast!$H$2:$H$393,$A41,Project_Forecast!$B$2:$B$393,Controls!$B$30,Project_Forecast!$A$2:$A$393,Controls!$B$7) -> 522962.5 | C41: =SUMIFS(Project_Forecast!$N$2:$N$393,Project_Forecast!$H$2:$H$393,$A41,Project_Forecast!$L$2:$L$393,"Secured",Project_Forecast!$B$2:$B$393,Controls!$B$30,Project_Forecast!$A$2:$A$393,Controls!$B$7) -> 522962.5 | D41: =SUMIFS(Project_Forecast!$AD$2:$AD$393,Project_Forecast!$H$2:$H$393,$A41,Project_Forecast!$B$2:$B$393,Controls!$B$30,Project_Forecast!$A$2:$A$393,Controls!$B$7) -> 496814.38 | E41: =SUMIFS(Project_Forecast!$O$2:$O$393,Project_Forecast!$H$2:$H$393,$A41,Project_Forecast!$B$2:$B$393,Controls!$B$30,Project_Forecast!$A$2:$A$393,Controls!$B$7) -> 536744.58 | G41: Presco | H41: =SUMIFS(Project_Forecast!$N$2:$N$393,Project_Forecast!$I$2:$I$393,$G41,Project_Forecast!$B$2:$B$393,Controls!$B$30,Project_Forecast!$A$2:$A$393,Controls!$B$7) -> 1441022.5 | I41: =SUMIFS(Project_Forecast!$N$2:$N$393,Project_Forecast!$I$2:$I$393,$G41,Project_Forecast!$L$2:$L$393,"Secured",Project_Forecast!$B$2:$B$393,Controls!$B$30,Project_Forecast!$A$2:$A$393,Controls!$B$7) -> 221811 | J41: =SUMIFS(Project_Forecast!$AD$2:$AD$393,Project_Forecast!$I$2:$I$393,$G41,Project_Forecast!$B$2:$B$393,Controls!$B$30,Project_Forecast!$A$2:$A$393,Controls!$B$7) -> 181750.2 | K41: =SUMIFS(Project_Forecast!$O$2:$O$393,Project_Forecast!$I$2:$I$393,$G41,Project_Forecast!$B$2:$B$393,Controls!$B$30,Project_Forecast!$A$2:$A$393,Controls!$B$7) -> 130227.27
A42: Rubber | B42: =SUMIFS(Project_Forecast!$N$2:$N$393,Project_Forecast!$H$2:$H$393,$A42,Project_Forecast!$B$2:$B$393,Controls!$B$30,Project_Forecast!$A$2:$A$393,Controls!$B$7) -> 1104561 | C42: =SUMIFS(Project_Forecast!$N$2:$N$393,Project_Forecast!$H$2:$H$393,$A42,Project_Forecast!$L$2:$L$393,"Secured",Project_Forecast!$B$2:$B$393,Controls!$B$30,Project_Forecast!$A$2:$A$393,Controls!$B$7) -> 1104561 | D42: =SUMIFS(Project_Forecast!$AD$2:$AD$393,Project_Forecast!$H$2:$H$393,$A42,Project_Forecast!$B$2:$B$393,Controls!$B$30,Project_Forecast!$A$2:$A$393,Controls!$B$7) -> 858348.65 | E42: =SUMIFS(Project_Forecast!$O$2:$O$393,Project_Forecast!$H$2:$H$393,$A42,Project_Forecast!$B$2:$B$393,Controls!$B$30,Project_Forecast!$A$2:$A$393,Controls!$B$7) -> 1008532.8 | G42: BPL | H42: =SUMIFS(Project_Forecast!$N$2:$N$393,Project_Forecast!$I$2:$I$393,$G42,Project_Forecast!$B$2:$B$393,Controls!$B$30,Project_Forecast!$A$2:$A$393,Controls!$B$7) -> 204798 | I42: =SUMIFS(Project_Forecast!$N$2:$N$393,Project_Forecast!$I$2:$I$393,$G42,Project_Forecast!$L$2:$L$393,"Secured",Project_Forecast!$B$2:$B$393,Controls!$B$30,Project_Forecast!$A$2:$A$393,Controls!$B$7) -> 204798 | J42: =SUMIFS(Project_Forecast!$AD$2:$AD$393,Project_Forecast!$I$2:$I$393,$G42,Project_Forecast!$B$2:$B$393,Controls!$B$30,Project_Forecast!$A$2:$A$393,Controls!$B$7) -> 204798 | K42: =SUMIFS(Project_Forecast!$O$2:$O$393,Project_Forecast!$I$2:$I$393,$G42,Project_Forecast!$B$2:$B$393,Controls!$B$30,Project_Forecast!$A$2:$A$393,Controls!$B$7) -> 217238.33
A43: Soy | B43: =SUMIFS(Project_Forecast!$N$2:$N$393,Project_Forecast!$H$2:$H$393,$A43,Project_Forecast!$B$2:$B$393,Controls!$B$30,Project_Forecast!$A$2:$A$393,Controls!$B$7) -> 500460.4 | C43: =SUMIFS(Project_Forecast!$N$2:$N$393,Project_Forecast!$H$2:$H$393,$A43,Project_Forecast!$L$2:$L$393,"Secured",Project_Forecast!$B$2:$B$393,Controls!$B$30,Project_Forecast!$A$2:$A$393,Controls!$B$7) -> 500460.4 | D43: =SUMIFS(Project_Forecast!$AD$2:$AD$393,Project_Forecast!$H$2:$H$393,$A43,Project_Forecast!$B$2:$B$393,Controls!$B$30,Project_Forecast!$A$2:$A$393,Controls!$B$7) -> 150138.12 | E43: =SUMIFS(Project_Forecast!$O$2:$O$393,Project_Forecast!$H$2:$H$393,$A43,Project_Forecast!$B$2:$B$393,Controls!$B$30,Project_Forecast!$A$2:$A$393,Controls!$B$7) -> 291532.03 | G43: Socfin Group | H43: =SUMIFS(Project_Forecast!$N$2:$N$393,Project_Forecast!$I$2:$I$393,$G43,Project_Forecast!$B$2:$B$393,Controls!$B$30,Project_Forecast!$A$2:$A$393,Controls!$B$7) -> 1494469 | I43: =SUMIFS(Project_Forecast!$N$2:$N$393,Project_Forecast!$I$2:$I$393,$G43,Project_Forecast!$L$2:$L$393,"Secured",Project_Forecast!$B$2:$B$393,Controls!$B$30,Project_Forecast!$A$2:$A$393,Controls!$B$7) -> 1494469 | J43: =SUMIFS(Project_Forecast!$AD$2:$AD$393,Project_Forecast!$I$2:$I$393,$G43,Project_Forecast!$B$2:$B$393,Controls!$B$30,Project_Forecast!$A$2:$A$393,Controls!$B$7) -> 747234.5 | K43: =SUMIFS(Project_Forecast!$O$2:$O$393,Project_Forecast!$I$2:$I$393,$G43,Project_Forecast!$B$2:$B$393,Controls!$B$30,Project_Forecast!$A$2:$A$393,Controls!$B$7) -> 786124.25
A44: Oil Palm & Rubber | B44: =SUMIFS(Project_Forecast!$N$2:$N$393,Project_Forecast!$H$2:$H$393,$A44,Project_Forecast!$B$2:$B$393,Controls!$B$30,Project_Forecast!$A$2:$A$393,Controls!$B$7) -> 0 | C44: =SUMIFS(Project_Forecast!$N$2:$N$393,Project_Forecast!$H$2:$H$393,$A44,Project_Forecast!$L$2:$L$393,"Secured",Project_Forecast!$B$2:$B$393,Controls!$B$30,Project_Forecast!$A$2:$A$393,Controls!$B$7) -> 0 | D44: =SUMIFS(Project_Forecast!$AD$2:$AD$393,Project_Forecast!$H$2:$H$393,$A44,Project_Forecast!$B$2:$B$393,Controls!$B$30,Project_Forecast!$A$2:$A$393,Controls!$B$7) -> 0 | E44: =SUMIFS(Project_Forecast!$O$2:$O$393,Project_Forecast!$H$2:$H$393,$A44,Project_Forecast!$B$2:$B$393,Controls!$B$30,Project_Forecast!$A$2:$A$393,Controls!$B$7) -> 0 | G44: Fauna & Flora | H44: =SUMIFS(Project_Forecast!$N$2:$N$393,Project_Forecast!$I$2:$I$393,$G44,Project_Forecast!$B$2:$B$393,Controls!$B$30,Project_Forecast!$A$2:$A$393,Controls!$B$7) -> 322438.08 | I44: =SUMIFS(Project_Forecast!$N$2:$N$393,Project_Forecast!$I$2:$I$393,$G44,Project_Forecast!$L$2:$L$393,"Secured",Project_Forecast!$B$2:$B$393,Controls!$B$30,Project_Forecast!$A$2:$A$393,Controls!$B$7) -> 322438.08 | J44: =SUMIFS(Project_Forecast!$AD$2:$AD$393,Project_Forecast!$I$2:$I$393,$G44,Project_Forecast!$B$2:$B$393,Controls!$B$30,Project_Forecast!$A$2:$A$393,Controls!$B$7) -> 161219.04 | K44: =SUMIFS(Project_Forecast!$O$2:$O$393,Project_Forecast!$I$2:$I$393,$G44,Project_Forecast!$B$2:$B$393,Controls!$B$30,Project_Forecast!$A$2:$A$393,Controls!$B$7) -> 0
A45: Multiple (Landscape) | B45: =SUMIFS(Project_Forecast!$N$2:$N$393,Project_Forecast!$H$2:$H$393,$A45,Project_Forecast!$B$2:$B$393,Controls!$B$30,Project_Forecast!$A$2:$A$393,Controls!$B$7) -> 0 | C45: =SUMIFS(Project_Forecast!$N$2:$N$393,Project_Forecast!$H$2:$H$393,$A45,Project_Forecast!$L$2:$L$393,"Secured",Project_Forecast!$B$2:$B$393,Controls!$B$30,Project_Forecast!$A$2:$A$393,Controls!$B$7) -> 0 | D45: =SUMIFS(Project_Forecast!$AD$2:$AD$393,Project_Forecast!$H$2:$H$393,$A45,Project_Forecast!$B$2:$B$393,Controls!$B$30,Project_Forecast!$A$2:$A$393,Controls!$B$7) -> 0 | E45: =SUMIFS(Project_Forecast!$O$2:$O$393,Project_Forecast!$H$2:$H$393,$A45,Project_Forecast!$B$2:$B$393,Controls!$B$30,Project_Forecast!$A$2:$A$393,Controls!$B$7) -> 0 | G45: Cashew Coast | H45: =SUMIFS(Project_Forecast!$N$2:$N$393,Project_Forecast!$I$2:$I$393,$G45,Project_Forecast!$B$2:$B$393,Controls!$B$30,Project_Forecast!$A$2:$A$393,Controls!$B$7) -> 522962.5 | I45: =SUMIFS(Project_Forecast!$N$2:$N$393,Project_Forecast!$I$2:$I$393,$G45,Project_Forecast!$L$2:$L$393,"Secured",Project_Forecast!$B$2:$B$393,Controls!$B$30,Project_Forecast!$A$2:$A$393,Controls!$B$7) -> 522962.5 | J45: =SUMIFS(Project_Forecast!$AD$2:$AD$393,Project_Forecast!$I$2:$I$393,$G45,Project_Forecast!$B$2:$B$393,Controls!$B$30,Project_Forecast!$A$2:$A$393,Controls!$B$7) -> 496814.38 | K45: =SUMIFS(Project_Forecast!$O$2:$O$393,Project_Forecast!$I$2:$I$393,$G45,Project_Forecast!$B$2:$B$393,Controls!$B$30,Project_Forecast!$A$2:$A$393,Controls!$B$7) -> 536744.58
A46: TBC | B46: =SUMIFS(Project_Forecast!$N$2:$N$393,Project_Forecast!$H$2:$H$393,$A46,Project_Forecast!$B$2:$B$393,Controls!$B$30,Project_Forecast!$A$2:$A$393,Controls!$B$7) -> 0 | C46: =SUMIFS(Project_Forecast!$N$2:$N$393,Project_Forecast!$H$2:$H$393,$A46,Project_Forecast!$L$2:$L$393,"Secured",Project_Forecast!$B$2:$B$393,Controls!$B$30,Project_Forecast!$A$2:$A$393,Controls!$B$7) -> 0 | D46: =SUMIFS(Project_Forecast!$AD$2:$AD$393,Project_Forecast!$H$2:$H$393,$A46,Project_Forecast!$B$2:$B$393,Controls!$B$30,Project_Forecast!$A$2:$A$393,Controls!$B$7) -> 0 | E46: =SUMIFS(Project_Forecast!$O$2:$O$393,Project_Forecast!$H$2:$H$393,$A46,Project_Forecast!$B$2:$B$393,Controls!$B$30,Project_Forecast!$A$2:$A$393,Controls!$B$7) -> 0 | G46: General Mills | H46: =SUMIFS(Project_Forecast!$N$2:$N$393,Project_Forecast!$I$2:$I$393,$G46,Project_Forecast!$B$2:$B$393,Controls!$B$30,Project_Forecast!$A$2:$A$393,Controls!$B$7) -> 433630.05 | I46: =SUMIFS(Project_Forecast!$N$2:$N$393,Project_Forecast!$I$2:$I$393,$G46,Project_Forecast!$L$2:$L$393,"Secured",Project_Forecast!$B$2:$B$393,Controls!$B$30,Project_Forecast!$A$2:$A$393,Controls!$B$7) -> 433630.05 | J46: =SUMIFS(Project_Forecast!$AD$2:$AD$393,Project_Forecast!$I$2:$I$393,$G46,Project_Forecast!$B$2:$B$393,Controls!$B$30,Project_Forecast!$A$2:$A$393,Controls!$B$7) -> 433630.05 | K46: =SUMIFS(Project_Forecast!$O$2:$O$393,Project_Forecast!$I$2:$I$393,$G46,Project_Forecast!$B$2:$B$393,Controls!$B$30,Project_Forecast!$A$2:$A$393,Controls!$B$7) -> 614078.94
A47: Other / not listed | B47: =$E$3-SUM(B38:B46) -> 3948443.9 | C47: =$H$3-SUM(C38:C46) -> 2922741.9 | D47: =$K$3-SUM(D38:D46) -> 2023800.7 | E47: =$B$5-SUM(E38:E46) -> 1203176.9 | G47: Nestlé (via PCUK) | H47: =SUMIFS(Project_Forecast!$N$2:$N$393,Project_Forecast!$I$2:$I$393,$G47,Project_Forecast!$B$2:$B$393,Controls!$B$30,Project_Forecast!$A$2:$A$393,Controls!$B$7) -> 3156284.6 | I47: =SUMIFS(Project_Forecast!$N$2:$N$393,Project_Forecast!$I$2:$I$393,$G47,Project_Forecast!$L$2:$L$393,"Secured",Project_Forecast!$B$2:$B$393,Controls!$B$30,Project_Forecast!$A$2:$A$393,Controls!$B$7) -> 3156284.6 | J47: =SUMIFS(Project_Forecast!$AD$2:$AD$393,Project_Forecast!$I$2:$I$393,$G47,Project_Forecast!$B$2:$B$393,Controls!$B$30,Project_Forecast!$A$2:$A$393,Controls!$B$7) -> 1263256.6 | K47: =SUMIFS(Project_Forecast!$O$2:$O$393,Project_Forecast!$I$2:$I$393,$G47,Project_Forecast!$B$2:$B$393,Controls!$B$30,Project_Forecast!$A$2:$A$393,Controls!$B$7) -> 1389380.9
A48: TOTAL | B48: =SUM(B38:B47) -> 15545818 | C48: =SUM(C38:C47) -> 12020285 | D48: =SUM(D38:D47) -> 7459200.5 | E48: =SUM(E38:E47) -> 6495719.3 | G48: Nestlé | H48: =SUMIFS(Project_Forecast!$N$2:$N$393,Project_Forecast!$I$2:$I$393,$G48,Project_Forecast!$B$2:$B$393,Controls!$B$30,Project_Forecast!$A$2:$A$393,Controls!$B$7) -> 500460.4 | I48: =SUMIFS(Project_Forecast!$N$2:$N$393,Project_Forecast!$I$2:$I$393,$G48,Project_Forecast!$L$2:$L$393,"Secured",Project_Forecast!$B$2:$B$393,Controls!$B$30,Project_Forecast!$A$2:$A$393,Controls!$B$7) -> 500460.4 | J48: =SUMIFS(Project_Forecast!$AD$2:$AD$393,Project_Forecast!$I$2:$I$393,$G48,Project_Forecast!$B$2:$B$393,Controls!$B$30,Project_Forecast!$A$2:$A$393,Controls!$B$7) -> 150138.12 | K48: =SUMIFS(Project_Forecast!$O$2:$O$393,Project_Forecast!$I$2:$I$393,$G48,Project_Forecast!$B$2:$B$393,Controls!$B$30,Project_Forecast!$A$2:$A$393,Controls!$B$7) -> 291532.03
A49: Income by Project Type | G49: RENL | H49: =SUMIFS(Project_Forecast!$N$2:$N$393,Project_Forecast!$I$2:$I$393,$G49,Project_Forecast!$B$2:$B$393,Controls!$B$30,Project_Forecast!$A$2:$A$393,Controls!$B$7) -> 1104561 | I49: =SUMIFS(Project_Forecast!$N$2:$N$393,Project_Forecast!$I$2:$I$393,$G49,Project_Forecast!$L$2:$L$393,"Secured",Project_Forecast!$B$2:$B$393,Controls!$B$30,Project_Forecast!$A$2:$A$393,Controls!$B$7) -> 1104561 | J49: =SUMIFS(Project_Forecast!$AD$2:$AD$393,Project_Forecast!$I$2:$I$393,$G49,Project_Forecast!$B$2:$B$393,Controls!$B$30,Project_Forecast!$A$2:$A$393,Controls!$B$7) -> 858348.65 | K49: =SUMIFS(Project_Forecast!$O$2:$O$393,Project_Forecast!$I$2:$I$393,$G49,Project_Forecast!$B$2:$B$393,Controls!$B$30,Project_Forecast!$A$2:$A$393,Controls!$B$7) -> 1008532.8
A50: Project_Type | B50: Net_Forecast | C50: Secured_Net | D50: WIP_YTD | E50: Invoiced_YTD | G50: Hershey (via PCUK) | H50: =SUMIFS(Project_Forecast!$N$2:$N$393,Project_Forecast!$I$2:$I$393,$G50,Project_Forecast!$B$2:$B$393,Controls!$B$30,Project_Forecast!$A$2:$A$393,Controls!$B$7) -> 653719.44 | I50: =SUMIFS(Project_Forecast!$N$2:$N$393,Project_Forecast!$I$2:$I$393,$G50,Project_Forecast!$L$2:$L$393,"Secured",Project_Forecast!$B$2:$B$393,Controls!$B$30,Project_Forecast!$A$2:$A$393,Controls!$B$7) -> 244444.44 | J50: =SUMIFS(Project_Forecast!$AD$2:$AD$393,Project_Forecast!$I$2:$I$393,$G50,Project_Forecast!$B$2:$B$393,Controls!$B$30,Project_Forecast!$A$2:$A$393,Controls!$B$7) -> 195555.55 | K50: =SUMIFS(Project_Forecast!$O$2:$O$393,Project_Forecast!$I$2:$I$393,$G50,Project_Forecast!$B$2:$B$393,Controls!$B$30,Project_Forecast!$A$2:$A$393,Controls!$B$7) -> 122187.25
A51: External | B51: =SUMIFS(Project_Forecast!$N$2:$N$393,Project_Forecast!$G$2:$G$393,$A51,Project_Forecast!$B$2:$B$393,Controls!$B$30,Project_Forecast!$A$2:$A$393,Controls!$B$7) -> 10801723 | C51: =SUMIFS(Project_Forecast!$N$2:$N$393,Project_Forecast!$G$2:$G$393,$A51,Project_Forecast!$L$2:$L$393,"Secured",Project_Forecast!$B$2:$B$393,Controls!$B$30,Project_Forecast!$A$2:$A$393,Controls!$B$7) -> 7685465.7 | D51: =SUMIFS(Project_Forecast!$AD$2:$AD$393,Project_Forecast!$G$2:$G$393,$A51,Project_Forecast!$B$2:$B$393,Controls!$B$30,Project_Forecast!$A$2:$A$393,Controls!$B$7) -> 5416620.2 | E51: =SUMIFS(Project_Forecast!$O$2:$O$393,Project_Forecast!$G$2:$G$393,$A51,Project_Forecast!$B$2:$B$393,Controls!$B$30,Project_Forecast!$A$2:$A$393,Controls!$B$7) -> 4654338.8 | G51: CDC | H51: =SUMIFS(Project_Forecast!$N$2:$N$393,Project_Forecast!$I$2:$I$393,$G51,Project_Forecast!$B$2:$B$393,Controls!$B$30,Project_Forecast!$A$2:$A$393,Controls!$B$7) -> 1416252 | I51: =SUMIFS(Project_Forecast!$N$2:$N$393,Project_Forecast!$I$2:$I$393,$G51,Project_Forecast!$L$2:$L$393,"Secured",Project_Forecast!$B$2:$B$393,Controls!$B$30,Project_Forecast!$A$2:$A$393,Controls!$B$7) -> 317469 | J51: =SUMIFS(Project_Forecast!$AD$2:$AD$393,Project_Forecast!$I$2:$I$393,$G51,Project_Forecast!$B$2:$B$393,Controls!$B$30,Project_Forecast!$A$2:$A$393,Controls!$B$7) -> 317469 | K51: =SUMIFS(Project_Forecast!$O$2:$O$393,Project_Forecast!$I$2:$I$393,$G51,Project_Forecast!$B$2:$B$393,Controls!$B$30,Project_Forecast!$A$2:$A$393,Controls!$B$7) -> 0
A52: Internal | B52: =SUMIFS(Project_Forecast!$N$2:$N$393,Project_Forecast!$G$2:$G$393,$A52,Project_Forecast!$B$2:$B$393,Controls!$B$30,Project_Forecast!$A$2:$A$393,Controls!$B$7) -> 4744094.5 | C52: =SUMIFS(Project_Forecast!$N$2:$N$393,Project_Forecast!$G$2:$G$393,$A52,Project_Forecast!$L$2:$L$393,"Secured",Project_Forecast!$B$2:$B$393,Controls!$B$30,Project_Forecast!$A$2:$A$393,Controls!$B$7) -> 4334819.5 | D52: =SUMIFS(Project_Forecast!$AD$2:$AD$393,Project_Forecast!$G$2:$G$393,$A52,Project_Forecast!$B$2:$B$393,Controls!$B$30,Project_Forecast!$A$2:$A$393,Controls!$B$7) -> 2042580.3 | E52: =SUMIFS(Project_Forecast!$O$2:$O$393,Project_Forecast!$G$2:$G$393,$A52,Project_Forecast!$B$2:$B$393,Controls!$B$30,Project_Forecast!$A$2:$A$393,Controls!$B$7) -> 2417179.1 | G52: Valency | H52: =SUMIFS(Project_Forecast!$N$2:$N$393,Project_Forecast!$I$2:$I$393,$G52,Project_Forecast!$B$2:$B$393,Controls!$B$30,Project_Forecast!$A$2:$A$393,Controls!$B$7) -> 913245 | I52: =SUMIFS(Project_Forecast!$N$2:$N$393,Project_Forecast!$I$2:$I$393,$G52,Project_Forecast!$L$2:$L$393,"Secured",Project_Forecast!$B$2:$B$393,Controls!$B$30,Project_Forecast!$A$2:$A$393,Controls!$B$7) -> 913245 | J52: =SUMIFS(Project_Forecast!$AD$2:$AD$393,Project_Forecast!$I$2:$I$393,$G52,Project_Forecast!$B$2:$B$393,Controls!$B$30,Project_Forecast!$A$2:$A$393,Controls!$B$7) -> 696184.8 | K52: =SUMIFS(Project_Forecast!$O$2:$O$393,Project_Forecast!$I$2:$I$393,$G52,Project_Forecast!$B$2:$B$393,Controls!$B$30,Project_Forecast!$A$2:$A$393,Controls!$B$7) -> 801822.68
A53: TOTAL | B53: =SUM(B51:B52) -> 15545818 | C53: =SUM(C51:C52) -> 12020285 | D53: =SUM(D51:D52) -> 7459200.5 | E53: =SUM(E51:E52) -> 7071517.9 | G53: FGMC | H53: =SUMIFS(Project_Forecast!$N$2:$N$393,Project_Forecast!$I$2:$I$393,$G53,Project_Forecast!$B$2:$B$393,Controls!$B$30,Project_Forecast!$A$2:$A$393,Controls!$B$7) -> 417503.85 | I53: =SUMIFS(Project_Forecast!$N$2:$N$393,Project_Forecast!$I$2:$I$393,$G53,Project_Forecast!$L$2:$L$393,"Secured",Project_Forecast!$B$2:$B$393,Controls!$B$30,Project_Forecast!$A$2:$A$393,Controls!$B$7) -> 417503.85 | J53: =SUMIFS(Project_Forecast!$AD$2:$AD$393,Project_Forecast!$I$2:$I$393,$G53,Project_Forecast!$B$2:$B$393,Controls!$B$30,Project_Forecast!$A$2:$A$393,Controls!$B$7) -> 417503.85 | K53: =SUMIFS(Project_Forecast!$O$2:$O$393,Project_Forecast!$I$2:$I$393,$G53,Project_Forecast!$B$2:$B$393,Controls!$B$30,Project_Forecast!$A$2:$A$393,Controls!$B$7) -> 466927.3
G54: Rainforest Alliance | H54: =SUMIFS(Project_Forecast!$N$2:$N$393,Project_Forecast!$I$2:$I$393,$G54,Project_Forecast!$B$2:$B$393,Controls!$B$30,Project_Forecast!$A$2:$A$393,Controls!$B$7) -> 128400 | I54: =SUMIFS(Project_Forecast!$N$2:$N$393,Project_Forecast!$I$2:$I$393,$G54,Project_Forecast!$L$2:$L$393,"Secured",Project_Forecast!$B$2:$B$393,Controls!$B$30,Project_Forecast!$A$2:$A$393,Controls!$B$7) -> 128400 | J54: =SUMIFS(Project_Forecast!$AD$2:$AD$393,Project_Forecast!$I$2:$I$393,$G54,Project_Forecast!$B$2:$B$393,Controls!$B$30,Project_Forecast!$A$2:$A$393,Controls!$B$7) -> 64200 | K54: =SUMIFS(Project_Forecast!$O$2:$O$393,Project_Forecast!$I$2:$I$393,$G54,Project_Forecast!$B$2:$B$393,Controls!$B$30,Project_Forecast!$A$2:$A$393,Controls!$B$7) -> 0
G55: Other / not listed | H55: =$E$3-SUM(H38:H54) -> 798262.8 | I55: =$H$3-SUM(I38:I54) -> 0 | J55: =$K$3-SUM(J38:J54) -> 0 | K55: =$B$5-SUM(K38:K54) -> -575798.62
G56: TOTAL | H56: =SUM(H38:H55) -> 15545818 | I56: =SUM(I38:I55) -> 12020285 | J56: =SUM(J38:J55) -> 7459200.5 | K56: =SUM(K38:K55) -> 6495719.3
E58: Income Bridge — FY (GHS)
E59: Gross contract value (GHS) | F59: =SUM(MM_Income!$P$5:$P$204) -> 16502775
E60: − Inclusive fees for other PF entities | F60: =-SUM(MM_Income!$R$5:$R$204) -> -463128.1
E61: − Inclusive subcontractor fees | F61: =-SUM(MM_Income!$Q$5:$Q$204) -> -411225
E62: − Inclusive expenses | F62: =-SUM(MM_Income!$S$5:$S$204) -> -82604
E63: = Net income (recognised PCGH) | F63: =F59+F60+F61+F62 -> 15545818
E64: − Pipeline (unweighted) | F64: =-SUMIFS(MM_Income!$T$5:$T$204,MM_Income!$U$5:$U$204,"Pipeline") -> -3525532.3
E65: = Secured net income | F65: =F63+F64 -> 12020285
E66: Secured = Net where Forecast_Class = "Secured"
E68: Projects by Status — contract, net, invoiced, WIP (GHS)
E69: Status | F69: Contract_Value_FY | G69: Net_FY | H69: Invoiced_YTD | I69: WIP_YTD
E70: =MM_Income!$AG$5 -> Current | F70: =SUMIFS(MM_Income!$P$5:$P$204,MM_Income!$E$5:$E$204,$E70) -> 9006520.8 | G70: =SUMIFS(MM_Income!$T$5:$T$204,MM_Income!$E$5:$E$204,$E70) -> 8736666.8 | H70: =SUMIFS(Project_Forecast!$O$2:$O$393,Project_Forecast!$K$2:$K$393,$E70,Project_Forecast!$B$2:$B$393,Controls!$B$30,Project_Forecast!$A$2:$A$393,Controls!$B$7) -> 4521467.8 | I70: =SUMIFS(Project_Forecast!$AD$2:$AD$393,Project_Forecast!$K$2:$K$393,$E70,Project_Forecast!$B$2:$B$393,Controls!$B$30,Project_Forecast!$A$2:$A$393,Controls!$B$7) -> 4922816.6
E71: =MM_Income!$AG$6 -> Completed | F71: =SUMIFS(MM_Income!$P$5:$P$204,MM_Income!$E$5:$E$204,$E71) -> 3970721.5 | G71: =SUMIFS(MM_Income!$T$5:$T$204,MM_Income!$E$5:$E$204,$E71) -> 3283618.4 | H71: =SUMIFS(Project_Forecast!$O$2:$O$393,Project_Forecast!$K$2:$K$393,$E71,Project_Forecast!$B$2:$B$393,Controls!$B$30,Project_Forecast!$A$2:$A$393,Controls!$B$7) -> 2550050.1 | I71: =SUMIFS(Project_Forecast!$AD$2:$AD$393,Project_Forecast!$K$2:$K$393,$E71,Project_Forecast!$B$2:$B$393,Controls!$B$30,Project_Forecast!$A$2:$A$393,Controls!$B$7) -> 2536383.9
E72: =MM_Income!$AG$7 -> Completed/Legacy | F72: =SUMIFS(MM_Income!$P$5:$P$204,MM_Income!$E$5:$E$204,$E72) -> 0 | G72: =SUMIFS(MM_Income!$T$5:$T$204,MM_Income!$E$5:$E$204,$E72) -> 0 | H72: =SUMIFS(Project_Forecast!$O$2:$O$393,Project_Forecast!$K$2:$K$393,$E72,Project_Forecast!$B$2:$B$393,Controls!$B$30,Project_Forecast!$A$2:$A$393,Controls!$B$7) -> 0 | I72: =SUMIFS(Project_Forecast!$AD$2:$AD$393,Project_Forecast!$K$2:$K$393,$E72,Project_Forecast!$B$2:$B$393,Controls!$B$30,Project_Forecast!$A$2:$A$393,Controls!$B$7) -> 0
E73: =MM_Income!$AG$8 -> Pipeline | F73: =SUMIFS(MM_Income!$P$5:$P$204,MM_Income!$E$5:$E$204,$E73) -> 3525532.3 | G73: =SUMIFS(MM_Income!$T$5:$T$204,MM_Income!$E$5:$E$204,$E73) -> 3525532.3 | H73: =SUMIFS(Project_Forecast!$O$2:$O$393,Project_Forecast!$K$2:$K$393,$E73,Project_Forecast!$B$2:$B$393,Controls!$B$30,Project_Forecast!$A$2:$A$393,Controls!$B$7) -> 0 | I73: =SUMIFS(Project_Forecast!$AD$2:$AD$393,Project_Forecast!$K$2:$K$393,$E73,Project_Forecast!$B$2:$B$393,Controls!$B$30,Project_Forecast!$A$2:$A$393,Controls!$B$7) -> 0
E74: =MM_Income!$AG$9 -> On Hold | F74: =SUMIFS(MM_Income!$P$5:$P$204,MM_Income!$E$5:$E$204,$E74) -> 0 | G74: =SUMIFS(MM_Income!$T$5:$T$204,MM_Income!$E$5:$E$204,$E74) -> 0 | H74: =SUMIFS(Project_Forecast!$O$2:$O$393,Project_Forecast!$K$2:$K$393,$E74,Project_Forecast!$B$2:$B$393,Controls!$B$30,Project_Forecast!$A$2:$A$393,Controls!$B$7) -> 0 | I74: =SUMIFS(Project_Forecast!$AD$2:$AD$393,Project_Forecast!$K$2:$K$393,$E74,Project_Forecast!$B$2:$B$393,Controls!$B$30,Project_Forecast!$A$2:$A$393,Controls!$B$7) -> 0
E75: TOTAL | F75: =SUM(F70:F74) -> 16502775 | G75: =SUM(G70:G74) -> 15545818 | H75: =SUM(H70:H74) -> 7071517.9 | I75: =SUM(I70:I74) -> 7459200.5
E76: Totals tie to FY Gross (B6), FY Net (E6), Invoiced YTD (B5) and WIP YTD (K3).

Sheet FixedCost_Output
A1: ="Fixed Costs versus Spend — "&Controls!$B$8 -> Fixed Costs versus Spend — PC Ghana
A2: ="Year-to-date through "&TEXT(Controls!$B$4,"dd-mmm-yyyy")&" | Budget vs actual by cost category, incl. PIGH cost share" -> Year-to-date through 30-Jun-2026 | Budget vs actual by cost category, incl. PIGH cost share
A3: Annual Budget (GHS) | B3: =SUM(FC_Budget_Vrs_Actual!$E$6:$E$79) -> 13774372 | D3: Budget YTD (GHS) | E3: =SUM(FC_Budget_Vrs_Actual!$F$6:$F$79) -> 6887185.8 | G3: Actual YTD (GHS) | H3: =SUM(FC_Budget_Vrs_Actual!$S$6:$S$79) -> 5801713.6 | J3: YTD Variance (GHS) | K3: =E3-H3 -> 1085472.2
A5: Spend vs Budget YTD | B5: =IFERROR(H3/E3,0) -> 0.84239249 | D5: PIGH Cost Share YTD (GHS) | E5: =SUM(FC_Budget_Vrs_Actual!$V$6:$V$79) -> 272202.16 | G5: Spend of Annual Budget | H5: =IFERROR(H3/B3,0) -> 0.42119625 | J5: Material Exceptions | K5: =COUNTIF(K12:K22,"REVIEW") -> 11
A9: Fixed Costs by Category — Budget vs Actual YTD
A11: Category | B11: QMR_Group | C11: Annual_Budget | D11: Budget_YTD | E11: Actual_YTD | F11: Variance | G11: Variance_% | H11: Spend_vs_Budget_YTD | I11: PIGH_Share_YTD | J11: Net_After_PIGH | K11: Status
A12: Direct technical costs | B12: =IFERROR(VLOOKUP($A12,Master_Mappings!$C$4:$D$85,2,FALSE()),"Other Fixed Costs") -> Direct Technical Costs | C12: =SUMIFS(FC_Budget_Vrs_Actual!$E$6:$E$79,FC_Budget_Vrs_Actual!$C$6:$C$79,$A12) -> 7230077.7 | D12: =SUMIFS(FC_Budget_Vrs_Actual!$F$6:$F$79,FC_Budget_Vrs_Actual!$C$6:$C$79,$A12) -> 3615038.9 | E12: =SUMIFS(FC_Budget_Vrs_Actual!$S$6:$S$79,FC_Budget_Vrs_Actual!$C$6:$C$79,$A12) -> 3229268.5 | F12: =D12-E12 -> 385770.3 | G12: =IFERROR(F12/D12,0) -> 0.10671263 | H12: =IFERROR(E12/D12,0) -> 0.89328737 | I12: =SUMIFS(FC_Budget_Vrs_Actual!$V$6:$V$79,FC_Budget_Vrs_Actual!$C$6:$C$79,$A12) -> 0 | J12: =E12-I12 -> 3229268.5 | K12: =IF(OR(ABS(F12)>=Controls!$B$12,ABS(G12)>=Controls!$B$13),"REVIEW","OK") -> REVIEW
A13: Direct support costs | B13: =IFERROR(VLOOKUP($A13,Master_Mappings!$C$4:$D$85,2,FALSE()),"Other Fixed Costs") -> Direct FinOps Costs | C13: =SUMIFS(FC_Budget_Vrs_Actual!$E$6:$E$79,FC_Budget_Vrs_Actual!$C$6:$C$79,$A13) -> 2322680 | D13: =SUMIFS(FC_Budget_Vrs_Actual!$F$6:$F$79,FC_Budget_Vrs_Actual!$C$6:$C$79,$A13) -> 1161340 | E13: =SUMIFS(FC_Budget_Vrs_Actual!$S$6:$S$79,FC_Budget_Vrs_Actual!$C$6:$C$79,$A13) -> 1287623.6 | F13: =D13-E13 -> -126283.65 | G13: =IFERROR(F13/D13,0) -> -0.1087396 | H13: =IFERROR(E13/D13,0) -> 1.1087396 | I13: =SUMIFS(FC_Budget_Vrs_Actual!$V$6:$V$79,FC_Budget_Vrs_Actual!$C$6:$C$79,$A13) -> 0 | J13: =E13-I13 -> 1287623.6 | K13: =IF(OR(ABS(F13)>=Controls!$B$12,ABS(G13)>=Controls!$B$13),"REVIEW","OK") -> REVIEW
A14: Recruitment, Benefits | B14: =IFERROR(VLOOKUP($A14,Master_Mappings!$C$4:$D$85,2,FALSE()),"Other Fixed Costs") -> Other Fixed Costs | C14: =SUMIFS(FC_Budget_Vrs_Actual!$E$6:$E$79,FC_Budget_Vrs_Actual!$C$6:$C$79,$A14) -> 321500 | D14: =SUMIFS(FC_Budget_Vrs_Actual!$F$6:$F$79,FC_Budget_Vrs_Actual!$C$6:$C$79,$A14) -> 160750 | E14: =SUMIFS(FC_Budget_Vrs_Actual!$S$6:$S$79,FC_Budget_Vrs_Actual!$C$6:$C$79,$A14) -> 89499.71 | F14: =D14-E14 -> 71250.29 | G14: =IFERROR(F14/D14,0) -> 0.44323664 | H14: =IFERROR(E14/D14,0) -> 0.55676336 | I14: =SUMIFS(FC_Budget_Vrs_Actual!$V$6:$V$79,FC_Budget_Vrs_Actual!$C$6:$C$79,$A14) -> 22279.928 | J14: =E14-I14 -> 67219.783 | K14: =IF(OR(ABS(F14)>=Controls!$B$12,ABS(G14)>=Controls!$B$13),"REVIEW","OK") -> REVIEW
A15: Professional development and Training | B15: =IFERROR(VLOOKUP($A15,Master_Mappings!$C$4:$D$85,2,FALSE()),"Other Fixed Costs") -> Other Fixed Costs | C15: =SUMIFS(FC_Budget_Vrs_Actual!$E$6:$E$79,FC_Budget_Vrs_Actual!$C$6:$C$79,$A15) -> 1217997 | D15: =SUMIFS(FC_Budget_Vrs_Actual!$F$6:$F$79,FC_Budget_Vrs_Actual!$C$6:$C$79,$A15) -> 608998.51 | E15: =SUMIFS(FC_Budget_Vrs_Actual!$S$6:$S$79,FC_Budget_Vrs_Actual!$C$6:$C$79,$A15) -> 201138.6 | F15: =D15-E15 -> 407859.91 | G15: =IFERROR(F15/D15,0) -> 0.66972234 | H15: =IFERROR(E15/D15,0) -> 0.33027766 | I15: =SUMIFS(FC_Budget_Vrs_Actual!$V$6:$V$79,FC_Budget_Vrs_Actual!$C$6:$C$79,$A15) -> 0 | J15: =E15-I15 -> 201138.6 | K15: =IF(OR(ABS(F15)>=Controls!$B$12,ABS(G15)>=Controls!$B$13),"REVIEW","OK") -> REVIEW
A16: Business development and Comms | B16: =IFERROR(VLOOKUP($A16,Master_Mappings!$C$4:$D$85,2,FALSE()),"Other Fixed Costs") -> Other Fixed Costs | C16: =SUMIFS(FC_Budget_Vrs_Actual!$E$6:$E$79,FC_Budget_Vrs_Actual!$C$6:$C$79,$A16) -> 247369.45 | D16: =SUMIFS(FC_Budget_Vrs_Actual!$F$6:$F$79,FC_Budget_Vrs_Actual!$C$6:$C$79,$A16) -> 123684.73 | E16: =SUMIFS(FC_Budget_Vrs_Actual!$S$6:$S$79,FC_Budget_Vrs_Actual!$C$6:$C$79,$A16) -> 99295.87 | F16: =D16-E16 -> 24388.855 | G16: =IFERROR(F16/D16,0) -> 0.19718567 | H16: =IFERROR(E16/D16,0) -> 0.80281433 | I16: =SUMIFS(FC_Budget_Vrs_Actual!$V$6:$V$79,FC_Budget_Vrs_Actual!$C$6:$C$79,$A16) -> 24823.967 | J16: =E16-I16 -> 74471.902 | K16: =IF(OR(ABS(F16)>=Controls!$B$12,ABS(G16)>=Controls!$B$13),"REVIEW","OK") -> REVIEW
A17: Internal events and meetings | B17: =IFERROR(VLOOKUP($A17,Master_Mappings!$C$4:$D$85,2,FALSE()),"Other Fixed Costs") -> Other Fixed Costs | C17: =SUMIFS(FC_Budget_Vrs_Actual!$E$6:$E$79,FC_Budget_Vrs_Actual!$C$6:$C$79,$A17) -> 439040 | D17: =SUMIFS(FC_Budget_Vrs_Actual!$F$6:$F$79,FC_Budget_Vrs_Actual!$C$6:$C$79,$A17) -> 219520 | E17: =SUMIFS(FC_Budget_Vrs_Actual!$S$6:$S$79,FC_Budget_Vrs_Actual!$C$6:$C$79,$A17) -> 33622.84 | F17: =D17-E17 -> 185897.16 | G17: =IFERROR(F17/D17,0) -> 0.84683473 | H17: =IFERROR(E17/D17,0) -> 0.15316527 | I17: =SUMIFS(FC_Budget_Vrs_Actual!$V$6:$V$79,FC_Budget_Vrs_Actual!$C$6:$C$79,$A17) -> 0 | J17: =E17-I17 -> 33622.84 | K17: =IF(OR(ABS(F17)>=Controls!$B$12,ABS(G17)>=Controls!$B$13),"REVIEW","OK") -> REVIEW
A18: Professional services and governance | B18: =IFERROR(VLOOKUP($A18,Master_Mappings!$C$4:$D$85,2,FALSE()),"Other Fixed Costs") -> Other Fixed Costs | C18: =SUMIFS(FC_Budget_Vrs_Actual!$E$6:$E$79,FC_Budget_Vrs_Actual!$C$6:$C$79,$A18) -> 1028561.7 | D18: =SUMIFS(FC_Budget_Vrs_Actual!$F$6:$F$79,FC_Budget_Vrs_Actual!$C$6:$C$79,$A18) -> 514280.87 | E18: =SUMIFS(FC_Budget_Vrs_Actual!$S$6:$S$79,FC_Budget_Vrs_Actual!$C$6:$C$79,$A18) -> 684241.87 | F18: =D18-E18 -> -169961 | G18: =IFERROR(F18/D18,0) -> -0.33048284 | H18: =IFERROR(E18/D18,0) -> 1.3304828 | I18: =SUMIFS(FC_Budget_Vrs_Actual!$V$6:$V$79,FC_Budget_Vrs_Actual!$C$6:$C$79,$A18) -> 162868.01 | J18: =E18-I18 -> 521373.86 | K18: =IF(OR(ABS(F18)>=Controls!$B$12,ABS(G18)>=Controls!$B$13),"REVIEW","OK") -> REVIEW
A19: IT and Data | B19: =IFERROR(VLOOKUP($A19,Master_Mappings!$C$4:$D$85,2,FALSE()),"Other Fixed Costs") -> Other Fixed Costs | C19: =SUMIFS(FC_Budget_Vrs_Actual!$E$6:$E$79,FC_Budget_Vrs_Actual!$C$6:$C$79,$A19) -> 423770.5 | D19: =SUMIFS(FC_Budget_Vrs_Actual!$F$6:$F$79,FC_Budget_Vrs_Actual!$C$6:$C$79,$A19) -> 211885.25 | E19: =SUMIFS(FC_Budget_Vrs_Actual!$S$6:$S$79,FC_Budget_Vrs_Actual!$C$6:$C$79,$A19) -> 71930.54 | F19: =D19-E19 -> 139954.71 | G19: =IFERROR(F19/D19,0) -> 0.66052125 | H19: =IFERROR(E19/D19,0) -> 0.33947875 | I19: =SUMIFS(FC_Budget_Vrs_Actual!$V$6:$V$79,FC_Budget_Vrs_Actual!$C$6:$C$79,$A19) -> 13558.087 | J19: =E19-I19 -> 58372.452 | K19: =IF(OR(ABS(F19)>=Controls!$B$12,ABS(G19)>=Controls!$B$13),"REVIEW","OK") -> REVIEW
A20: Office Running costs | B20: =IFERROR(VLOOKUP($A20,Master_Mappings!$C$4:$D$85,2,FALSE()),"Other Fixed Costs") -> Other Fixed Costs | C20: =SUMIFS(FC_Budget_Vrs_Actual!$E$6:$E$79,FC_Budget_Vrs_Actual!$C$6:$C$79,$A20) -> 498375.13 | D20: =SUMIFS(FC_Budget_Vrs_Actual!$F$6:$F$79,FC_Budget_Vrs_Actual!$C$6:$C$79,$A20) -> 249187.57 | E20: =SUMIFS(FC_Budget_Vrs_Actual!$S$6:$S$79,FC_Budget_Vrs_Actual!$C$6:$C$79,$A20) -> 194888.67 | F20: =D20-E20 -> 54298.895 | G20: =IFERROR(F20/D20,0) -> 0.21790371 | H20: =IFERROR(E20/D20,0) -> 0.78209629 | I20: =SUMIFS(FC_Budget_Vrs_Actual!$V$6:$V$79,FC_Budget_Vrs_Actual!$C$6:$C$79,$A20) -> 48672.168 | J20: =E20-I20 -> 146216.5 | K20: =IF(OR(ABS(F20)>=Controls!$B$12,ABS(G20)>=Controls!$B$13),"REVIEW","OK") -> REVIEW
A21: Financial Charges | B21: =IFERROR(VLOOKUP($A21,Master_Mappings!$C$4:$D$85,2,FALSE()),"Other Fixed Costs") -> Other Fixed Costs | C21: =SUMIFS(FC_Budget_Vrs_Actual!$E$6:$E$79,FC_Budget_Vrs_Actual!$C$6:$C$79,$A21) -> 45000 | D21: =SUMIFS(FC_Budget_Vrs_Actual!$F$6:$F$79,FC_Budget_Vrs_Actual!$C$6:$C$79,$A21) -> 22500 | E21: =SUMIFS(FC_Budget_Vrs_Actual!$S$6:$S$79,FC_Budget_Vrs_Actual!$C$6:$C$79,$A21) -> 26331.8 | F21: =D21-E21 -> -3831.8 | G21: =IFERROR(F21/D21,0) -> -0.17030222 | H21: =IFERROR(E21/D21,0) -> 1.1703022 | I21: =SUMIFS(FC_Budget_Vrs_Actual!$V$6:$V$79,FC_Budget_Vrs_Actual!$C$6:$C$79,$A21) -> 0 | J21: =E21-I21 -> 26331.8 | K21: =IF(OR(ABS(F21)>=Controls!$B$12,ABS(G21)>=Controls!$B$13),"REVIEW","OK") -> REVIEW
A22: Foreign Exchange Losses / (Gains) | B22: =IFERROR(VLOOKUP($A22,Master_Mappings!$C$4:$D$85,2,FALSE()),"Other Fixed Costs") -> Other Fixed Costs | C22: =SUMIFS(FC_Budget_Vrs_Actual!$E$6:$E$79,FC_Budget_Vrs_Actual!$C$6:$C$79,$A22) -> 0 | D22: =SUMIFS(FC_Budget_Vrs_Actual!$F$6:$F$79,FC_Budget_Vrs_Actual!$C$6:$C$79,$A22) -> 0 | E22: =SUMIFS(FC_Budget_Vrs_Actual!$S$6:$S$79,FC_Budget_Vrs_Actual!$C$6:$C$79,$A22) -> -116128.53 | F22: =D22-E22 -> 116128.53 | G22: =IFERROR(F22/D22,0) -> 0 | H22: =IFERROR(E22/D22,0) -> 0 | I22: =SUMIFS(FC_Budget_Vrs_Actual!$V$6:$V$79,FC_Budget_Vrs_Actual!$C$6:$C$79,$A22) -> 0 | J22: =E22-I22 -> -116128.53 | K22: =IF(OR(ABS(F22)>=Controls!$B$12,ABS(G22)>=Controls!$B$13),"REVIEW","OK") -> REVIEW
A23: TOTAL | C23: =SUM(C12:C22) -> 13774372 | D23: =SUM(D12:D22) -> 6887185.8 | E23: =SUM(E12:E22) -> 5801713.6 | F23: =SUM(F12:F22) -> 1085472.2 | G23: =IFERROR(F23/D23,0) -> 0.15760751 | H23: =IFERROR(E23/D23,0) -> 0.84239249 | I23: =SUM(I12:I22) -> 272202.16 | J23: =SUM(J12:J22) -> 5529511.4
A26: Core vs Discretionary
A27: Cost_Nature | B27: Annual_Budget | C27: Budget_YTD | D27: Actual_YTD | E27: Spend_vs_Budget_YTD
A28: Core | B28: =SUMIFS(FC_Budget_Vrs_Actual!$E$6:$E$79,FC_Budget_Vrs_Actual!$D$6:$D$79,$A28) -> 11869965 | C28: =SUMIFS(FC_Budget_Vrs_Actual!$F$6:$F$79,FC_Budget_Vrs_Actual!$D$6:$D$79,$A28) -> 5934982.5 | D28: =SUMIFS(FC_Budget_Vrs_Actual!$S$6:$S$79,FC_Budget_Vrs_Actual!$D$6:$D$79,$A28) -> 5467656.3 | E28: =IFERROR(D28/C28,0) -> 0.92125903
A29: Discretionary | B29: =SUMIFS(FC_Budget_Vrs_Actual!$E$6:$E$79,FC_Budget_Vrs_Actual!$D$6:$D$79,$A29) -> 1904406.5 | C29: =SUMIFS(FC_Budget_Vrs_Actual!$F$6:$F$79,FC_Budget_Vrs_Actual!$D$6:$D$79,$A29) -> 952203.23 | D29: =SUMIFS(FC_Budget_Vrs_Actual!$S$6:$S$79,FC_Budget_Vrs_Actual!$D$6:$D$79,$A29) -> 334057.31 | E29: =IFERROR(D29/C29,0) -> 0.35082564
A73: Fixed Costs by Category — Individual Quarters (GHS)
A74: Category | B74: Q1 | C74: Q2 | D74: Q3 | E74: Q4 | F74: YTD
A75: =A12 -> Direct technical costs | B75: =SUMIFS(FC_Budget_Vrs_Actual!$Y$6:$Y$79,FC_Budget_Vrs_Actual!$C$6:$C$79,$A75) -> 1587508.1 | C75: =SUMIFS(FC_Budget_Vrs_Actual!$AA$6:$AA$79,FC_Budget_Vrs_Actual!$C$6:$C$79,$A75) -> 1641760.5 | D75: =SUMIFS(FC_Budget_Vrs_Actual!$AC$6:$AC$79,FC_Budget_Vrs_Actual!$C$6:$C$79,$A75) -> 0 | E75: =SUMIFS(FC_Budget_Vrs_Actual!$AE$6:$AE$79,FC_Budget_Vrs_Actual!$C$6:$C$79,$A75) -> 0 | F75: =SUM(B75:E75) -> 3229268.5
A76: =A13 -> Direct support costs | B76: =SUMIFS(FC_Budget_Vrs_Actual!$Y$6:$Y$79,FC_Budget_Vrs_Actual!$C$6:$C$79,$A76) -> 642948.54 | C76: =SUMIFS(FC_Budget_Vrs_Actual!$AA$6:$AA$79,FC_Budget_Vrs_Actual!$C$6:$C$79,$A76) -> 644675.11 | D76: =SUMIFS(FC_Budget_Vrs_Actual!$AC$6:$AC$79,FC_Budget_Vrs_Actual!$C$6:$C$79,$A76) -> 0 | E76: =SUMIFS(FC_Budget_Vrs_Actual!$AE$6:$AE$79,FC_Budget_Vrs_Actual!$C$6:$C$79,$A76) -> 0 | F76: =SUM(B76:E76) -> 1287623.6
A77: =A14 -> Recruitment, Benefits | B77: =SUMIFS(FC_Budget_Vrs_Actual!$Y$6:$Y$79,FC_Budget_Vrs_Actual!$C$6:$C$79,$A77) -> 50831.5 | C77: =SUMIFS(FC_Budget_Vrs_Actual!$AA$6:$AA$79,FC_Budget_Vrs_Actual!$C$6:$C$79,$A77) -> 38668.21 | D77: =SUMIFS(FC_Budget_Vrs_Actual!$AC$6:$AC$79,FC_Budget_Vrs_Actual!$C$6:$C$79,$A77) -> 0 | E77: =SUMIFS(FC_Budget_Vrs_Actual!$AE$6:$AE$79,FC_Budget_Vrs_Actual!$C$6:$C$79,$A77) -> 0 | F77: =SUM(B77:E77) -> 89499.71
A78: =A15 -> Professional development and Training | B78: =SUMIFS(FC_Budget_Vrs_Actual!$Y$6:$Y$79,FC_Budget_Vrs_Actual!$C$6:$C$79,$A78) -> 19760.54 | C78: =SUMIFS(FC_Budget_Vrs_Actual!$AA$6:$AA$79,FC_Budget_Vrs_Actual!$C$6:$C$79,$A78) -> 181378.06 | D78: =SUMIFS(FC_Budget_Vrs_Actual!$AC$6:$AC$79,FC_Budget_Vrs_Actual!$C$6:$C$79,$A78) -> 0 | E78: =SUMIFS(FC_Budget_Vrs_Actual!$AE$6:$AE$79,FC_Budget_Vrs_Actual!$C$6:$C$79,$A78) -> 0 | F78: =SUM(B78:E78) -> 201138.6
A79: =A16 -> Business development and Comms | B79: =SUMIFS(FC_Budget_Vrs_Actual!$Y$6:$Y$79,FC_Budget_Vrs_Actual!$C$6:$C$79,$A79) -> 73364.22 | C79: =SUMIFS(FC_Budget_Vrs_Actual!$AA$6:$AA$79,FC_Budget_Vrs_Actual!$C$6:$C$79,$A79) -> 25931.65 | D79: =SUMIFS(FC_Budget_Vrs_Actual!$AC$6:$AC$79,FC_Budget_Vrs_Actual!$C$6:$C$79,$A79) -> 0 | E79: =SUMIFS(FC_Budget_Vrs_Actual!$AE$6:$AE$79,FC_Budget_Vrs_Actual!$C$6:$C$79,$A79) -> 0 | F79: =SUM(B79:E79) -> 99295.87
A80: =A17 -> Internal events and meetings | B80: =SUMIFS(FC_Budget_Vrs_Actual!$Y$6:$Y$79,FC_Budget_Vrs_Actual!$C$6:$C$79,$A80) -> 25490.41 | C80: =SUMIFS(FC_Budget_Vrs_Actual!$AA$6:$AA$79,FC_Budget_Vrs_Actual!$C$6:$C$79,$A80) -> 8132.43 | D80: =SUMIFS(FC_Budget_Vrs_Actual!$AC$6:$AC$79,FC_Budget_Vrs_Actual!$C$6:$C$79,$A80) -> 0 | E80: =SUMIFS(FC_Budget_Vrs_Actual!$AE$6:$AE$79,FC_Budget_Vrs_Actual!$C$6:$C$79,$A80) -> 0 | F80: =SUM(B80:E80) -> 33622.84
A81: =A18 -> Professional services and governance | B81: =SUMIFS(FC_Budget_Vrs_Actual!$Y$6:$Y$79,FC_Budget_Vrs_Actual!$C$6:$C$79,$A81) -> 343205.44 | C81: =SUMIFS(FC_Budget_Vrs_Actual!$AA$6:$AA$79,FC_Budget_Vrs_Actual!$C$6:$C$79,$A81) -> 341036.43 | D81: =SUMIFS(FC_Budget_Vrs_Actual!$AC$6:$AC$79,FC_Budget_Vrs_Actual!$C$6:$C$79,$A81) -> 0 | E81: =SUMIFS(FC_Budget_Vrs_Actual!$AE$6:$AE$79,FC_Budget_Vrs_Actual!$C$6:$C$79,$A81) -> 0 | F81: =SUM(B81:E81) -> 684241.87
A82: =A19 -> IT and Data | B82: =SUMIFS(FC_Budget_Vrs_Actual!$Y$6:$Y$79,FC_Budget_Vrs_Actual!$C$6:$C$79,$A82) -> 24117.25 | C82: =SUMIFS(FC_Budget_Vrs_Actual!$AA$6:$AA$79,FC_Budget_Vrs_Actual!$C$6:$C$79,$A82) -> 47813.29 | D82: =SUMIFS(FC_Budget_Vrs_Actual!$AC$6:$AC$79,FC_Budget_Vrs_Actual!$C$6:$C$79,$A82) -> 0 | E82: =SUMIFS(FC_Budget_Vrs_Actual!$AE$6:$AE$79,FC_Budget_Vrs_Actual!$C$6:$C$79,$A82) -> 0 | F82: =SUM(B82:E82) -> 71930.54
A83: =A20 -> Office Running costs | B83: =SUMIFS(FC_Budget_Vrs_Actual!$Y$6:$Y$79,FC_Budget_Vrs_Actual!$C$6:$C$79,$A83) -> 64792.58 | C83: =SUMIFS(FC_Budget_Vrs_Actual!$AA$6:$AA$79,FC_Budget_Vrs_Actual!$C$6:$C$79,$A83) -> 130096.09 | D83: =SUMIFS(FC_Budget_Vrs_Actual!$AC$6:$AC$79,FC_Budget_Vrs_Actual!$C$6:$C$79,$A83) -> 0 | E83: =SUMIFS(FC_Budget_Vrs_Actual!$AE$6:$AE$79,FC_Budget_Vrs_Actual!$C$6:$C$79,$A83) -> 0 | F83: =SUM(B83:E83) -> 194888.67
A84: =A21 -> Financial Charges | B84: =SUMIFS(FC_Budget_Vrs_Actual!$Y$6:$Y$79,FC_Budget_Vrs_Actual!$C$6:$C$79,$A84) -> 8808.26 | C84: =SUMIFS(FC_Budget_Vrs_Actual!$AA$6:$AA$79,FC_Budget_Vrs_Actual!$C$6:$C$79,$A84) -> 17523.54 | D84: =SUMIFS(FC_Budget_Vrs_Actual!$AC$6:$AC$79,FC_Budget_Vrs_Actual!$C$6:$C$79,$A84) -> 0 | E84: =SUMIFS(FC_Budget_Vrs_Actual!$AE$6:$AE$79,FC_Budget_Vrs_Actual!$C$6:$C$79,$A84) -> 0 | F84: =SUM(B84:E84) -> 26331.8
A85: =A22 -> Foreign Exchange Losses / (Gains) | B85: =SUMIFS(FC_Budget_Vrs_Actual!$Y$6:$Y$79,FC_Budget_Vrs_Actual!$C$6:$C$79,$A85) -> -61465.49 | C85: =SUMIFS(FC_Budget_Vrs_Actual!$AA$6:$AA$79,FC_Budget_Vrs_Actual!$C$6:$C$79,$A85) -> -54663.04 | D85: =SUMIFS(FC_Budget_Vrs_Actual!$AC$6:$AC$79,FC_Budget_Vrs_Actual!$C$6:$C$79,$A85) -> 0 | E85: =SUMIFS(FC_Budget_Vrs_Actual!$AE$6:$AE$79,FC_Budget_Vrs_Actual!$C$6:$C$79,$A85) -> 0 | F85: =SUM(B85:E85) -> -116128.53
A86: TOTAL | B86: =SUM(B75:B85) -> 2779361.3 | C86: =SUM(C75:C85) -> 3022352.2 | D86: =SUM(D75:D85) -> 0 | E86: =SUM(E75:E85) -> 0 | F86: =SUM(F75:F85) -> 5801713.6
A89: PIGH Cost Share by Quarter (GHS)
B90: Q1 | C90: Q2 | D90: Q3 | E90: Q4 | F90: YTD
A91: PIGH share of fixed costs | B91: =SUM(FC_Budget_Vrs_Actual!$Z$6:$Z$79) -> 134538.61 | C91: =SUM(FC_Budget_Vrs_Actual!$AB$6:$AB$79) -> 137663.55 | D91: =SUM(FC_Budget_Vrs_Actual!$AD$6:$AD$79) -> 0 | E91: =SUM(FC_Budget_Vrs_Actual!$AF$6:$AF$79) -> 0 | F91: =SUM(B91:E91) -> 272202.16
A92: This quarter to invoice PIGH | B92: =SUM(FC_Budget_Vrs_Actual!$AG$6:$AG$79) -> 137663.55 | C92: Increment for the reporting quarter only (per Controls!B6) — cumulative YTD sits in the row above; per-line detail on FC_Budget_Vrs_Actual.

Sheet Balance_Sheet
A1: ="Balance Sheet — "&Controls!$B$8 -> Balance Sheet — PC Ghana
A2: ="Quarter end: "&TEXT(Controls!$B$4,"dd-mmm-yyyy")&" | Statement by quarter with liquidity ratios (GHS)" -> Quarter end: 30-Jun-2026 | Statement by quarter with liquidity ratios (GHS) | H2: =IF(VALUE(MID(Controls!$B$6,2,1))>1,IF(COUNTIFS(Trial_Balance!$B$2:$B$995,Controls!$B$5&"-Q"&(VALUE(MID(Controls!$B$6,2,1))-1),Trial_Balance!$A$2:$A$995,Controls!$B$7)>0,"Opening basis: Q"&(VALUE(MID(Controls!$B$6,2,1))-1)&" closing trial balance","Opening basis: selected-quarter TB opening balances (prior-quarter TB not loaded)"),"Opening basis: Q1 TB opening balances (start of year)") -> Opening basis: selected-quarter TB opening balances (prior-quarter TB not loaded)
A3: Total Assets (GHS) | B3: =INDEX($B$17:$E$17,1,VALUE(MID(Controls!$B$6,2,1))) -> 11257421 | D3: Working Capital (GHS) | E3: =INDEX($C$34:$F$34,1,VALUE(MID(Controls!$B$6,2,1))) -> 5711207.9 | G3: Current Ratio | H3: =INDEX($C$33:$F$33,1,VALUE(MID(Controls!$B$6,2,1))) -> 2.761659 | J3: Months of Core Cost Cover | K3: =INDEX($C$36:$F$36,1,VALUE(MID(Controls!$B$6,2,1))) -> 5.7737739
A5: Quarter columns Q1-Q4 (B:E) are each populated only from that quarter's own Trial_Balance rows (closing balances, natural TB signs: assets +, liabilities/equity −); once a quarter's TB is loaded its column is fixed and is never overwritten when a later reporting quarter is selected. The Selected Quarter block (H:K) derives automatically from Controls: Opening = prior-quarter closing balance (falling back to the selected snapshot's TB opening column when no prior-quarter TB is loaded), Closing = the selected quarter's own TB closing position. Opening↔closing continuity is monitored in row 39 and in Checks.
A6: Balance Sheet Statement (GHS) | H6: ="Selected Quarter — "&Controls!$B$6&" (opening = prior-quarter closing)" -> Selected Quarter — Q2 (opening = prior-quarter closing)
A7: Line | B7: Q1 | C7: Q2 | D7: Q3 | E7: Q4 | F7: Movement_vs_Prior | G7: Movement_% | H7: Opening_Balance | I7: Closing_Balance | J7: Movement | K7: Movement_%
A8: Total Fixed Assets | B8: =IF(COUNTIFS(Trial_Balance!$B$2:$B$995,Controls!$B$5&"-Q1",Trial_Balance!$A$2:$A$995,Controls!$B$7)=0,"-",B9+B10+B11+B12) -> - | C8: =IF(COUNTIFS(Trial_Balance!$B$2:$B$995,Controls!$B$5&"-Q2",Trial_Balance!$A$2:$A$995,Controls!$B$7)=0,"-",C9+C10+C11+C12) -> 2304264.8 | D8: =IF(COUNTIFS(Trial_Balance!$B$2:$B$995,Controls!$B$5&"-Q3",Trial_Balance!$A$2:$A$995,Controls!$B$7)=0,"-",D9+D10+D11+D12) -> - | E8: =IF(COUNTIFS(Trial_Balance!$B$2:$B$995,Controls!$B$5&"-Q4",Trial_Balance!$A$2:$A$995,Controls!$B$7)=0,"-",E9+E10+E11+E12) -> - | F8: =IF(VALUE(MID(Controls!$B$6,2,1))=1,"-",IF(AND(ISNUMBER(INDEX($B8:$E8,1,VALUE(MID(Controls!$B$6,2,1)))),ISNUMBER(INDEX($B8:$E8,1,VALUE(MID(Controls!$B$6,2,1))-1))),INDEX($B8:$E8,1,VALUE(MID(Controls!$B$6,2,1)))-INDEX($B8:$E8,1,VALUE(MID(Controls!$B$6,2,1))-1),"-")) -> - | G8: =IF(ISNUMBER($F8),IFERROR($F8/ABS(INDEX($B8:$E8,1,VALUE(MID(Controls!$B$6,2,1))-1)),"-"),"-") -> - | H8: =IF(ISNUMBER(H9),SUM(H9:H12),"-") -> 2195320.6 | I8: =INDEX($B8:$E8,1,VALUE(MID(Controls!$B$6,2,1))) -> 2304264.8 | J8: =IF(AND(ISNUMBER($H8),ISNUMBER($I8)),$I8-$H8,"-") -> 108944.17 | K8: =IF(AND(ISNUMBER($J8),ISNUMBER($H8)),IFERROR($J8/ABS($H8),"-"),"-") -> 0.04962563
A9: Land and Building | B9: =IF(COUNTIFS(Trial_Balance!$B$2:$B$995,Controls!$B$5&"-Q1",Trial_Balance!$A$2:$A$995,Controls!$B$7)=0,"-",SUMIFS(Trial_Balance!$H$2:$H$995,Trial_Balance!$I$2:$I$995,$A9,Trial_Balance!$B$2:$B$995,Controls!$B$5&"-Q1",Trial_Balance!$A$2:$A$995,Controls!$B$7)) -> - | C9: =IF(COUNTIFS(Trial_Balance!$B$2:$B$995,Controls!$B$5&"-Q2",Trial_Balance!$A$2:$A$995,Controls!$B$7)=0,"-",SUMIFS(Trial_Balance!$H$2:$H$995,Trial_Balance!$I$2:$I$995,$A9,Trial_Balance!$B$2:$B$995,Controls!$B$5&"-Q2",Trial_Balance!$A$2:$A$995,Controls!$B$7)) -> 1413084.9 | D9: =IF(COUNTIFS(Trial_Balance!$B$2:$B$995,Controls!$B$5&"-Q3",Trial_Balance!$A$2:$A$995,Controls!$B$7)=0,"-",SUMIFS(Trial_Balance!$H$2:$H$995,Trial_Balance!$I$2:$I$995,$A9,Trial_Balance!$B$2:$B$995,Controls!$B$5&"-Q3",Trial_Balance!$A$2:$A$995,Controls!$B$7)) -> - | E9: =IF(COUNTIFS(Trial_Balance!$B$2:$B$995,Controls!$B$5&"-Q4",Trial_Balance!$A$2:$A$995,Controls!$B$7)=0,"-",SUMIFS(Trial_Balance!$H$2:$H$995,Trial_Balance!$I$2:$I$995,$A9,Trial_Balance!$B$2:$B$995,Controls!$B$5&"-Q4",Trial_Balance!$A$2:$A$995,Controls!$B$7)) -> - | F9: =IF(VALUE(MID(Controls!$B$6,2,1))=1,"-",IF(AND(ISNUMBER(INDEX($B9:$E9,1,VALUE(MID(Controls!$B$6,2,1)))),ISNUMBER(INDEX($B9:$E9,1,VALUE(MID(Controls!$B$6,2,1))-1))),INDEX($B9:$E9,1,VALUE(MID(Controls!$B$6,2,1)))-INDEX($B9:$E9,1,VALUE(MID(Controls!$B$6,2,1))-1),"-")) -> - | G9: =IF(ISNUMBER($F9),IFERROR($F9/ABS(INDEX($B9:$E9,1,VALUE(MID(Controls!$B$6,2,1))-1)),"-"),"-") -> - | H9: =IF(AND(VALUE(MID(Controls!$B$6,2,1))>1,COUNTIFS(Trial_Balance!$B$2:$B$995,Controls!$B$5&"-Q"&(VALUE(MID(Controls!$B$6,2,1))-1),Trial_Balance!$A$2:$A$995,Controls!$B$7)>0),INDEX($B9:$E9,1,VALUE(MID(Controls!$B$6,2,1))-1),IF(COUNTIFS(Trial_Balance!$B$2:$B$995,Controls!$B$30,Trial_Balance!$A$2:$A$995,Controls!$B$7)>0,SUMIFS(Trial_Balance!$E$2:$E$995,Trial_Balance!$I$2:$I$995,$A9,Trial_Balance!$B$2:$B$995,Controls!$B$30,Trial_Balance!$A$2:$A$995,Controls!$B$7),"-")) -> 1413084.9 | I9: =INDEX($B9:$E9,1,VALUE(MID(Controls!$B$6,2,1))) -> 1413084.9 | J9: =IF(AND(ISNUMBER($H9),ISNUMBER($I9)),$I9-$H9,"-") -> 0 | K9: =IF(AND(ISNUMBER($J9),ISNUMBER($H9)),IFERROR($J9/ABS($H9),"-"),"-") -> 0
A10: Furniture, Fixtures and Equipment | B10: =IF(COUNTIFS(Trial_Balance!$B$2:$B$995,Controls!$B$5&"-Q1",Trial_Balance!$A$2:$A$995,Controls!$B$7)=0,"-",SUMIFS(Trial_Balance!$H$2:$H$995,Trial_Balance!$I$2:$I$995,$A10,Trial_Balance!$B$2:$B$995,Controls!$B$5&"-Q1",Trial_Balance!$A$2:$A$995,Controls!$B$7)) -> - | C10: =IF(COUNTIFS(Trial_Balance!$B$2:$B$995,Controls!$B$5&"-Q2",Trial_Balance!$A$2:$A$995,Controls!$B$7)=0,"-",SUMIFS(Trial_Balance!$H$2:$H$995,Trial_Balance!$I$2:$I$995,$A10,Trial_Balance!$B$2:$B$995,Controls!$B$5&"-Q2",Trial_Balance!$A$2:$A$995,Controls!$B$7)) -> 583090.14 | D10: =IF(COUNTIFS(Trial_Balance!$B$2:$B$995,Controls!$B$5&"-Q3",Trial_Balance!$A$2:$A$995,Controls!$B$7)=0,"-",SUMIFS(Trial_Balance!$H$2:$H$995,Trial_Balance!$I$2:$I$995,$A10,Trial_Balance!$B$2:$B$995,Controls!$B$5&"-Q3",Trial_Balance!$A$2:$A$995,Controls!$B$7)) -> - | E10: =IF(COUNTIFS(Trial_Balance!$B$2:$B$995,Controls!$B$5&"-Q4",Trial_Balance!$A$2:$A$995,Controls!$B$7)=0,"-",SUMIFS(Trial_Balance!$H$2:$H$995,Trial_Balance!$I$2:$I$995,$A10,Trial_Balance!$B$2:$B$995,Controls!$B$5&"-Q4",Trial_Balance!$A$2:$A$995,Controls!$B$7)) -> - | F10: =IF(VALUE(MID(Controls!$B$6,2,1))=1,"-",IF(AND(ISNUMBER(INDEX($B10:$E10,1,VALUE(MID(Controls!$B$6,2,1)))),ISNUMBER(INDEX($B10:$E10,1,VALUE(MID(Controls!$B$6,2,1))-1))),INDEX($B10:$E10,1,VALUE(MID(Controls!$B$6,2,1)))-INDEX($B10:$E10,1,VALUE(MID(Controls!$B$6,2,1))-1),"-")) -> - | G10: =IF(ISNUMBER($F10),IFERROR($F10/ABS(INDEX($B10:$E10,1,VALUE(MID(Controls!$B$6,2,1))-1)),"-"),"-") -> - | H10: =IF(AND(VALUE(MID(Controls!$B$6,2,1))>1,COUNTIFS(Trial_Balance!$B$2:$B$995,Controls!$B$5&"-Q"&(VALUE(MID(Controls!$B$6,2,1))-1),Trial_Balance!$A$2:$A$995,Controls!$B$7)>0),INDEX($B10:$E10,1,VALUE(MID(Controls!$B$6,2,1))-1),IF(COUNTIFS(Trial_Balance!$B$2:$B$995,Controls!$B$30,Trial_Balance!$A$2:$A$995,Controls!$B$7)>0,SUMIFS(Trial_Balance!$E$2:$E$995,Trial_Balance!$I$2:$I$995,$A10,Trial_Balance!$B$2:$B$995,Controls!$B$30,Trial_Balance!$A$2:$A$995,Controls!$B$7),"-")) -> 489166.96 | I10: =INDEX($B10:$E10,1,VALUE(MID(Controls!$B$6,2,1))) -> 583090.14 | J10: =IF(AND(ISNUMBER($H10),ISNUMBER($I10)),$I10-$H10,"-") -> 93923.18 | K10: =IF(AND(ISNUMBER($J10),ISNUMBER($H10)),IFERROR($J10/ABS($H10),"-"),"-") -> 0.19200639
A11: Investments > 3 months | B11: =IF(COUNTIFS(Trial_Balance!$B$2:$B$995,Controls!$B$5&"-Q1",Trial_Balance!$A$2:$A$995,Controls!$B$7)=0,"-",SUMIFS(Trial_Balance!$H$2:$H$995,Trial_Balance!$I$2:$I$995,$A11,Trial_Balance!$B$2:$B$995,Controls!$B$5&"-Q1",Trial_Balance!$A$2:$A$995,Controls!$B$7)) -> - | C11: =IF(COUNTIFS(Trial_Balance!$B$2:$B$995,Controls!$B$5&"-Q2",Trial_Balance!$A$2:$A$995,Controls!$B$7)=0,"-",SUMIFS(Trial_Balance!$H$2:$H$995,Trial_Balance!$I$2:$I$995,$A11,Trial_Balance!$B$2:$B$995,Controls!$B$5&"-Q2",Trial_Balance!$A$2:$A$995,Controls!$B$7)) -> 0 | D11: =IF(COUNTIFS(Trial_Balance!$B$2:$B$995,Controls!$B$5&"-Q3",Trial_Balance!$A$2:$A$995,Controls!$B$7)=0,"-",SUMIFS(Trial_Balance!$H$2:$H$995,Trial_Balance!$I$2:$I$995,$A11,Trial_Balance!$B$2:$B$995,Controls!$B$5&"-Q3",Trial_Balance!$A$2:$A$995,Controls!$B$7)) -> - | E11: =IF(COUNTIFS(Trial_Balance!$B$2:$B$995,Controls!$B$5&"-Q4",Trial_Balance!$A$2:$A$995,Controls!$B$7)=0,"-",SUMIFS(Trial_Balance!$H$2:$H$995,Trial_Balance!$I$2:$I$995,$A11,Trial_Balance!$B$2:$B$995,Controls!$B$5&"-Q4",Trial_Balance!$A$2:$A$995,Controls!$B$7)) -> - | F11: =IF(VALUE(MID(Controls!$B$6,2,1))=1,"-",IF(AND(ISNUMBER(INDEX($B11:$E11,1,VALUE(MID(Controls!$B$6,2,1)))),ISNUMBER(INDEX($B11:$E11,1,VALUE(MID(Controls!$B$6,2,1))-1))),INDEX($B11:$E11,1,VALUE(MID(Controls!$B$6,2,1)))-INDEX($B11:$E11,1,VALUE(MID(Controls!$B$6,2,1))-1),"-")) -> - | G11: =IF(ISNUMBER($F11),IFERROR($F11/ABS(INDEX($B11:$E11,1,VALUE(MID(Controls!$B$6,2,1))-1)),"-"),"-") -> - | H11: =IF(AND(VALUE(MID(Controls!$B$6,2,1))>1,COUNTIFS(Trial_Balance!$B$2:$B$995,Controls!$B$5&"-Q"&(VALUE(MID(Controls!$B$6,2,1))-1),Trial_Balance!$A$2:$A$995,Controls!$B$7)>0),INDEX($B11:$E11,1,VALUE(MID(Controls!$B$6,2,1))-1),IF(COUNTIFS(Trial_Balance!$B$2:$B$995,Controls!$B$30,Trial_Balance!$A$2:$A$995,Controls!$B$7)>0,SUMIFS(Trial_Balance!$E$2:$E$995,Trial_Balance!$I$2:$I$995,$A11,Trial_Balance!$B$2:$B$995,Controls!$B$30,Trial_Balance!$A$2:$A$995,Controls!$B$7),"-")) -> 0 | I11: =INDEX($B11:$E11,1,VALUE(MID(Controls!$B$6,2,1))) -> 0 | J11: =IF(AND(ISNUMBER($H11),ISNUMBER($I11)),$I11-$H11,"-") -> 0 | K11: =IF(AND(ISNUMBER($J11),ISNUMBER($H11)),IFERROR($J11/ABS($H11),"-"),"-") -> -
A12: Intangible Assets | B12: =IF(COUNTIFS(Trial_Balance!$B$2:$B$995,Controls!$B$5&"-Q1",Trial_Balance!$A$2:$A$995,Controls!$B$7)=0,"-",SUMIFS(Trial_Balance!$H$2:$H$995,Trial_Balance!$I$2:$I$995,$A12,Trial_Balance!$B$2:$B$995,Controls!$B$5&"-Q1",Trial_Balance!$A$2:$A$995,Controls!$B$7)) -> - | C12: =IF(COUNTIFS(Trial_Balance!$B$2:$B$995,Controls!$B$5&"-Q2",Trial_Balance!$A$2:$A$995,Controls!$B$7)=0,"-",SUMIFS(Trial_Balance!$H$2:$H$995,Trial_Balance!$I$2:$I$995,$A12,Trial_Balance!$B$2:$B$995,Controls!$B$5&"-Q2",Trial_Balance!$A$2:$A$995,Controls!$B$7)) -> 308089.74 | D12: =IF(COUNTIFS(Trial_Balance!$B$2:$B$995,Controls!$B$5&"-Q3",Trial_Balance!$A$2:$A$995,Controls!$B$7)=0,"-",SUMIFS(Trial_Balance!$H$2:$H$995,Trial_Balance!$I$2:$I$995,$A12,Trial_Balance!$B$2:$B$995,Controls!$B$5&"-Q3",Trial_Balance!$A$2:$A$995,Controls!$B$7)) -> - | E12: =IF(COUNTIFS(Trial_Balance!$B$2:$B$995,Controls!$B$5&"-Q4",Trial_Balance!$A$2:$A$995,Controls!$B$7)=0,"-",SUMIFS(Trial_Balance!$H$2:$H$995,Trial_Balance!$I$2:$I$995,$A12,Trial_Balance!$B$2:$B$995,Controls!$B$5&"-Q4",Trial_Balance!$A$2:$A$995,Controls!$B$7)) -> - | F12: =IF(VALUE(MID(Controls!$B$6,2,1))=1,"-",IF(AND(ISNUMBER(INDEX($B12:$E12,1,VALUE(MID(Controls!$B$6,2,1)))),ISNUMBER(INDEX($B12:$E12,1,VALUE(MID(Controls!$B$6,2,1))-1))),INDEX($B12:$E12,1,VALUE(MID(Controls!$B$6,2,1)))-INDEX($B12:$E12,1,VALUE(MID(Controls!$B$6,2,1))-1),"-")) -> - | G12: =IF(ISNUMBER($F12),IFERROR($F12/ABS(INDEX($B12:$E12,1,VALUE(MID(Controls!$B$6,2,1))-1)),"-"),"-") -> - | H12: =IF(AND(VALUE(MID(Controls!$B$6,2,1))>1,COUNTIFS(Trial_Balance!$B$2:$B$995,Controls!$B$5&"-Q"&(VALUE(MID(Controls!$B$6,2,1))-1),Trial_Balance!$A$2:$A$995,Controls!$B$7)>0),INDEX($B12:$E12,1,VALUE(MID(Controls!$B$6,2,1))-1),IF(COUNTIFS(Trial_Balance!$B$2:$B$995,Controls!$B$30,Trial_Balance!$A$2:$A$995,Controls!$B$7)>0,SUMIFS(Trial_Balance!$E$2:$E$995,Trial_Balance!$I$2:$I$995,$A12,Trial_Balance!$B$2:$B$995,Controls!$B$30,Trial_Balance!$A$2:$A$995,Controls!$B$7),"-")) -> 293068.75 | I12: =INDEX($B12:$E12,1,VALUE(MID(Controls!$B$6,2,1))) -> 308089.74 | J12: =IF(AND(ISNUMBER($H12),ISNUMBER($I12)),$I12-$H12,"-") -> 15020.99 | K12: =IF(AND(ISNUMBER($J12),ISNUMBER($H12)),IFERROR($J12/ABS($H12),"-"),"-") -> 0.051254151
A13: Total Current Assets | B13: =IF(COUNTIFS(Trial_Balance!$B$2:$B$995,Controls!$B$5&"-Q1",Trial_Balance!$A$2:$A$995,Controls!$B$7)=0,"-",B14+B15+B16) -> - | C13: =IF(COUNTIFS(Trial_Balance!$B$2:$B$995,Controls!$B$5&"-Q2",Trial_Balance!$A$2:$A$995,Controls!$B$7)=0,"-",C14+C15+C16) -> 8953156.5 | D13: =IF(COUNTIFS(Trial_Balance!$B$2:$B$995,Controls!$B$5&"-Q3",Trial_Balance!$A$2:$A$995,Controls!$B$7)=0,"-",D14+D15+D16) -> - | E13: =IF(COUNTIFS(Trial_Balance!$B$2:$B$995,Controls!$B$5&"-Q4",Trial_Balance!$A$2:$A$995,Controls!$B$7)=0,"-",E14+E15+E16) -> - | F13: =IF(VALUE(MID(Controls!$B$6,2,1))=1,"-",IF(AND(ISNUMBER(INDEX($B13:$E13,1,VALUE(MID(Controls!$B$6,2,1)))),ISNUMBER(INDEX($B13:$E13,1,VALUE(MID(Controls!$B$6,2,1))-1))),INDEX($B13:$E13,1,VALUE(MID(Controls!$B$6,2,1)))-INDEX($B13:$E13,1,VALUE(MID(Controls!$B$6,2,1))-1),"-")) -> - | G13: =IF(ISNUMBER($F13),IFERROR($F13/ABS(INDEX($B13:$E13,1,VALUE(MID(Controls!$B$6,2,1))-1)),"-"),"-") -> - | H13: =IF(ISNUMBER(H14),SUM(H14:H16),"-") -> 7618650.8 | I13: =INDEX($B13:$E13,1,VALUE(MID(Controls!$B$6,2,1))) -> 8953156.5 | J13: =IF(AND(ISNUMBER($H13),ISNUMBER($I13)),$I13-$H13,"-") -> 1334505.7 | K13: =IF(AND(ISNUMBER($J13),ISNUMBER($H13)),IFERROR($J13/ABS($H13),"-"),"-") -> 0.17516299
A14: Trade Debtors | B14: =IF(COUNTIFS(Trial_Balance!$B$2:$B$995,Controls!$B$5&"-Q1",Trial_Balance!$A$2:$A$995,Controls!$B$7)=0,"-",SUMIFS(Trial_Balance!$H$2:$H$995,Trial_Balance!$I$2:$I$995,$A14,Trial_Balance!$B$2:$B$995,Controls!$B$5&"-Q1",Trial_Balance!$A$2:$A$995,Controls!$B$7)) -> - | C14: =IF(COUNTIFS(Trial_Balance!$B$2:$B$995,Controls!$B$5&"-Q2",Trial_Balance!$A$2:$A$995,Controls!$B$7)=0,"-",SUMIFS(Trial_Balance!$H$2:$H$995,Trial_Balance!$I$2:$I$995,$A14,Trial_Balance!$B$2:$B$995,Controls!$B$5&"-Q2",Trial_Balance!$A$2:$A$995,Controls!$B$7)) -> 6877195.6 | D14: =IF(COUNTIFS(Trial_Balance!$B$2:$B$995,Controls!$B$5&"-Q3",Trial_Balance!$A$2:$A$995,Controls!$B$7)=0,"-",SUMIFS(Trial_Balance!$H$2:$H$995,Trial_Balance!$I$2:$I$995,$A14,Trial_Balance!$B$2:$B$995,Controls!$B$5&"-Q3",Trial_Balance!$A$2:$A$995,Controls!$B$7)) -> - | E14: =IF(COUNTIFS(Trial_Balance!$B$2:$B$995,Controls!$B$5&"-Q4",Trial_Balance!$A$2:$A$995,Controls!$B$7)=0,"-",SUMIFS(Trial_Balance!$H$2:$H$995,Trial_Balance!$I$2:$I$995,$A14,Trial_Balance!$B$2:$B$995,Controls!$B$5&"-Q4",Trial_Balance!$A$2:$A$995,Controls!$B$7)) -> - | F14: =IF(VALUE(MID(Controls!$B$6,2,1))=1,"-",IF(AND(ISNUMBER(INDEX($B14:$E14,1,VALUE(MID(Controls!$B$6,2,1)))),ISNUMBER(INDEX($B14:$E14,1,VALUE(MID(Controls!$B$6,2,1))-1))),INDEX($B14:$E14,1,VALUE(MID(Controls!$B$6,2,1)))-INDEX($B14:$E14,1,VALUE(MID(Controls!$B$6,2,1))-1),"-")) -> - | G14: =IF(ISNUMBER($F14),IFERROR($F14/ABS(INDEX($B14:$E14,1,VALUE(MID(Controls!$B$6,2,1))-1)),"-"),"-") -> - | H14: =IF(AND(VALUE(MID(Controls!$B$6,2,1))>1,COUNTIFS(Trial_Balance!$B$2:$B$995,Controls!$B$5&"-Q"&(VALUE(MID(Controls!$B$6,2,1))-1),Trial_Balance!$A$2:$A$995,Controls!$B$7)>0),INDEX($B14:$E14,1,VALUE(MID(Controls!$B$6,2,1))-1),IF(COUNTIFS(Trial_Balance!$B$2:$B$995,Controls!$B$30,Trial_Balance!$A$2:$A$995,Controls!$B$7)>0,SUMIFS(Trial_Balance!$E$2:$E$995,Trial_Balance!$I$2:$I$995,$A14,Trial_Balance!$B$2:$B$995,Controls!$B$30,Trial_Balance!$A$2:$A$995,Controls!$B$7),"-")) -> 5391347.5 | I14: =INDEX($B14:$E14,1,VALUE(MID(Controls!$B$6,2,1))) -> 6877195.6 | J14: =IF(AND(ISNUMBER($H14),ISNUMBER($I14)),$I14-$H14,"-") -> 1485848.1 | K14: =IF(AND(ISNUMBER($J14),ISNUMBER($H14)),IFERROR($J14/ABS($H14),"-"),"-") -> 0.27559865
A15: Cash in Hand and at Bank | B15: =IF(COUNTIFS(Trial_Balance!$B$2:$B$995,Controls!$B$5&"-Q1",Trial_Balance!$A$2:$A$995,Controls!$B$7)=0,"-",SUMIFS(Trial_Balance!$H$2:$H$995,Trial_Balance!$I$2:$I$995,$A15,Trial_Balance!$B$2:$B$995,Controls!$B$5&"-Q1",Trial_Balance!$A$2:$A$995,Controls!$B$7)) -> - | C15: =IF(COUNTIFS(Trial_Balance!$B$2:$B$995,Controls!$B$5&"-Q2",Trial_Balance!$A$2:$A$995,Controls!$B$7)=0,"-",SUMIFS(Trial_Balance!$H$2:$H$995,Trial_Balance!$I$2:$I$995,$A15,Trial_Balance!$B$2:$B$995,Controls!$B$5&"-Q2",Trial_Balance!$A$2:$A$995,Controls!$B$7)) -> 536578.52 | D15: =IF(COUNTIFS(Trial_Balance!$B$2:$B$995,Controls!$B$5&"-Q3",Trial_Balance!$A$2:$A$995,Controls!$B$7)=0,"-",SUMIFS(Trial_Balance!$H$2:$H$995,Trial_Balance!$I$2:$I$995,$A15,Trial_Balance!$B$2:$B$995,Controls!$B$5&"-Q3",Trial_Balance!$A$2:$A$995,Controls!$B$7)) -> - | E15: =IF(COUNTIFS(Trial_Balance!$B$2:$B$995,Controls!$B$5&"-Q4",Trial_Balance!$A$2:$A$995,Controls!$B$7)=0,"-",SUMIFS(Trial_Balance!$H$2:$H$995,Trial_Balance!$I$2:$I$995,$A15,Trial_Balance!$B$2:$B$995,Controls!$B$5&"-Q4",Trial_Balance!$A$2:$A$995,Controls!$B$7)) -> - | F15: =IF(VALUE(MID(Controls!$B$6,2,1))=1,"-",IF(AND(ISNUMBER(INDEX($B15:$E15,1,VALUE(MID(Controls!$B$6,2,1)))),ISNUMBER(INDEX($B15:$E15,1,VALUE(MID(Controls!$B$6,2,1))-1))),INDEX($B15:$E15,1,VALUE(MID(Controls!$B$6,2,1)))-INDEX($B15:$E15,1,VALUE(MID(Controls!$B$6,2,1))-1),"-")) -> - | G15: =IF(ISNUMBER($F15),IFERROR($F15/ABS(INDEX($B15:$E15,1,VALUE(MID(Controls!$B$6,2,1))-1)),"-"),"-") -> - | H15: =IF(AND(VALUE(MID(Controls!$B$6,2,1))>1,COUNTIFS(Trial_Balance!$B$2:$B$995,Controls!$B$5&"-Q"&(VALUE(MID(Controls!$B$6,2,1))-1),Trial_Balance!$A$2:$A$995,Controls!$B$7)>0),INDEX($B15:$E15,1,VALUE(MID(Controls!$B$6,2,1))-1),IF(COUNTIFS(Trial_Balance!$B$2:$B$995,Controls!$B$30,Trial_Balance!$A$2:$A$995,Controls!$B$7)>0,SUMIFS(Trial_Balance!$E$2:$E$995,Trial_Balance!$I$2:$I$995,$A15,Trial_Balance!$B$2:$B$995,Controls!$B$30,Trial_Balance!$A$2:$A$995,Controls!$B$7),"-")) -> 1291533.2 | I15: =INDEX($B15:$E15,1,VALUE(MID(Controls!$B$6,2,1))) -> 536578.52 | J15: =IF(AND(ISNUMBER($H15),ISNUMBER($I15)),$I15-$H15,"-") -> -754954.72 | K15: =IF(AND(ISNUMBER($J15),ISNUMBER($H15)),IFERROR($J15/ABS($H15),"-"),"-") -> -0.58454146
A16: Other Receivables | B16: =IF(COUNTIFS(Trial_Balance!$B$2:$B$995,Controls!$B$5&"-Q1",Trial_Balance!$A$2:$A$995,Controls!$B$7)=0,"-",SUMIFS(Trial_Balance!$H$2:$H$995,Trial_Balance!$I$2:$I$995,$A16,Trial_Balance!$B$2:$B$995,Controls!$B$5&"-Q1",Trial_Balance!$A$2:$A$995,Controls!$B$7)) -> - | C16: =IF(COUNTIFS(Trial_Balance!$B$2:$B$995,Controls!$B$5&"-Q2",Trial_Balance!$A$2:$A$995,Controls!$B$7)=0,"-",SUMIFS(Trial_Balance!$H$2:$H$995,Trial_Balance!$I$2:$I$995,$A16,Trial_Balance!$B$2:$B$995,Controls!$B$5&"-Q2",Trial_Balance!$A$2:$A$995,Controls!$B$7)) -> 1539382.3 | D16: =IF(COUNTIFS(Trial_Balance!$B$2:$B$995,Controls!$B$5&"-Q3",Trial_Balance!$A$2:$A$995,Controls!$B$7)=0,"-",SUMIFS(Trial_Balance!$H$2:$H$995,Trial_Balance!$I$2:$I$995,$A16,Trial_Balance!$B$2:$B$995,Controls!$B$5&"-Q3",Trial_Balance!$A$2:$A$995,Controls!$B$7)) -> - | E16: =IF(COUNTIFS(Trial_Balance!$B$2:$B$995,Controls!$B$5&"-Q4",Trial_Balance!$A$2:$A$995,Controls!$B$7)=0,"-",SUMIFS(Trial_Balance!$H$2:$H$995,Trial_Balance!$I$2:$I$995,$A16,Trial_Balance!$B$2:$B$995,Controls!$B$5&"-Q4",Trial_Balance!$A$2:$A$995,Controls!$B$7)) -> - | F16: =IF(VALUE(MID(Controls!$B$6,2,1))=1,"-",IF(AND(ISNUMBER(INDEX($B16:$E16,1,VALUE(MID(Controls!$B$6,2,1)))),ISNUMBER(INDEX($B16:$E16,1,VALUE(MID(Controls!$B$6,2,1))-1))),INDEX($B16:$E16,1,VALUE(MID(Controls!$B$6,2,1)))-INDEX($B16:$E16,1,VALUE(MID(Controls!$B$6,2,1))-1),"-")) -> - | G16: =IF(ISNUMBER($F16),IFERROR($F16/ABS(INDEX($B16:$E16,1,VALUE(MID(Controls!$B$6,2,1))-1)),"-"),"-") -> - | H16: =IF(AND(VALUE(MID(Controls!$B$6,2,1))>1,COUNTIFS(Trial_Balance!$B$2:$B$995,Controls!$B$5&"-Q"&(VALUE(MID(Controls!$B$6,2,1))-1),Trial_Balance!$A$2:$A$995,Controls!$B$7)>0),INDEX($B16:$E16,1,VALUE(MID(Controls!$B$6,2,1))-1),IF(COUNTIFS(Trial_Balance!$B$2:$B$995,Controls!$B$30,Trial_Balance!$A$2:$A$995,Controls!$B$7)>0,SUMIFS(Trial_Balance!$E$2:$E$995,Trial_Balance!$I$2:$I$995,$A16,Trial_Balance!$B$2:$B$995,Controls!$B$30,Trial_Balance!$A$2:$A$995,Controls!$B$7),"-")) -> 935770.03 | I16: =INDEX($B16:$E16,1,VALUE(MID(Controls!$B$6,2,1))) -> 1539382.3 | J16: =IF(AND(ISNUMBER($H16),ISNUMBER($I16)),$I16-$H16,"-") -> 603612.29 | K16: =IF(AND(ISNUMBER($J16),ISNUMBER($H16)),IFERROR($J16/ABS($H16),"-"),"-") -> 0.64504341
A17: Total Assets | B17: =IF(COUNTIFS(Trial_Balance!$B$2:$B$995,Controls!$B$5&"-Q1",Trial_Balance!$A$2:$A$995,Controls!$B$7)=0,"-",B8+B13) -> - | C17: =IF(COUNTIFS(Trial_Balance!$B$2:$B$995,Controls!$B$5&"-Q2",Trial_Balance!$A$2:$A$995,Controls!$B$7)=0,"-",C8+C13) -> 11257421 | D17: =IF(COUNTIFS(Trial_Balance!$B$2:$B$995,Controls!$B$5&"-Q3",Trial_Balance!$A$2:$A$995,Controls!$B$7)=0,"-",D8+D13) -> - | E17: =IF(COUNTIFS(Trial_Balance!$B$2:$B$995,Controls!$B$5&"-Q4",Trial_Balance!$A$2:$A$995,Controls!$B$7)=0,"-",E8+E13) -> - | F17: =IF(VALUE(MID(Controls!$B$6,2,1))=1,"-",IF(AND(ISNUMBER(INDEX($B17:$E17,1,VALUE(MID(Controls!$B$6,2,1)))),ISNUMBER(INDEX($B17:$E17,1,VALUE(MID(Controls!$B$6,2,1))-1))),INDEX($B17:$E17,1,VALUE(MID(Controls!$B$6,2,1)))-INDEX($B17:$E17,1,VALUE(MID(Controls!$B$6,2,1))-1),"-")) -> - | G17: =IF(ISNUMBER($F17),IFERROR($F17/ABS(INDEX($B17:$E17,1,VALUE(MID(Controls!$B$6,2,1))-1)),"-"),"-") -> - | H17: =IF(AND(ISNUMBER(H8),ISNUMBER(H13)),H8+H13,"-") -> 9813971.4 | I17: =INDEX($B17:$E17,1,VALUE(MID(Controls!$B$6,2,1))) -> 11257421 | J17: =IF(AND(ISNUMBER($H17),ISNUMBER($I17)),$I17-$H17,"-") -> 1443449.9 | K17: =IF(AND(ISNUMBER($J17),ISNUMBER($H17)),IFERROR($J17/ABS($H17),"-"),"-") -> 0.14708111
A18: Total Current Liabilities | B18: =IF(COUNTIFS(Trial_Balance!$B$2:$B$995,Controls!$B$5&"-Q1",Trial_Balance!$A$2:$A$995,Controls!$B$7)=0,"-",B19+B20) -> - | C18: =IF(COUNTIFS(Trial_Balance!$B$2:$B$995,Controls!$B$5&"-Q2",Trial_Balance!$A$2:$A$995,Controls!$B$7)=0,"-",C19+C20) -> -3241948.6 | D18: =IF(COUNTIFS(Trial_Balance!$B$2:$B$995,Controls!$B$5&"-Q3",Trial_Balance!$A$2:$A$995,Controls!$B$7)=0,"-",D19+D20) -> - | E18: =IF(COUNTIFS(Trial_Balance!$B$2:$B$995,Controls!$B$5&"-Q4",Trial_Balance!$A$2:$A$995,Controls!$B$7)=0,"-",E19+E20) -> - | F18: =IF(VALUE(MID(Controls!$B$6,2,1))=1,"-",IF(AND(ISNUMBER(INDEX($B18:$E18,1,VALUE(MID(Controls!$B$6,2,1)))),ISNUMBER(INDEX($B18:$E18,1,VALUE(MID(Controls!$B$6,2,1))-1))),INDEX($B18:$E18,1,VALUE(MID(Controls!$B$6,2,1)))-INDEX($B18:$E18,1,VALUE(MID(Controls!$B$6,2,1))-1),"-")) -> - | G18: =IF(ISNUMBER($F18),IFERROR($F18/ABS(INDEX($B18:$E18,1,VALUE(MID(Controls!$B$6,2,1))-1)),"-"),"-") -> - | H18: =IF(AND(ISNUMBER(H19),ISNUMBER(H20)),H19+H20,"-") -> -3156685.4 | I18: =INDEX($B18:$E18,1,VALUE(MID(Controls!$B$6,2,1))) -> -3241948.6 | J18: =IF(AND(ISNUMBER($H18),ISNUMBER($I18)),$I18-$H18,"-") -> -85263.18 | K18: =IF(AND(ISNUMBER($J18),ISNUMBER($H18)),IFERROR($J18/ABS($H18),"-"),"-") -> -0.02701035
A19: Trade Creditors | B19: =IF(COUNTIFS(Trial_Balance!$B$2:$B$995,Controls!$B$5&"-Q1",Trial_Balance!$A$2:$A$995,Controls!$B$7)=0,"-",SUMIFS(Trial_Balance!$H$2:$H$995,Trial_Balance!$I$2:$I$995,$A19,Trial_Balance!$B$2:$B$995,Controls!$B$5&"-Q1",Trial_Balance!$A$2:$A$995,Controls!$B$7)) -> - | C19: =IF(COUNTIFS(Trial_Balance!$B$2:$B$995,Controls!$B$5&"-Q2",Trial_Balance!$A$2:$A$995,Controls!$B$7)=0,"-",SUMIFS(Trial_Balance!$H$2:$H$995,Trial_Balance!$I$2:$I$995,$A19,Trial_Balance!$B$2:$B$995,Controls!$B$5&"-Q2",Trial_Balance!$A$2:$A$995,Controls!$B$7)) -> -2328909.3 | D19: =IF(COUNTIFS(Trial_Balance!$B$2:$B$995,Controls!$B$5&"-Q3",Trial_Balance!$A$2:$A$995,Controls!$B$7)=0,"-",SUMIFS(Trial_Balance!$H$2:$H$995,Trial_Balance!$I$2:$I$995,$A19,Trial_Balance!$B$2:$B$995,Controls!$B$5&"-Q3",Trial_Balance!$A$2:$A$995,Controls!$B$7)) -> - | E19: =IF(COUNTIFS(Trial_Balance!$B$2:$B$995,Controls!$B$5&"-Q4",Trial_Balance!$A$2:$A$995,Controls!$B$7)=0,"-",SUMIFS(Trial_Balance!$H$2:$H$995,Trial_Balance!$I$2:$I$995,$A19,Trial_Balance!$B$2:$B$995,Controls!$B$5&"-Q4",Trial_Balance!$A$2:$A$995,Controls!$B$7)) -> - | F19: =IF(VALUE(MID(Controls!$B$6,2,1))=1,"-",IF(AND(ISNUMBER(INDEX($B19:$E19,1,VALUE(MID(Controls!$B$6,2,1)))),ISNUMBER(INDEX($B19:$E19,1,VALUE(MID(Controls!$B$6,2,1))-1))),INDEX($B19:$E19,1,VALUE(MID(Controls!$B$6,2,1)))-INDEX($B19:$E19,1,VALUE(MID(Controls!$B$6,2,1))-1),"-")) -> - | G19: =IF(ISNUMBER($F19),IFERROR($F19/ABS(INDEX($B19:$E19,1,VALUE(MID(Controls!$B$6,2,1))-1)),"-"),"-") -> - | H19: =IF(AND(VALUE(MID(Controls!$B$6,2,1))>1,COUNTIFS(Trial_Balance!$B$2:$B$995,Controls!$B$5&"-Q"&(VALUE(MID(Controls!$B$6,2,1))-1),Trial_Balance!$A$2:$A$995,Controls!$B$7)>0),INDEX($B19:$E19,1,VALUE(MID(Controls!$B$6,2,1))-1),IF(COUNTIFS(Trial_Balance!$B$2:$B$995,Controls!$B$30,Trial_Balance!$A$2:$A$995,Controls!$B$7)>0,SUMIFS(Trial_Balance!$E$2:$E$995,Trial_Balance!$I$2:$I$995,$A19,Trial_Balance!$B$2:$B$995,Controls!$B$30,Trial_Balance!$A$2:$A$995,Controls!$B$7),"-")) -> -2618677 | I19: =INDEX($B19:$E19,1,VALUE(MID(Controls!$B$6,2,1))) -> -2328909.3 | J19: =IF(AND(ISNUMBER($H19),ISNUMBER($I19)),$I19-$H19,"-") -> 289767.68 | K19: =IF(AND(ISNUMBER($J19),ISNUMBER($H19)),IFERROR($J19/ABS($H19),"-"),"-") -> 0.11065423
A20: Other Creditors | B20: =IF(COUNTIFS(Trial_Balance!$B$2:$B$995,Controls!$B$5&"-Q1",Trial_Balance!$A$2:$A$995,Controls!$B$7)=0,"-",SUMIFS(Trial_Balance!$H$2:$H$995,Trial_Balance!$I$2:$I$995,$A20,Trial_Balance!$B$2:$B$995,Controls!$B$5&"-Q1",Trial_Balance!$A$2:$A$995,Controls!$B$7)) -> - | C20: =IF(COUNTIFS(Trial_Balance!$B$2:$B$995,Controls!$B$5&"-Q2",Trial_Balance!$A$2:$A$995,Controls!$B$7)=0,"-",SUMIFS(Trial_Balance!$H$2:$H$995,Trial_Balance!$I$2:$I$995,$A20,Trial_Balance!$B$2:$B$995,Controls!$B$5&"-Q2",Trial_Balance!$A$2:$A$995,Controls!$B$7)) -> -913039.35 | D20: =IF(COUNTIFS(Trial_Balance!$B$2:$B$995,Controls!$B$5&"-Q3",Trial_Balance!$A$2:$A$995,Controls!$B$7)=0,"-",SUMIFS(Trial_Balance!$H$2:$H$995,Trial_Balance!$I$2:$I$995,$A20,Trial_Balance!$B$2:$B$995,Controls!$B$5&"-Q3",Trial_Balance!$A$2:$A$995,Controls!$B$7)) -> - | E20: =IF(COUNTIFS(Trial_Balance!$B$2:$B$995,Controls!$B$5&"-Q4",Trial_Balance!$A$2:$A$995,Controls!$B$7)=0,"-",SUMIFS(Trial_Balance!$H$2:$H$995,Trial_Balance!$I$2:$I$995,$A20,Trial_Balance!$B$2:$B$995,Controls!$B$5&"-Q4",Trial_Balance!$A$2:$A$995,Controls!$B$7)) -> - | F20: =IF(VALUE(MID(Controls!$B$6,2,1))=1,"-",IF(AND(ISNUMBER(INDEX($B20:$E20,1,VALUE(MID(Controls!$B$6,2,1)))),ISNUMBER(INDEX($B20:$E20,1,VALUE(MID(Controls!$B$6,2,1))-1))),INDEX($B20:$E20,1,VALUE(MID(Controls!$B$6,2,1)))-INDEX($B20:$E20,1,VALUE(MID(Controls!$B$6,2,1))-1),"-")) -> - | G20: =IF(ISNUMBER($F20),IFERROR($F20/ABS(INDEX($B20:$E20,1,VALUE(MID(Controls!$B$6,2,1))-1)),"-"),"-") -> - | H20: =IF(AND(VALUE(MID(Controls!$B$6,2,1))>1,COUNTIFS(Trial_Balance!$B$2:$B$995,Controls!$B$5&"-Q"&(VALUE(MID(Controls!$B$6,2,1))-1),Trial_Balance!$A$2:$A$995,Controls!$B$7)>0),INDEX($B20:$E20,1,VALUE(MID(Controls!$B$6,2,1))-1),IF(COUNTIFS(Trial_Balance!$B$2:$B$995,Controls!$B$30,Trial_Balance!$A$2:$A$995,Controls!$B$7)>0,SUMIFS(Trial_Balance!$E$2:$E$995,Trial_Balance!$I$2:$I$995,$A20,Trial_Balance!$B$2:$B$995,Controls!$B$30,Trial_Balance!$A$2:$A$995,Controls!$B$7),"-")) -> -538008.49 | I20: =INDEX($B20:$E20,1,VALUE(MID(Controls!$B$6,2,1))) -> -913039.35 | J20: =IF(AND(ISNUMBER($H20),ISNUMBER($I20)),$I20-$H20,"-") -> -375030.86 | K20: =IF(AND(ISNUMBER($J20),ISNUMBER($H20)),IFERROR($J20/ABS($H20),"-"),"-") -> -0.69707238
A21: Long Term Liabilities | B21: =IF(COUNTIFS(Trial_Balance!$B$2:$B$995,Controls!$B$5&"-Q1",Trial_Balance!$A$2:$A$995,Controls!$B$7)=0,"-",B22) -> - | C21: =IF(COUNTIFS(Trial_Balance!$B$2:$B$995,Controls!$B$5&"-Q2",Trial_Balance!$A$2:$A$995,Controls!$B$7)=0,"-",C22) -> -0.33 | D21: =IF(COUNTIFS(Trial_Balance!$B$2:$B$995,Controls!$B$5&"-Q3",Trial_Balance!$A$2:$A$995,Controls!$B$7)=0,"-",D22) -> - | E21: =IF(COUNTIFS(Trial_Balance!$B$2:$B$995,Controls!$B$5&"-Q4",Trial_Balance!$A$2:$A$995,Controls!$B$7)=0,"-",E22) -> - | F21: =IF(VALUE(MID(Controls!$B$6,2,1))=1,"-",IF(AND(ISNUMBER(INDEX($B21:$E21,1,VALUE(MID(Controls!$B$6,2,1)))),ISNUMBER(INDEX($B21:$E21,1,VALUE(MID(Controls!$B$6,2,1))-1))),INDEX($B21:$E21,1,VALUE(MID(Controls!$B$6,2,1)))-INDEX($B21:$E21,1,VALUE(MID(Controls!$B$6,2,1))-1),"-")) -> - | G21: =IF(ISNUMBER($F21),IFERROR($F21/ABS(INDEX($B21:$E21,1,VALUE(MID(Controls!$B$6,2,1))-1)),"-"),"-") -> - | H21: =IF(ISNUMBER(H22),H22,"-") -> -0.33 | I21: =INDEX($B21:$E21,1,VALUE(MID(Controls!$B$6,2,1))) -> -0.33 | J21: =IF(AND(ISNUMBER($H21),ISNUMBER($I21)),$I21-$H21,"-") -> 0 | K21: =IF(AND(ISNUMBER($J21),ISNUMBER($H21)),IFERROR($J21/ABS($H21),"-"),"-") -> 0
A22: Loans > 1 year | B22: =IF(COUNTIFS(Trial_Balance!$B$2:$B$995,Controls!$B$5&"-Q1",Trial_Balance!$A$2:$A$995,Controls!$B$7)=0,"-",SUMIFS(Trial_Balance!$H$2:$H$995,Trial_Balance!$I$2:$I$995,$A22,Trial_Balance!$B$2:$B$995,Controls!$B$5&"-Q1",Trial_Balance!$A$2:$A$995,Controls!$B$7)) -> - | C22: =IF(COUNTIFS(Trial_Balance!$B$2:$B$995,Controls!$B$5&"-Q2",Trial_Balance!$A$2:$A$995,Controls!$B$7)=0,"-",SUMIFS(Trial_Balance!$H$2:$H$995,Trial_Balance!$I$2:$I$995,$A22,Trial_Balance!$B$2:$B$995,Controls!$B$5&"-Q2",Trial_Balance!$A$2:$A$995,Controls!$B$7)) -> -0.33 | D22: =IF(COUNTIFS(Trial_Balance!$B$2:$B$995,Controls!$B$5&"-Q3",Trial_Balance!$A$2:$A$995,Controls!$B$7)=0,"-",SUMIFS(Trial_Balance!$H$2:$H$995,Trial_Balance!$I$2:$I$995,$A22,Trial_Balance!$B$2:$B$995,Controls!$B$5&"-Q3",Trial_Balance!$A$2:$A$995,Controls!$B$7)) -> - | E22: =IF(COUNTIFS(Trial_Balance!$B$2:$B$995,Controls!$B$5&"-Q4",Trial_Balance!$A$2:$A$995,Controls!$B$7)=0,"-",SUMIFS(Trial_Balance!$H$2:$H$995,Trial_Balance!$I$2:$I$995,$A22,Trial_Balance!$B$2:$B$995,Controls!$B$5&"-Q4",Trial_Balance!$A$2:$A$995,Controls!$B$7)) -> - | F22: =IF(VALUE(MID(Controls!$B$6,2,1))=1,"-",IF(AND(ISNUMBER(INDEX($B22:$E22,1,VALUE(MID(Controls!$B$6,2,1)))),ISNUMBER(INDEX($B22:$E22,1,VALUE(MID(Controls!$B$6,2,1))-1))),INDEX($B22:$E22,1,VALUE(MID(Controls!$B$6,2,1)))-INDEX($B22:$E22,1,VALUE(MID(Controls!$B$6,2,1))-1),"-")) -> - | G22: =IF(ISNUMBER($F22),IFERROR($F22/ABS(INDEX($B22:$E22,1,VALUE(MID(Controls!$B$6,2,1))-1)),"-"),"-") -> - | H22: =IF(AND(VALUE(MID(Controls!$B$6,2,1))>1,COUNTIFS(Trial_Balance!$B$2:$B$995,Controls!$B$5&"-Q"&(VALUE(MID(Controls!$B$6,2,1))-1),Trial_Balance!$A$2:$A$995,Controls!$B$7)>0),INDEX($B22:$E22,1,VALUE(MID(Controls!$B$6,2,1))-1),IF(COUNTIFS(Trial_Balance!$B$2:$B$995,Controls!$B$30,Trial_Balance!$A$2:$A$995,Controls!$B$7)>0,SUMIFS(Trial_Balance!$E$2:$E$995,Trial_Balance!$I$2:$I$995,$A22,Trial_Balance!$B$2:$B$995,Controls!$B$30,Trial_Balance!$A$2:$A$995,Controls!$B$7),"-")) -> -0.33 | I22: =INDEX($B22:$E22,1,VALUE(MID(Controls!$B$6,2,1))) -> -0.33 | J22: =IF(AND(ISNUMBER($H22),ISNUMBER($I22)),$I22-$H22,"-") -> 0 | K22: =IF(AND(ISNUMBER($J22),ISNUMBER($H22)),IFERROR($J22/ABS($H22),"-"),"-") -> 0
A23: Total Liabilities | B23: =IF(COUNTIFS(Trial_Balance!$B$2:$B$995,Controls!$B$5&"-Q1",Trial_Balance!$A$2:$A$995,Controls!$B$7)=0,"-",B18+B21) -> - | C23: =IF(COUNTIFS(Trial_Balance!$B$2:$B$995,Controls!$B$5&"-Q2",Trial_Balance!$A$2:$A$995,Controls!$B$7)=0,"-",C18+C21) -> -3241949 | D23: =IF(COUNTIFS(Trial_Balance!$B$2:$B$995,Controls!$B$5&"-Q3",Trial_Balance!$A$2:$A$995,Controls!$B$7)=0,"-",D18+D21) -> - | E23: =IF(COUNTIFS(Trial_Balance!$B$2:$B$995,Controls!$B$5&"-Q4",Trial_Balance!$A$2:$A$995,Controls!$B$7)=0,"-",E18+E21) -> - | F23: =IF(VALUE(MID(Controls!$B$6,2,1))=1,"-",IF(AND(ISNUMBER(INDEX($B23:$E23,1,VALUE(MID(Controls!$B$6,2,1)))),ISNUMBER(INDEX($B23:$E23,1,VALUE(MID(Controls!$B$6,2,1))-1))),INDEX($B23:$E23,1,VALUE(MID(Controls!$B$6,2,1)))-INDEX($B23:$E23,1,VALUE(MID(Controls!$B$6,2,1))-1),"-")) -> - | G23: =IF(ISNUMBER($F23),IFERROR($F23/ABS(INDEX($B23:$E23,1,VALUE(MID(Controls!$B$6,2,1))-1)),"-"),"-") -> - | H23: =IF(AND(ISNUMBER(H18),ISNUMBER(H21)),H18+H21,"-") -> -3156685.8 | I23: =INDEX($B23:$E23,1,VALUE(MID(Controls!$B$6,2,1))) -> -3241949 | J23: =IF(AND(ISNUMBER($H23),ISNUMBER($I23)),$I23-$H23,"-") -> -85263.18 | K23: =IF(AND(ISNUMBER($J23),ISNUMBER($H23)),IFERROR($J23/ABS($H23),"-"),"-") -> -0.027010348
A24: Total Assets Less Liabilities | B24: =IF(COUNTIFS(Trial_Balance!$B$2:$B$995,Controls!$B$5&"-Q1",Trial_Balance!$A$2:$A$995,Controls!$B$7)=0,"-",B17+B23) -> - | C24: =IF(COUNTIFS(Trial_Balance!$B$2:$B$995,Controls!$B$5&"-Q2",Trial_Balance!$A$2:$A$995,Controls!$B$7)=0,"-",C17+C23) -> 8015472.3 | D24: =IF(COUNTIFS(Trial_Balance!$B$2:$B$995,Controls!$B$5&"-Q3",Trial_Balance!$A$2:$A$995,Controls!$B$7)=0,"-",D17+D23) -> - | E24: =IF(COUNTIFS(Trial_Balance!$B$2:$B$995,Controls!$B$5&"-Q4",Trial_Balance!$A$2:$A$995,Controls!$B$7)=0,"-",E17+E23) -> - | F24: =IF(VALUE(MID(Controls!$B$6,2,1))=1,"-",IF(AND(ISNUMBER(INDEX($B24:$E24,1,VALUE(MID(Controls!$B$6,2,1)))),ISNUMBER(INDEX($B24:$E24,1,VALUE(MID(Controls!$B$6,2,1))-1))),INDEX($B24:$E24,1,VALUE(MID(Controls!$B$6,2,1)))-INDEX($B24:$E24,1,VALUE(MID(Controls!$B$6,2,1))-1),"-")) -> - | G24: =IF(ISNUMBER($F24),IFERROR($F24/ABS(INDEX($B24:$E24,1,VALUE(MID(Controls!$B$6,2,1))-1)),"-"),"-") -> - | H24: =IF(AND(ISNUMBER(H17),ISNUMBER(H23)),H17+H23,"-") -> 6657285.7 | I24: =INDEX($B24:$E24,1,VALUE(MID(Controls!$B$6,2,1))) -> 8015472.3 | J24: =IF(AND(ISNUMBER($H24),ISNUMBER($I24)),$I24-$H24,"-") -> 1358186.7 | K24: =IF(AND(ISNUMBER($J24),ISNUMBER($H24)),IFERROR($J24/ABS($H24),"-"),"-") -> 0.20401508
A25: Total Capital and Reserves | B25: =IF(COUNTIFS(Trial_Balance!$B$2:$B$995,Controls!$B$5&"-Q1",Trial_Balance!$A$2:$A$995,Controls!$B$7)=0,"-",B26+B27+B28) -> - | C25: =IF(COUNTIFS(Trial_Balance!$B$2:$B$995,Controls!$B$5&"-Q2",Trial_Balance!$A$2:$A$995,Controls!$B$7)=0,"-",C26+C27+C28) -> -8015472.3 | D25: =IF(COUNTIFS(Trial_Balance!$B$2:$B$995,Controls!$B$5&"-Q3",Trial_Balance!$A$2:$A$995,Controls!$B$7)=0,"-",D26+D27+D28) -> - | E25: =IF(COUNTIFS(Trial_Balance!$B$2:$B$995,Controls!$B$5&"-Q4",Trial_Balance!$A$2:$A$995,Controls!$B$7)=0,"-",E26+E27+E28) -> - | F25: =IF(VALUE(MID(Controls!$B$6,2,1))=1,"-",IF(AND(ISNUMBER(INDEX($B25:$E25,1,VALUE(MID(Controls!$B$6,2,1)))),ISNUMBER(INDEX($B25:$E25,1,VALUE(MID(Controls!$B$6,2,1))-1))),INDEX($B25:$E25,1,VALUE(MID(Controls!$B$6,2,1)))-INDEX($B25:$E25,1,VALUE(MID(Controls!$B$6,2,1))-1),"-")) -> - | G25: =IF(ISNUMBER($F25),IFERROR($F25/ABS(INDEX($B25:$E25,1,VALUE(MID(Controls!$B$6,2,1))-1)),"-"),"-") -> - | H25: =IF(ISNUMBER(H26),SUM(H26:H28),"-") -> -6657285.7 | I25: =INDEX($B25:$E25,1,VALUE(MID(Controls!$B$6,2,1))) -> -8015472.3 | J25: =IF(AND(ISNUMBER($H25),ISNUMBER($I25)),$I25-$H25,"-") -> -1358186.7 | K25: =IF(AND(ISNUMBER($J25),ISNUMBER($H25)),IFERROR($J25/ABS($H25),"-"),"-") -> -0.20401508
A26: Share Capital | B26: =IF(COUNTIFS(Trial_Balance!$B$2:$B$995,Controls!$B$5&"-Q1",Trial_Balance!$A$2:$A$995,Controls!$B$7)=0,"-",SUMIFS(Trial_Balance!$H$2:$H$995,Trial_Balance!$I$2:$I$995,$A26,Trial_Balance!$B$2:$B$995,Controls!$B$5&"-Q1",Trial_Balance!$A$2:$A$995,Controls!$B$7)) -> - | C26: =IF(COUNTIFS(Trial_Balance!$B$2:$B$995,Controls!$B$5&"-Q2",Trial_Balance!$A$2:$A$995,Controls!$B$7)=0,"-",SUMIFS(Trial_Balance!$H$2:$H$995,Trial_Balance!$I$2:$I$995,$A26,Trial_Balance!$B$2:$B$995,Controls!$B$5&"-Q2",Trial_Balance!$A$2:$A$995,Controls!$B$7)) -> -19999.87 | D26: =IF(COUNTIFS(Trial_Balance!$B$2:$B$995,Controls!$B$5&"-Q3",Trial_Balance!$A$2:$A$995,Controls!$B$7)=0,"-",SUMIFS(Trial_Balance!$H$2:$H$995,Trial_Balance!$I$2:$I$995,$A26,Trial_Balance!$B$2:$B$995,Controls!$B$5&"-Q3",Trial_Balance!$A$2:$A$995,Controls!$B$7)) -> - | E26: =IF(COUNTIFS(Trial_Balance!$B$2:$B$995,Controls!$B$5&"-Q4",Trial_Balance!$A$2:$A$995,Controls!$B$7)=0,"-",SUMIFS(Trial_Balance!$H$2:$H$995,Trial_Balance!$I$2:$I$995,$A26,Trial_Balance!$B$2:$B$995,Controls!$B$5&"-Q4",Trial_Balance!$A$2:$A$995,Controls!$B$7)) -> - | F26: =IF(VALUE(MID(Controls!$B$6,2,1))=1,"-",IF(AND(ISNUMBER(INDEX($B26:$E26,1,VALUE(MID(Controls!$B$6,2,1)))),ISNUMBER(INDEX($B26:$E26,1,VALUE(MID(Controls!$B$6,2,1))-1))),INDEX($B26:$E26,1,VALUE(MID(Controls!$B$6,2,1)))-INDEX($B26:$E26,1,VALUE(MID(Controls!$B$6,2,1))-1),"-")) -> - | G26: =IF(ISNUMBER($F26),IFERROR($F26/ABS(INDEX($B26:$E26,1,VALUE(MID(Controls!$B$6,2,1))-1)),"-"),"-") -> - | H26: =IF(AND(VALUE(MID(Controls!$B$6,2,1))>1,COUNTIFS(Trial_Balance!$B$2:$B$995,Controls!$B$5&"-Q"&(VALUE(MID(Controls!$B$6,2,1))-1),Trial_Balance!$A$2:$A$995,Controls!$B$7)>0),INDEX($B26:$E26,1,VALUE(MID(Controls!$B$6,2,1))-1),IF(COUNTIFS(Trial_Balance!$B$2:$B$995,Controls!$B$30,Trial_Balance!$A$2:$A$995,Controls!$B$7)>0,SUMIFS(Trial_Balance!$E$2:$E$995,Trial_Balance!$I$2:$I$995,$A26,Trial_Balance!$B$2:$B$995,Controls!$B$30,Trial_Balance!$A$2:$A$995,Controls!$B$7),"-")) -> -19999.87 | I26: =INDEX($B26:$E26,1,VALUE(MID(Controls!$B$6,2,1))) -> -19999.87 | J26: =IF(AND(ISNUMBER($H26),ISNUMBER($I26)),$I26-$H26,"-") -> 0 | K26: =IF(AND(ISNUMBER($J26),ISNUMBER($H26)),IFERROR($J26/ABS($H26),"-"),"-") -> 0
A27: Retained Reserves | B27: =IF(COUNTIFS(Trial_Balance!$B$2:$B$995,Controls!$B$5&"-Q1",Trial_Balance!$A$2:$A$995,Controls!$B$7)=0,"-",SUMIFS(Trial_Balance!$H$2:$H$995,Trial_Balance!$I$2:$I$995,$A27,Trial_Balance!$B$2:$B$995,Controls!$B$5&"-Q1",Trial_Balance!$A$2:$A$995,Controls!$B$7)) -> - | C27: =IF(COUNTIFS(Trial_Balance!$B$2:$B$995,Controls!$B$5&"-Q2",Trial_Balance!$A$2:$A$995,Controls!$B$7)=0,"-",SUMIFS(Trial_Balance!$H$2:$H$995,Trial_Balance!$I$2:$I$995,$A27,Trial_Balance!$B$2:$B$995,Controls!$B$5&"-Q2",Trial_Balance!$A$2:$A$995,Controls!$B$7)) -> -5476585 | D27: =IF(COUNTIFS(Trial_Balance!$B$2:$B$995,Controls!$B$5&"-Q3",Trial_Balance!$A$2:$A$995,Controls!$B$7)=0,"-",SUMIFS(Trial_Balance!$H$2:$H$995,Trial_Balance!$I$2:$I$995,$A27,Trial_Balance!$B$2:$B$995,Controls!$B$5&"-Q3",Trial_Balance!$A$2:$A$995,Controls!$B$7)) -> - | E27: =IF(COUNTIFS(Trial_Balance!$B$2:$B$995,Controls!$B$5&"-Q4",Trial_Balance!$A$2:$A$995,Controls!$B$7)=0,"-",SUMIFS(Trial_Balance!$H$2:$H$995,Trial_Balance!$I$2:$I$995,$A27,Trial_Balance!$B$2:$B$995,Controls!$B$5&"-Q4",Trial_Balance!$A$2:$A$995,Controls!$B$7)) -> - | F27: =IF(VALUE(MID(Controls!$B$6,2,1))=1,"-",IF(AND(ISNUMBER(INDEX($B27:$E27,1,VALUE(MID(Controls!$B$6,2,1)))),ISNUMBER(INDEX($B27:$E27,1,VALUE(MID(Controls!$B$6,2,1))-1))),INDEX($B27:$E27,1,VALUE(MID(Controls!$B$6,2,1)))-INDEX($B27:$E27,1,VALUE(MID(Controls!$B$6,2,1))-1),"-")) -> - | G27: =IF(ISNUMBER($F27),IFERROR($F27/ABS(INDEX($B27:$E27,1,VALUE(MID(Controls!$B$6,2,1))-1)),"-"),"-") -> - | H27: =IF(AND(VALUE(MID(Controls!$B$6,2,1))>1,COUNTIFS(Trial_Balance!$B$2:$B$995,Controls!$B$5&"-Q"&(VALUE(MID(Controls!$B$6,2,1))-1),Trial_Balance!$A$2:$A$995,Controls!$B$7)>0),INDEX($B27:$E27,1,VALUE(MID(Controls!$B$6,2,1))-1),IF(COUNTIFS(Trial_Balance!$B$2:$B$995,Controls!$B$30,Trial_Balance!$A$2:$A$995,Controls!$B$7)>0,SUMIFS(Trial_Balance!$E$2:$E$995,Trial_Balance!$I$2:$I$995,$A27,Trial_Balance!$B$2:$B$995,Controls!$B$30,Trial_Balance!$A$2:$A$995,Controls!$B$7),"-")) -> -5476585 | I27: =INDEX($B27:$E27,1,VALUE(MID(Controls!$B$6,2,1))) -> -5476585 | J27: =IF(AND(ISNUMBER($H27),ISNUMBER($I27)),$I27-$H27,"-") -> 0 | K27: =IF(AND(ISNUMBER($J27),ISNUMBER($H27)),IFERROR($J27/ABS($H27),"-"),"-") -> 0
A28: Current P&L | B28: =IF(COUNTIFS(Trial_Balance!$B$2:$B$995,Controls!$B$5&"-Q1",Trial_Balance!$A$2:$A$995,Controls!$B$7)=0,"-",SUMIFS(Trial_Balance!$H$2:$H$995,Trial_Balance!$I$2:$I$995,$A28,Trial_Balance!$B$2:$B$995,Controls!$B$5&"-Q1",Trial_Balance!$A$2:$A$995,Controls!$B$7)) -> - | C28: =IF(COUNTIFS(Trial_Balance!$B$2:$B$995,Controls!$B$5&"-Q2",Trial_Balance!$A$2:$A$995,Controls!$B$7)=0,"-",SUMIFS(Trial_Balance!$H$2:$H$995,Trial_Balance!$I$2:$I$995,$A28,Trial_Balance!$B$2:$B$995,Controls!$B$5&"-Q2",Trial_Balance!$A$2:$A$995,Controls!$B$7)) -> -2518887.5 | D28: =IF(COUNTIFS(Trial_Balance!$B$2:$B$995,Controls!$B$5&"-Q3",Trial_Balance!$A$2:$A$995,Controls!$B$7)=0,"-",SUMIFS(Trial_Balance!$H$2:$H$995,Trial_Balance!$I$2:$I$995,$A28,Trial_Balance!$B$2:$B$995,Controls!$B$5&"-Q3",Trial_Balance!$A$2:$A$995,Controls!$B$7)) -> - | E28: =IF(COUNTIFS(Trial_Balance!$B$2:$B$995,Controls!$B$5&"-Q4",Trial_Balance!$A$2:$A$995,Controls!$B$7)=0,"-",SUMIFS(Trial_Balance!$H$2:$H$995,Trial_Balance!$I$2:$I$995,$A28,Trial_Balance!$B$2:$B$995,Controls!$B$5&"-Q4",Trial_Balance!$A$2:$A$995,Controls!$B$7)) -> - | F28: =IF(VALUE(MID(Controls!$B$6,2,1))=1,"-",IF(AND(ISNUMBER(INDEX($B28:$E28,1,VALUE(MID(Controls!$B$6,2,1)))),ISNUMBER(INDEX($B28:$E28,1,VALUE(MID(Controls!$B$6,2,1))-1))),INDEX($B28:$E28,1,VALUE(MID(Controls!$B$6,2,1)))-INDEX($B28:$E28,1,VALUE(MID(Controls!$B$6,2,1))-1),"-")) -> - | G28: =IF(ISNUMBER($F28),IFERROR($F28/ABS(INDEX($B28:$E28,1,VALUE(MID(Controls!$B$6,2,1))-1)),"-"),"-") -> - | H28: =IF(AND(VALUE(MID(Controls!$B$6,2,1))>1,COUNTIFS(Trial_Balance!$B$2:$B$995,Controls!$B$5&"-Q"&(VALUE(MID(Controls!$B$6,2,1))-1),Trial_Balance!$A$2:$A$995,Controls!$B$7)>0),INDEX($B28:$E28,1,VALUE(MID(Controls!$B$6,2,1))-1),IF(COUNTIFS(Trial_Balance!$B$2:$B$995,Controls!$B$30,Trial_Balance!$A$2:$A$995,Controls!$B$7)>0,SUMIFS(Trial_Balance!$E$2:$E$995,Trial_Balance!$I$2:$I$995,$A28,Trial_Balance!$B$2:$B$995,Controls!$B$30,Trial_Balance!$A$2:$A$995,Controls!$B$7),"-")) -> -1160700.8 | I28: =INDEX($B28:$E28,1,VALUE(MID(Controls!$B$6,2,1))) -> -2518887.5 | J28: =IF(AND(ISNUMBER($H28),ISNUMBER($I28)),$I28-$H28,"-") -> -1358186.7 | K28: =IF(AND(ISNUMBER($J28),ISNUMBER($H28)),IFERROR($J28/ABS($H28),"-"),"-") -> -1.1701436
H29: Opening | I29: Closing
A30: Balance Sheet Check (Assets − Liabilities − Capital) | C30: =IF(ISNUMBER(B17),B24+B25,0) -> 0 | D30: =IF(ISNUMBER(C17),C24+C25,0) -> 0 | E30: =IF(ISNUMBER(D17),D24+D25,0) -> 0 | F30: =IF(ISNUMBER(E17),E24+E25,0) -> 0 | H30: =IF(ISNUMBER(H24),H24+H25,0) -> 0 | I30: =IF(ISNUMBER(I24),I24+I25,0) -> 0
A32: Ratios and Liquidity
A33: Current Ratio | C33: =IFERROR(IF(AND(ISNUMBER(B13),ISNUMBER(B18)),B13/ABS(B18),"-"),"-") -> - | D33: =IFERROR(IF(AND(ISNUMBER(C13),ISNUMBER(C18)),C13/ABS(C18),"-"),"-") -> 2.761659 | E33: =IFERROR(IF(AND(ISNUMBER(D13),ISNUMBER(D18)),D13/ABS(D18),"-"),"-") -> - | F33: =IFERROR(IF(AND(ISNUMBER(E13),ISNUMBER(E18)),E13/ABS(E18),"-"),"-") -> -
A34: Working Capital | C34: =IF(AND(ISNUMBER(B13),ISNUMBER(B18)),B13+B18,"-") -> - | D34: =IF(AND(ISNUMBER(C13),ISNUMBER(C18)),C13+C18,"-") -> 5711207.9 | E34: =IF(AND(ISNUMBER(D13),ISNUMBER(D18)),D13+D18,"-") -> - | F34: =IF(AND(ISNUMBER(E13),ISNUMBER(E18)),E13+E18,"-") -> -
A35: Core Fixed Costs per Month | C35: =SUMIFS(MM_FixedCost!$F$5:$F$78,MM_FixedCost!$E$5:$E$78,"Core")/12 -> 989163.76 | D35: =SUMIFS(MM_FixedCost!$F$5:$F$78,MM_FixedCost!$E$5:$E$78,"Core")/12 -> 989163.76 | E35: =SUMIFS(MM_FixedCost!$F$5:$F$78,MM_FixedCost!$E$5:$E$78,"Core")/12 -> 989163.76 | F35: =SUMIFS(MM_FixedCost!$F$5:$F$78,MM_FixedCost!$E$5:$E$78,"Core")/12 -> 989163.76
A36: Months of Core Cost Cover | C36: =IFERROR(C34/C35,"-") -> - | D36: =IFERROR(D34/D35,"-") -> 5.7737739 | E36: =IFERROR(E34/E35,"-") -> - | F36: =IFERROR(F34/F35,"-") -> -
A37: Intercompany Net Position | C37: =IF(COUNTIFS(Trial_Balance!$B$2:$B$995,Controls!$B$5&"-Q1",Trial_Balance!$A$2:$A$995,Controls!$B$7)=0,"-",SUMIFS(Trial_Balance!$H$2:$H$995,Trial_Balance!$J$2:$J$995,"?*",Trial_Balance!$B$2:$B$995,Controls!$B$5&"-Q1",Trial_Balance!$A$2:$A$995,Controls!$B$7)) -> - | D37: =IF(COUNTIFS(Trial_Balance!$B$2:$B$995,Controls!$B$5&"-Q2",Trial_Balance!$A$2:$A$995,Controls!$B$7)=0,"-",SUMIFS(Trial_Balance!$H$2:$H$995,Trial_Balance!$J$2:$J$995,"?*",Trial_Balance!$B$2:$B$995,Controls!$B$5&"-Q2",Trial_Balance!$A$2:$A$995,Controls!$B$7)) -> 134284.6 | E37: =IF(COUNTIFS(Trial_Balance!$B$2:$B$995,Controls!$B$5&"-Q3",Trial_Balance!$A$2:$A$995,Controls!$B$7)=0,"-",SUMIFS(Trial_Balance!$H$2:$H$995,Trial_Balance!$J$2:$J$995,"?*",Trial_Balance!$B$2:$B$995,Controls!$B$5&"-Q3",Trial_Balance!$A$2:$A$995,Controls!$B$7)) -> - | F37: =IF(COUNTIFS(Trial_Balance!$B$2:$B$995,Controls!$B$5&"-Q4",Trial_Balance!$A$2:$A$995,Controls!$B$7)=0,"-",SUMIFS(Trial_Balance!$H$2:$H$995,Trial_Balance!$J$2:$J$995,"?*",Trial_Balance!$B$2:$B$995,Controls!$B$5&"-Q4",Trial_Balance!$A$2:$A$995,Controls!$B$7)) -> -
A38: Balance Sheet Check | C38: =C30 -> 0 | D38: =D30 -> 0 | E38: =E30 -> 0 | F38: =F30 -> 0
A39: Opening ↔ prior Closing continuity (Q2 Opening − Q1 Closing, etc.) | C39: n/a | D39: =IFERROR(IF(OR(COUNTIFS(Trial_Balance!$B$2:$B$995,Controls!$B$5&"-Q2",Trial_Balance!$A$2:$A$995,Controls!$B$7)=0,B17="-"),"-",SUMPRODUCT(SUMIFS(Trial_Balance!$E$2:$E$995,Trial_Balance!$I$2:$I$995,$A$9:$A$12,Trial_Balance!$B$2:$B$995,Controls!$B$5&"-Q2",Trial_Balance!$A$2:$A$995,Controls!$B$7))+SUMPRODUCT(SUMIFS(Trial_Balance!$E$2:$E$995,Trial_Balance!$I$2:$I$995,$A$14:$A$16,Trial_Balance!$B$2:$B$995,Controls!$B$5&"-Q2",Trial_Balance!$A$2:$A$995,Controls!$B$7))-N(B17)),"-") -> - | E39: =IFERROR(IF(OR(COUNTIFS(Trial_Balance!$B$2:$B$995,Controls!$B$5&"-Q3",Trial_Balance!$A$2:$A$995,Controls!$B$7)=0,C17="-"),"-",SUMPRODUCT(SUMIFS(Trial_Balance!$E$2:$E$995,Trial_Balance!$I$2:$I$995,$A$9:$A$12,Trial_Balance!$B$2:$B$995,Controls!$B$5&"-Q3",Trial_Balance!$A$2:$A$995,Controls!$B$7))+SUMPRODUCT(SUMIFS(Trial_Balance!$E$2:$E$995,Trial_Balance!$I$2:$I$995,$A$14:$A$16,Trial_Balance!$B$2:$B$995,Controls!$B$5&"-Q3",Trial_Balance!$A$2:$A$995,Controls!$B$7))-N(C17)),"-") -> - | F39: =IFERROR(IF(OR(COUNTIFS(Trial_Balance!$B$2:$B$995,Controls!$B$5&"-Q4",Trial_Balance!$A$2:$A$995,Controls!$B$7)=0,D17="-"),"-",SUMPRODUCT(SUMIFS(Trial_Balance!$E$2:$E$995,Trial_Balance!$I$2:$I$995,$A$9:$A$12,Trial_Balance!$B$2:$B$995,Controls!$B$5&"-Q4",Trial_Balance!$A$2:$A$995,Controls!$B$7))+SUMPRODUCT(SUMIFS(Trial_Balance!$E$2:$E$995,Trial_Balance!$I$2:$I$995,$A$14:$A$16,Trial_Balance!$B$2:$B$995,Controls!$B$5&"-Q4",Trial_Balance!$A$2:$A$995,Controls!$B$7))-N(D17)),"-") -> -

Sheet TB_Review
A1: ="Trial Balance Review — "&Controls!$B$8&" — "&$O$1 -> Trial Balance Review — PC Ghana — 2026-Q2 | N1: Effective TB Review Period | O1: =IF(COUNTIFS(Trial_Balance!$B$2:$B$995,Controls!$B$30,Trial_Balance!$A$2:$A$995,Controls!$B$7)>0,Controls!$B$30,IF(COUNTIFS(Trial_Balance!$B$2:$B$995,Controls!$B$5&"-Q4",Trial_Balance!$A$2:$A$995,Controls!$B$7)>0,Controls!$B$5&"-Q4",IF(COUNTIFS(Trial_Balance!$B$2:$B$995,Controls!$B$5&"-Q3",Trial_Balance!$A$2:$A$995,Controls!$B$7)>0,Controls!$B$5&"-Q3",IF(COUNTIFS(Trial_Balance!$B$2:$B$995,Controls!$B$5&"-Q2",Trial_Balance!$A$2:$A$995,Controls!$B$7)>0,Controls!$B$5&"-Q2",IF(COUNTIFS(Trial_Balance!$B$2:$B$995,Controls!$B$5&"-Q1",Trial_Balance!$A$2:$A$995,Controls!$B$7)>0,Controls!$B$5&"-Q1",Controls!$B$30))))) -> 2026-Q2 | P1: (auto-falls back to latest loaded quarter if selected has no TB rows)
A2: Finance quality-control view: completeness, movements, exceptions and review tracking for the selected quarter.
A3: TB ROWS · SELECTED QTR | C3: BALANCE CHECK (Σ CLOSING) | E3: UNMAPPED ACCOUNTS | G3: DUPLICATE ACCT-PERIOD
A4: =COUNTIFS(Trial_Balance!$B$2:$B$995,$O$1,Trial_Balance!$A$2:$A$995,Controls!$B$7) -> 118 | C4: =SUMIFS(Trial_Balance!$H$2:$H$995,Trial_Balance!$B$2:$B$995,$O$1,Trial_Balance!$A$2:$A$995,Controls!$B$7) -> 6.7757242e-10 | E4: =Checks!$B$24 -> 0 | G4: =Checks!$B$33 -> 0
A6: NO-MOVEMENT BALANCES | C6: UNEXPECTED SIGN | E6: LARGEST MOVEMENT (ABS) | G6: INTERCOMPANY NET
A7: =SUM($K$41:$K$170) -> 18 | C7: =SUM($L$41:$L$170) -> 11 | E7: =IFERROR(LARGE($J$41:$J$170,1),0) -> 2260770.6 | G7: =IFERROR(--INDEX(Balance_Sheet!$C$37:$F$37,1,VALUE(MID(Controls!$B$6,2,1))),0) -> 134284.6
H8: MOVEMENT BY ACCOUNT (GHS)
A9: TOP 10 ACCOUNT MOVEMENTS — SELECTED QUARTER (GHS)
A10: Rank | B10: Account | C10: Description | D10: Opening | E10: Closing | F10: Movement
A11: 1 | B11: =IFERROR(INDEX($A:$A,MATCH(LARGE($J$41:$J$170,1),$J$41:$J$170,0)+40),"—") -> 4000 | C11: =IFERROR(INDEX($B:$B,MATCH(LARGE($J$41:$J$170,1),$J$41:$J$170,0)+40),"—") -> Consultancy (Fees Contract) Income | D11: =IFERROR(INDEX($E:$E,MATCH(LARGE($J$41:$J$170,1),$J$41:$J$170,0)+40),"—") -> -2449460 | E11: =IFERROR(INDEX($H:$H,MATCH(LARGE($J$41:$J$170,1),$J$41:$J$170,0)+40),"—") -> -4710230.6 | F11: =IFERROR(INDEX($I:$I,MATCH(LARGE($J$41:$J$170,1),$J$41:$J$170,0)+40),"—") -> -2260770.6
A12: 2 | B12: =IFERROR(INDEX($A:$A,MATCH(LARGE($J$41:$J$170,2),$J$41:$J$170,0)+40),"—") -> 4050 | C12: =IFERROR(INDEX($B:$B,MATCH(LARGE($J$41:$J$170,2),$J$41:$J$170,0)+40),"—") -> Consultancy (PG+PC Contract Fees) Income | D12: =IFERROR(INDEX($E:$E,MATCH(LARGE($J$41:$J$170,2),$J$41:$J$170,0)+40),"—") -> -376399.08 | E12: =IFERROR(INDEX($H:$H,MATCH(LARGE($J$41:$J$170,2),$J$41:$J$170,0)+40),"—") -> -2486538.7 | F12: =IFERROR(INDEX($I:$I,MATCH(LARGE($J$41:$J$170,2),$J$41:$J$170,0)+40),"—") -> -2110139.6
A13: 3 | B13: =IFERROR(INDEX($A:$A,MATCH(LARGE($J$41:$J$170,3),$J$41:$J$170,0)+40),"—") -> 6000 | C13: =IFERROR(INDEX($B:$B,MATCH(LARGE($J$41:$J$170,3),$J$41:$J$170,0)+40),"—") -> Technical - Salaries | D13: =IFERROR(INDEX($E:$E,MATCH(LARGE($J$41:$J$170,3),$J$41:$J$170,0)+40),"—") -> 1318800.1 | E13: =IFERROR(INDEX($H:$H,MATCH(LARGE($J$41:$J$170,3),$J$41:$J$170,0)+40),"—") -> 2684369.5 | F13: =IFERROR(INDEX($I:$I,MATCH(LARGE($J$41:$J$170,3),$J$41:$J$170,0)+40),"—") -> 1365569.4
A14: 4 | B14: =IFERROR(INDEX($A:$A,MATCH(LARGE($J$41:$J$170,4),$J$41:$J$170,0)+40),"—") -> 1185 | C14: =IFERROR(INDEX($B:$B,MATCH(LARGE($J$41:$J$170,4),$J$41:$J$170,0)+40),"—") -> INTER COMPANY-PIA- Proforest Initiative Africa (PIGH) | D14: =IFERROR(INDEX($E:$E,MATCH(LARGE($J$41:$J$170,4),$J$41:$J$170,0)+40),"—") -> -1180853.8 | E14: =IFERROR(INDEX($H:$H,MATCH(LARGE($J$41:$J$170,4),$J$41:$J$170,0)+40),"—") -> 0 | F14: =IFERROR(INDEX($I:$I,MATCH(LARGE($J$41:$J$170,4),$J$41:$J$170,0)+40),"—") -> 1180853.8
A15: 5 | B15: =IFERROR(INDEX($A:$A,MATCH(LARGE($J$41:$J$170,5),$J$41:$J$170,0)+40),"—") -> 1100 | C15: =IFERROR(INDEX($B:$B,MATCH(LARGE($J$41:$J$170,5),$J$41:$J$170,0)+40),"—") -> Debtors Control Account | D15: =IFERROR(INDEX($E:$E,MATCH(LARGE($J$41:$J$170,5),$J$41:$J$170,0)+40),"—") -> 4576083.2 | E15: =IFERROR(INDEX($H:$H,MATCH(LARGE($J$41:$J$170,5),$J$41:$J$170,0)+40),"—") -> 5632577.6 | F15: =IFERROR(INDEX($I:$I,MATCH(LARGE($J$41:$J$170,5),$J$41:$J$170,0)+40),"—") -> 1056494.5
A16: 6 | B16: =IFERROR(INDEX($A:$A,MATCH(LARGE($J$41:$J$170,6),$J$41:$J$170,0)+40),"—") -> 5200 | C16: =IFERROR(INDEX($B:$B,MATCH(LARGE($J$41:$J$170,6),$J$41:$J$170,0)+40),"—") -> Recoverable Project Expenses | D16: =IFERROR(INDEX($E:$E,MATCH(LARGE($J$41:$J$170,6),$J$41:$J$170,0)+40),"—") -> 151893.42 | E16: =IFERROR(INDEX($H:$H,MATCH(LARGE($J$41:$J$170,6),$J$41:$J$170,0)+40),"—") -> 968118.94 | F16: =IFERROR(INDEX($I:$I,MATCH(LARGE($J$41:$J$170,6),$J$41:$J$170,0)+40),"—") -> 816225.52
